Workbook

Sheet Inputs
A1: AVIATION LEASE CASH FLOW MODEL | Model Inputs & Assumptions
A2: Blue = Hardcoded Input | Black = Formula | Green = Cross-sheet Link | Yellow Background = Key Assumption
B4: SCENARIO & DEAL SELECTOR
B5: Active Deal (1=737, 2=A320) | C5: 1
B6: Scenario (1=Base, 2=Upside, 3=Downside) | C6: 1
B8: AIRCRAFT & DEAL ASSUMPTIONS
B9: Parameter | C9: Boeing 737-800 (Deal 1) | E9: Airbus A320neo (Deal 2)
B10: Aircraft Type | C10: Boeing 737-800 | F10: Airbus A320neo
B11: Manufacturer Serial No. | C11: MSN-28024 | F11: MSN-10458
B12: Year of Manufacture | C12: 2018 | F12: 2020
B13: Purchase Price ($) | C13: 72000000 | F13: 85000000
B14: Lease Rate Factor (monthly) | C14: 0.0078 | F14: 0.0082
B15: Monthly Lease Payment ($) | C15: =C14*C13 -> 561600 | F15: =F14*F13 -> 697000
B16: Lease Term (months) | C16: 120 | F16: 144
B17: Lease Start Date | C17: 2024-01-01 | F17: 2024-04-01
B18: Lessee Name | C18: Regional Air Inc. | F18: EuroFly S.A.
B19: Lessee Credit Rating | C19: BB+ | F19: BBB-
B22: DEBT FINANCING ASSUMPTIONS
B23: Parameter | C23: Deal 1 (737) | E23: Deal 2 (A320)
B24: LTV Ratio | C24: 0.75 | F24: 0.7
B25: Loan Amount ($) | C25: =C13*C24 -> 54000000 | F25: =F13*F24 -> 59500000
B26: Annual Interest Rate | C26: 0.055 | F26: 0.06
B27: Amortization Period (months) | C27: 120 | F27: 144
B28: Balloon Payment (% of orig.) | C28: 0.2 | F28: 0.15
B29: Loan Origination Fee (%) | C29: 0.01 | F29: 0.01
B30: DSCR Covenant Minimum | C30: 1.25 | F30: 1.2
B33: OPERATING COSTS & MAINTENANCE RESERVES (Annual)
B34: Cost Item | C34: Deal 1 (737) | E34: Deal 2 (A320)
B35: Servicer / Asset Mgmt Fee ($) | C35: 180000 | F35: 210000
B36: Insurance (Annual $) | C36: 120000 | F36: 140000
B37: Legal & Administrative ($) | C37: 40000 | F37: 50000
B38: Maintenance Reserve - Engine ($) | C38: 450000 | F38: 520000
B39: Maintenance Reserve - Airframe ($) | C39: 180000 | F39: 200000
B40: Other OpEx ($) | C40: 60000 | F40: 75000
B41: Annual Cost Escalation (%) | C41: 0.025 | F41: 0.025
B44: RESIDUAL VALUE & EXIT ASSUMPTIONS
B45: Parameter | C45: Deal 1 (737) | E45: Deal 2 (A320)
B46: Annual Depreciation Rate (%) | C46: 0.035 | F46: 0.03
B47: Base Residual Value ($) | C47: =C13*(1-C46)^(C16/12) -> 50420324 | F47: =F13*(1-F46)^(F16/12) -> 58976601
B48: Haircut to RV (Base %) | C48: 0.05 | F48: 0.05
B49: Haircut to RV (Downside %) | C49: 0.2 | F49: 0.2
B50: Haircut to RV (Upside %) | C50: 0 | F50: 0
B51: Re-Lease Period (months, if default) | C51: 6 | F51: 6
B52: Re-Lease Rate Factor (Base) | C52: 0.0065 | F52: 0.0068
B55: SCENARIO ADJUSTMENT FACTORS (Applied to Active Deal)
C56: Base | E56: Upside | G56: Downside
B57: Lease Rate Factor Adj. | C57: 1 | E57: 1.05 | G57: 0.85
B58: OpEx Adj. | C58: 1 | E58: 0.95 | G58: 1.15
B59: Residual Value Adj. | C59: 1 | E59: 1.1 | G59: 0.8
B60: Lessee Default (month #) | C60: 0 | E60: 0 | G60: 36
B61: Maintenance Shock ($) | C61: 0 | E61: 0 | G61: 500000
B64: ACTIVE SCENARIO LOOKUPS (Formula-Driven)
B65: Active: LRF Adj. | C65: =IF($C$6=1,C57,IF($C$6=2,E57,G57)) -> 1
B66: Active: OpEx Adj. | C66: =IF($C$6=1,C58,IF($C$6=2,E58,G58)) -> 1
B67: Active: RV Adj. | C67: =IF($C$6=1,C59,IF($C$6=2,E59,G59)) -> 1
B68: Active: Default Month | C68: =IF($C$6=1,C60,IF($C$6=2,E60,G60)) -> 0
B69: Active: Maint. Shock ($) | C69: =IF($C$6=1,C61,IF($C$6=2,E61,G61)) -> 0
B71: Active: Purchase Price ($) | C71: =IF($C$5=1,C13,F13) -> 72000000
B72: Active: LRF (adj.) | C72: =IF($C$5=1,C14,F14)*C65 -> 0.0078
B73: Active: Monthly Lease Pmt ($) | C73: =C71*C72 -> 561600
B74: Active: Lease Term (months) | C74: =IF($C$5=1,C16,F16) -> 120
B75: Active: LTV Ratio | C75: =IF($C$5=1,C24,F24) -> 0.75
B76: Active: Loan Amount ($) | C76: =C71*C75 -> 54000000
B77: Active: Interest Rate (Annual) | C77: =IF($C$5=1,C26,F26) -> 0.055
B78: Active: Amort. Period (months) | C78: =IF($C$5=1,C27,F27) -> 120
B79: Active: Balloon % of Orig. | C79: =IF($C$5=1,C28,F28) -> 0.2
B80: Active: Annual Depr. Rate | C80: =IF($C$5=1,C46,F46) -> 0.035
B81: Active: RV Haircut (scenario adj.) | C81: =IF($C$5=1,IF($C$6=1,C48,IF($C$6=2,C50,C49)),IF($C$6=1,F48,IF($C$6=2,F50,F49))) -> 0.05
B82: Active: Total Annual OpEx ($) adj. | C82: =IF($C$5=1,SUM(C35:C40),SUM(F35:F40))*C66 -> 1030000
B83: Active: OpEx Escalation (%) | C83: =IF($C$5=1,C41,F41) -> 0.025
B84: Active: DSCR Covenant Min. | C84: =IF($C$5=1,C30,F30) -> 1.25
B85: Active: Re-Lease Period (months) | C85: =IF($C$5=1,C51,F51) -> 6
B86: Active: Re-Lease Rate Factor | C86: =IF($C$5=1,C52,F52) -> 0.0065
B87: Active: Origination Fee (%) | C87: =IF($C$5=1,C29,F29) -> 0.01

Sheet Debt Schedule
A1: AVIATION LEASE CASH FLOW MODEL | Debt Amortization Schedule
B3: Loan Amount | D3: Interest Rate (Annual) | F3: Amort. Period (mo) | H3: Balloon % | J3: Origination Fee
B4: =Inputs!C76 -> 54000000 | D4: =Inputs!C77 -> 0.055 | F4: =Inputs!C78 -> 120 | H4: =Inputs!C79 -> 0.2 | J4: =Inputs!C87 -> 0.01
B6: Balloon Amount ($) | C6: =Inputs!C76*Inputs!C79 -> 10800000
B7: Monthly Interest Rate | C7: =Inputs!C77/12 -> 0.0045833333
B8: Monthly P&I Payment ($) | C8: =IFERROR(PMT(C7,Inputs!C78,-(Inputs!C76-C6),-C6,0),0) -> 536541.9
B9: Origination Fee ($) | C9: =Inputs!C76*Inputs!C87 -> 540000
B11: Month | C11: Date | D11: Beg. Balance ($) | E11: Scheduled P&I ($) | F11: Interest ($) | G11: Principal ($) | H11: Balloon ($) | I11: Total Debt Svc ($) | J11: End Balance ($) | K11: LTV %
B12: 0 | C12: =DATE(2024,1,1) -> 45292 | D12: =Inputs!C76 -> 54000000 | E12: 0 | F12: 0 | G12: 0 | H12: 0 | I12: 0 | J12: 0 | K12: 0
B13: 1 | C13: =EDATE($C$12,1) -> 45323 | D13: =IF(1>Inputs!$C$78,0,D12) -> 54000000 | E13: =IF(D13=0,0,MIN($C$8,D13+F13)) -> 536541.9 | F13: =IF(D13=0,0,D13*$C$7) -> 247500 | G13: =IF(D13=0,0,E13-F13) -> 289041.9 | H13: =IF(1=Inputs!$C$78,$C$6,0) -> 0 | I13: =IF(D13=0,0,E13+H13) -> 536541.9 | J13: =IF(D13=0,0,MAX(0,D13-G13-H13)) -> 53710958 | K13: =IF(D13=0,0,I13/Inputs!$C$71*(1-Inputs!$C$80)^(1/12)) -> 0.0074298793
B14: 2 | C14: =EDATE($C$12,2) -> 45352 | D14: =IF(2>Inputs!$C$78,0,J13) -> 53710958 | E14: =IF(D14=0,0,MIN($C$8,D14+F14)) -> 536541.9 | F14: =IF(D14=0,0,D14*$C$7) -> 246175.22 | G14: =IF(D14=0,0,E14-F14) -> 290366.68 | H14: =IF(2=Inputs!$C$78,$C$6,0) -> 0 | I14: =IF(D14=0,0,E14+H14) -> 536541.9 | J14: =IF(D14=0,0,MAX(0,D14-G14-H14)) -> 53420591 | K14: =IF(D14=0,0,I14/Inputs!$C$71*(1-Inputs!$C$80)^(2/12)) -> 0.0074078532
B15: 3 | C15: =EDATE($C$12,3) -> 45383 | D15: =IF(3>Inputs!$C$78,0,J14) -> 53420591 | E15: =IF(D15=0,0,MIN($C$8,D15+F15)) -> 536541.9 | F15: =IF(D15=0,0,D15*$C$7) -> 244844.38 | G15: =IF(D15=0,0,E15-F15) -> 291697.52 | H15: =IF(3=Inputs!$C$78,$C$6,0) -> 0 | I15: =IF(D15=0,0,E15+H15) -> 536541.9 | J15: =IF(D15=0,0,MAX(0,D15-G15-H15)) -> 53128894 | K15: =IF(D15=0,0,I15/Inputs!$C$71*(1-Inputs!$C$80)^(3/12)) -> 0.0073858924
B16: 4 | C16: =EDATE($C$12,4) -> 45413 | D16: =IF(4>Inputs!$C$78,0,J15) -> 53128894 | E16: =IF(D16=0,0,MIN($C$8,D16+F16)) -> 536541.9 | F16: =IF(D16=0,0,D16*$C$7) -> 243507.43 | G16: =IF(D16=0,0,E16-F16) -> 293034.47 | H16: =IF(4=Inputs!$C$78,$C$6,0) -> 0 | I16: =IF(D16=0,0,E16+H16) -> 536541.9 | J16: =IF(D16=0,0,MAX(0,D16-G16-H16)) -> 52835859 | K16: =IF(D16=0,0,I16/Inputs!$C$71*(1-Inputs!$C$80)^(4/12)) -> 0.0073639967
B17: 5 | C17: =EDATE($C$12,5) -> 45444 | D17: =IF(5>Inputs!$C$78,0,J16) -> 52835859 | E17: =IF(D17=0,0,MIN($C$8,D17+F17)) -> 536541.9 | F17: =IF(D17=0,0,D17*$C$7) -> 242164.36 | G17: =IF(D17=0,0,E17-F17) -> 294377.55 | H17: =IF(5=Inputs!$C$78,$C$6,0) -> 0 | I17: =IF(D17=0,0,E17+H17) -> 536541.9 | J17: =IF(D17=0,0,MAX(0,D17-G17-H17)) -> 52541482 | K17: =IF(D17=0,0,I17/Inputs!$C$71*(1-Inputs!$C$80)^(5/12)) -> 0.0073421659
B18: 6 | C18: =EDATE($C$12,6) -> 45474 | D18: =IF(6>Inputs!$C$78,0,J17) -> 52541482 | E18: =IF(D18=0,0,MIN($C$8,D18+F18)) -> 536541.9 | F18: =IF(D18=0,0,D18*$C$7) -> 240815.13 | G18: =IF(D18=0,0,E18-F18) -> 295726.78 | H18: =IF(6=Inputs!$C$78,$C$6,0) -> 0 | I18: =IF(D18=0,0,E18+H18) -> 536541.9 | J18: =IF(D18=0,0,MAX(0,D18-G18-H18)) -> 52245755 | K18: =IF(D18=0,0,I18/Inputs!$C$71*(1-Inputs!$C$80)^(6/12)) -> 0.0073203999
B19: 7 | C19: =EDATE($C$12,7) -> 45505 | D19: =IF(7>Inputs!$C$78,0,J18) -> 52245755 | E19: =IF(D19=0,0,MIN($C$8,D19+F19)) -> 536541.9 | F19: =IF(D19=0,0,D19*$C$7) -> 239459.71 | G19: =IF(D19=0,0,E19-F19) -> 297082.19 | H19: =IF(7=Inputs!$C$78,$C$6,0) -> 0 | I19: =IF(D19=0,0,E19+H19) -> 536541.9 | J19: =IF(D19=0,0,MAX(0,D19-G19-H19)) -> 51948673 | K19: =IF(D19=0,0,I19/Inputs!$C$71*(1-Inputs!$C$80)^(7/12)) -> 0.0072986983
B20: 8 | C20: =EDATE($C$12,8) -> 45536 | D20: =IF(8>Inputs!$C$78,0,J19) -> 51948673 | E20: =IF(D20=0,0,MIN($C$8,D20+F20)) -> 536541.9 | F20: =IF(D20=0,0,D20*$C$7) -> 238098.08 | G20: =IF(D20=0,0,E20-F20) -> 298443.82 | H20: =IF(8=Inputs!$C$78,$C$6,0) -> 0 | I20: =IF(D20=0,0,E20+H20) -> 536541.9 | J20: =IF(D20=0,0,MAX(0,D20-G20-H20)) -> 51650229 | K20: =IF(D20=0,0,I20/Inputs!$C$71*(1-Inputs!$C$80)^(8/12)) -> 0.0072770611
B21: 9 | C21: =EDATE($C$12,9) -> 45566 | D21: =IF(9>Inputs!$C$78,0,J20) -> 51650229 | E21: =IF(D21=0,0,MIN($C$8,D21+F21)) -> 536541.9 | F21: =IF(D21=0,0,D21*$C$7) -> 236730.22 | G21: =IF(D21=0,0,E21-F21) -> 299811.68 | H21: =IF(9=Inputs!$C$78,$C$6,0) -> 0 | I21: =IF(D21=0,0,E21+H21) -> 536541.9 | J21: =IF(D21=0,0,MAX(0,D21-G21-H21)) -> 51350417 | K21: =IF(D21=0,0,I21/Inputs!$C$71*(1-Inputs!$C$80)^(9/12)) -> 0.0072554881
B22: 10 | C22: =EDATE($C$12,10) -> 45597 | D22: =IF(10>Inputs!$C$78,0,J21) -> 51350417 | E22: =IF(D22=0,0,MIN($C$8,D22+F22)) -> 536541.9 | F22: =IF(D22=0,0,D22*$C$7) -> 235356.08 | G22: =IF(D22=0,0,E22-F22) -> 301185.82 | H22: =IF(10=Inputs!$C$78,$C$6,0) -> 0 | I22: =IF(D22=0,0,E22+H22) -> 536541.9 | J22: =IF(D22=0,0,MAX(0,D22-G22-H22)) -> 51049232 | K22: =IF(D22=0,0,I22/Inputs!$C$71*(1-Inputs!$C$80)^(10/12)) -> 0.007233979
B23: 11 | C23: =EDATE($C$12,11) -> 45627 | D23: =IF(11>Inputs!$C$78,0,J22) -> 51049232 | E23: =IF(D23=0,0,MIN($C$8,D23+F23)) -> 536541.9 | F23: =IF(D23=0,0,D23*$C$7) -> 233975.64 | G23: =IF(D23=0,0,E23-F23) -> 302566.26 | H23: =IF(11=Inputs!$C$78,$C$6,0) -> 0 | I23: =IF(D23=0,0,E23+H23) -> 536541.9 | J23: =IF(D23=0,0,MAX(0,D23-G23-H23)) -> 50746665 | K23: =IF(D23=0,0,I23/Inputs!$C$71*(1-Inputs!$C$80)^(11/12)) -> 0.0072125336
B24: 12 | C24: =EDATE($C$12,12) -> 45658 | D24: =IF(12>Inputs!$C$78,0,J23) -> 50746665 | E24: =IF(D24=0,0,MIN($C$8,D24+F24)) -> 536541.9 | F24: =IF(D24=0,0,D24*$C$7) -> 232588.88 | G24: =IF(D24=0,0,E24-F24) -> 303953.02 | H24: =IF(12=Inputs!$C$78,$C$6,0) -> 0 | I24: =IF(D24=0,0,E24+H24) -> 536541.9 | J24: =IF(D24=0,0,MAX(0,D24-G24-H24)) -> 50442712 | K24: =IF(D24=0,0,I24/Inputs!$C$71*(1-Inputs!$C$80)^(12/12)) -> 0.0071911519
B25: 13 | C25: =EDATE($C$12,13) -> 45689 | D25: =IF(13>Inputs!$C$78,0,J24) -> 50442712 | E25: =IF(D25=0,0,MIN($C$8,D25+F25)) -> 536541.9 | F25: =IF(D25=0,0,D25*$C$7) -> 231195.76 | G25: =IF(D25=0,0,E25-F25) -> 305346.14 | H25: =IF(13=Inputs!$C$78,$C$6,0) -> 0 | I25: =IF(D25=0,0,E25+H25) -> 536541.9 | J25: =IF(D25=0,0,MAX(0,D25-G25-H25)) -> 50137366 | K25: =IF(D25=0,0,I25/Inputs!$C$71*(1-Inputs!$C$80)^(13/12)) -> 0.0071698335
B26: 14 | C26: =EDATE($C$12,14) -> 45717 | D26: =IF(14>Inputs!$C$78,0,J25) -> 50137366 | E26: =IF(D26=0,0,MIN($C$8,D26+F26)) -> 536541.9 | F26: =IF(D26=0,0,D26*$C$7) -> 229796.26 | G26: =IF(D26=0,0,E26-F26) -> 306745.64 | H26: =IF(14=Inputs!$C$78,$C$6,0) -> 0 | I26: =IF(D26=0,0,E26+H26) -> 536541.9 | J26: =IF(D26=0,0,MAX(0,D26-G26-H26)) -> 49830621 | K26: =IF(D26=0,0,I26/Inputs!$C$71*(1-Inputs!$C$80)^(14/12)) -> 0.0071485783
B27: 15 | C27: =EDATE($C$12,15) -> 45748 | D27: =IF(15>Inputs!$C$78,0,J26) -> 49830621 | E27: =IF(D27=0,0,MIN($C$8,D27+F27)) -> 536541.9 | F27: =IF(D27=0,0,D27*$C$7) -> 228390.34 | G27: =IF(D27=0,0,E27-F27) -> 308151.56 | H27: =IF(15=Inputs!$C$78,$C$6,0) -> 0 | I27: =IF(D27=0,0,E27+H27) -> 536541.9 | J27: =IF(D27=0,0,MAX(0,D27-G27-H27)) -> 49522469 | K27: =IF(D27=0,0,I27/Inputs!$C$71*(1-Inputs!$C$80)^(15/12)) -> 0.0071273862
B28: 16 | C28: =EDATE($C$12,16) -> 45778 | D28: =IF(16>Inputs!$C$78,0,J27) -> 49522469 | E28: =IF(D28=0,0,MIN($C$8,D28+F28)) -> 536541.9 | F28: =IF(D28=0,0,D28*$C$7) -> 226977.98 | G28: =IF(D28=0,0,E28-F28) -> 309563.92 | H28: =IF(16=Inputs!$C$78,$C$6,0) -> 0 | I28: =IF(D28=0,0,E28+H28) -> 536541.9 | J28: =IF(D28=0,0,MAX(0,D28-G28-H28)) -> 49212905 | K28: =IF(D28=0,0,I28/Inputs!$C$71*(1-Inputs!$C$80)^(16/12)) -> 0.0071062568
B29: 17 | C29: =EDATE($C$12,17) -> 45809 | D29: =IF(17>Inputs!$C$78,0,J28) -> 49212905 | E29: =IF(D29=0,0,MIN($C$8,D29+F29)) -> 536541.9 | F29: =IF(D29=0,0,D29*$C$7) -> 225559.15 | G29: =IF(D29=0,0,E29-F29) -> 310982.75 | H29: =IF(17=Inputs!$C$78,$C$6,0) -> 0 | I29: =IF(D29=0,0,E29+H29) -> 536541.9 | J29: =IF(D29=0,0,MAX(0,D29-G29-H29)) -> 48901922 | K29: =IF(D29=0,0,I29/Inputs!$C$71*(1-Inputs!$C$80)^(17/12)) -> 0.0070851901
B30: 18 | C30: =EDATE($C$12,18) -> 45839 | D30: =IF(18>Inputs!$C$78,0,J29) -> 48901922 | E30: =IF(D30=0,0,MIN($C$8,D30+F30)) -> 536541.9 | F30: =IF(D30=0,0,D30*$C$7) -> 224133.81 | G30: =IF(D30=0,0,E30-F30) -> 312408.09 | H30: =IF(18=Inputs!$C$78,$C$6,0) -> 0 | I30: =IF(D30=0,0,E30+H30) -> 536541.9 | J30: =IF(D30=0,0,MAX(0,D30-G30-H30)) -> 48589514 | K30: =IF(D30=0,0,I30/Inputs!$C$71*(1-Inputs!$C$80)^(18/12)) -> 0.0070641859
B31: 19 | C31: =EDATE($C$12,19) -> 45870 | D31: =IF(19>Inputs!$C$78,0,J30) -> 48589514 | E31: =IF(D31=0,0,MIN($C$8,D31+F31)) -> 536541.9 | F31: =IF(D31=0,0,D31*$C$7) -> 222701.94 | G31: =IF(D31=0,0,E31-F31) -> 313839.96 | H31: =IF(19=Inputs!$C$78,$C$6,0) -> 0 | I31: =IF(D31=0,0,E31+H31) -> 536541.9 | J31: =IF(D31=0,0,MAX(0,D31-G31-H31)) -> 48275674 | K31: =IF(D31=0,0,I31/Inputs!$C$71*(1-Inputs!$C$80)^(19/12)) -> 0.0070432439
B32: 20 | C32: =EDATE($C$12,20) -> 45901 | D32: =IF(20>Inputs!$C$78,0,J31) -> 48275674 | E32: =IF(D32=0,0,MIN($C$8,D32+F32)) -> 536541.9 | F32: =IF(D32=0,0,D32*$C$7) -> 221263.51 | G32: =IF(D32=0,0,E32-F32) -> 315278.39 | H32: =IF(20=Inputs!$C$78,$C$6,0) -> 0 | I32: =IF(D32=0,0,E32+H32) -> 536541.9 | J32: =IF(D32=0,0,MAX(0,D32-G32-H32)) -> 47960396 | K32: =IF(D32=0,0,I32/Inputs!$C$71*(1-Inputs!$C$80)^(20/12)) -> 0.007022364
B33: 21 | C33: =EDATE($C$12,21) -> 45931 | D33: =IF(21>Inputs!$C$78,0,J32) -> 47960396 | E33: =IF(D33=0,0,MIN($C$8,D33+F33)) -> 536541.9 | F33: =IF(D33=0,0,D33*$C$7) -> 219818.48 | G33: =IF(D33=0,0,E33-F33) -> 316723.42 | H33: =IF(21=Inputs!$C$78,$C$6,0) -> 0 | I33: =IF(D33=0,0,E33+H33) -> 536541.9 | J33: =IF(D33=0,0,MAX(0,D33-G33-H33)) -> 47643672 | K33: =IF(D33=0,0,I33/Inputs!$C$71*(1-Inputs!$C$80)^(21/12)) -> 0.007001546
B34: 22 | C34: =EDATE($C$12,22) -> 45962 | D34: =IF(22>Inputs!$C$78,0,J33) -> 47643672 | E34: =IF(D34=0,0,MIN($C$8,D34+F34)) -> 536541.9 | F34: =IF(D34=0,0,D34*$C$7) -> 218366.83 | G34: =IF(D34=0,0,E34-F34) -> 318175.07 | H34: =IF(22=Inputs!$C$78,$C$6,0) -> 0 | I34: =IF(D34=0,0,E34+H34) -> 536541.9 | J34: =IF(D34=0,0,MAX(0,D34-G34-H34)) -> 47325497 | K34: =IF(D34=0,0,I34/Inputs!$C$71*(1-Inputs!$C$80)^(22/12)) -> 0.0069807897
B35: 23 | C35: =EDATE($C$12,23) -> 45992 | D35: =IF(23>Inputs!$C$78,0,J34) -> 47325497 | E35: =IF(D35=0,0,MIN($C$8,D35+F35)) -> 536541.9 | F35: =IF(D35=0,0,D35*$C$7) -> 216908.53 | G35: =IF(D35=0,0,E35-F35) -> 319633.37 | H35: =IF(23=Inputs!$C$78,$C$6,0) -> 0 | I35: =IF(D35=0,0,E35+H35) -> 536541.9 | J35: =IF(D35=0,0,MAX(0,D35-G35-H35)) -> 47005864 | K35: =IF(D35=0,0,I35/Inputs!$C$71*(1-Inputs!$C$80)^(23/12)) -> 0.006960095
B36: 24 | C36: =EDATE($C$12,24) -> 46023 | D36: =IF(24>Inputs!$C$78,0,J35) -> 47005864 | E36: =IF(D36=0,0,MIN($C$8,D36+F36)) -> 536541.9 | F36: =IF(D36=0,0,D36*$C$7) -> 215443.54 | G36: =IF(D36=0,0,E36-F36) -> 321098.36 | H36: =IF(24=Inputs!$C$78,$C$6,0) -> 0 | I36: =IF(D36=0,0,E36+H36) -> 536541.9 | J36: =IF(D36=0,0,MAX(0,D36-G36-H36)) -> 46684766 | K36: =IF(D36=0,0,I36/Inputs!$C$71*(1-Inputs!$C$80)^(24/12)) -> 0.0069394616
B37: 25 | C37: =EDATE($C$12,25) -> 46054 | D37: =IF(25>Inputs!$C$78,0,J36) -> 46684766 | E37: =IF(D37=0,0,MIN($C$8,D37+F37)) -> 536541.9 | F37: =IF(D37=0,0,D37*$C$7) -> 213971.84 | G37: =IF(D37=0,0,E37-F37) -> 322570.06 | H37: =IF(25=Inputs!$C$78,$C$6,0) -> 0 | I37: =IF(D37=0,0,E37+H37) -> 536541.9 | J37: =IF(D37=0,0,MAX(0,D37-G37-H37)) -> 46362196 | K37: =IF(D37=0,0,I37/Inputs!$C$71*(1-Inputs!$C$80)^(25/12)) -> 0.0069188893
B38: 26 | C38: =EDATE($C$12,26) -> 46082 | D38: =IF(26>Inputs!$C$78,0,J37) -> 46362196 | E38: =IF(D38=0,0,MIN($C$8,D38+F38)) -> 536541.9 | F38: =IF(D38=0,0,D38*$C$7) -> 212493.4 | G38: =IF(D38=0,0,E38-F38) -> 324048.5 | H38: =IF(26=Inputs!$C$78,$C$6,0) -> 0 | I38: =IF(D38=0,0,E38+H38) -> 536541.9 | J38: =IF(D38=0,0,MAX(0,D38-G38-H38)) -> 46038147 | K38: =IF(D38=0,0,I38/Inputs!$C$71*(1-Inputs!$C$80)^(26/12)) -> 0.0068983781
B39: 27 | C39: =EDATE($C$12,27) -> 46113 | D39: =IF(27>Inputs!$C$78,0,J38) -> 46038147 | E39: =IF(D39=0,0,MIN($C$8,D39+F39)) -> 536541.9 | F39: =IF(D39=0,0,D39*$C$7) -> 211008.17 | G39: =IF(D39=0,0,E39-F39) -> 325533.73 | H39: =IF(27=Inputs!$C$78,$C$6,0) -> 0 | I39: =IF(D39=0,0,E39+H39) -> 536541.9 | J39: =IF(D39=0,0,MAX(0,D39-G39-H39)) -> 45712613 | K39: =IF(D39=0,0,I39/Inputs!$C$71*(1-Inputs!$C$80)^(27/12)) -> 0.0068779276
B40: 28 | C40: =EDATE($C$12,28) -> 46143 | D40: =IF(28>Inputs!$C$78,0,J39) -> 45712613 | E40: =IF(D40=0,0,MIN($C$8,D40+F40)) -> 536541.9 | F40: =IF(D40=0,0,D40*$C$7) -> 209516.14 | G40: =IF(D40=0,0,E40-F40) -> 327025.76 | H40: =IF(28=Inputs!$C$78,$C$6,0) -> 0 | I40: =IF(D40=0,0,E40+H40) -> 536541.9 | J40: =IF(D40=0,0,MAX(0,D40-G40-H40)) -> 45385588 | K40: =IF(D40=0,0,I40/Inputs!$C$71*(1-Inputs!$C$80)^(28/12)) -> 0.0068575378
B41: 29 | C41: =EDATE($C$12,29) -> 46174 | D41: =IF(29>Inputs!$C$78,0,J40) -> 45385588 | E41: =IF(D41=0,0,MIN($C$8,D41+F41)) -> 536541.9 | F41: =IF(D41=0,0,D41*$C$7) -> 208017.28 | G41: =IF(D41=0,0,E41-F41) -> 328524.62 | H41: =IF(29=Inputs!$C$78,$C$6,0) -> 0 | I41: =IF(D41=0,0,E41+H41) -> 536541.9 | J41: =IF(D41=0,0,MAX(0,D41-G41-H41)) -> 45057063 | K41: =IF(D41=0,0,I41/Inputs!$C$71*(1-Inputs!$C$80)^(29/12)) -> 0.0068372085
B42: 30 | C42: =EDATE($C$12,30) -> 46204 | D42: =IF(30>Inputs!$C$78,0,J41) -> 45057063 | E42: =IF(D42=0,0,MIN($C$8,D42+F42)) -> 536541.9 | F42: =IF(D42=0,0,D42*$C$7) -> 206511.54 | G42: =IF(D42=0,0,E42-F42) -> 330030.36 | H42: =IF(30=Inputs!$C$78,$C$6,0) -> 0 | I42: =IF(D42=0,0,E42+H42) -> 536541.9 | J42: =IF(D42=0,0,MAX(0,D42-G42-H42)) -> 44727033 | K42: =IF(D42=0,0,I42/Inputs!$C$71*(1-Inputs!$C$80)^(30/12)) -> 0.0068169394
B43: 31 | C43: =EDATE($C$12,31) -> 46235 | D43: =IF(31>Inputs!$C$78,0,J42) -> 44727033 | E43: =IF(D43=0,0,MIN($C$8,D43+F43)) -> 536541.9 | F43: =IF(D43=0,0,D43*$C$7) -> 204998.9 | G43: =IF(D43=0,0,E43-F43) -> 331543 | H43: =IF(31=Inputs!$C$78,$C$6,0) -> 0 | I43: =IF(D43=0,0,E43+H43) -> 536541.9 | J43: =IF(D43=0,0,MAX(0,D43-G43-H43)) -> 44395490 | K43: =IF(D43=0,0,I43/Inputs!$C$71*(1-Inputs!$C$80)^(31/12)) -> 0.0067967303
B44: 32 | C44: =EDATE($C$12,32) -> 46266 | D44: =IF(32>Inputs!$C$78,0,J43) -> 44395490 | E44: =IF(D44=0,0,MIN($C$8,D44+F44)) -> 536541.9 | F44: =IF(D44=0,0,D44*$C$7) -> 203479.33 | G44: =IF(D44=0,0,E44-F44) -> 333062.57 | H44: =IF(32=Inputs!$C$78,$C$6,0) -> 0 | I44: =IF(D44=0,0,E44+H44) -> 536541.9 | J44: =IF(D44=0,0,MAX(0,D44-G44-H44)) -> 44062427 | K44: =IF(D44=0,0,I44/Inputs!$C$71*(1-Inputs!$C$80)^(32/12)) -> 0.0067765812
B45: 33 | C45: =EDATE($C$12,33) -> 46296 | D45: =IF(33>Inputs!$C$78,0,J44) -> 44062427 | E45: =IF(D45=0,0,MIN($C$8,D45+F45)) -> 536541.9 | F45: =IF(D45=0,0,D45*$C$7) -> 201952.79 | G45: =IF(D45=0,0,E45-F45) -> 334589.11 | H45: =IF(33=Inputs!$C$78,$C$6,0) -> 0 | I45: =IF(D45=0,0,E45+H45) -> 536541.9 | J45: =IF(D45=0,0,MAX(0,D45-G45-H45)) -> 43727838 | K45: =IF(D45=0,0,I45/Inputs!$C$71*(1-Inputs!$C$80)^(33/12)) -> 0.0067564919
B46: 34 | C46: =EDATE($C$12,34) -> 46327 | D46: =IF(34>Inputs!$C$78,0,J45) -> 43727838 | E46: =IF(D46=0,0,MIN($C$8,D46+F46)) -> 536541.9 | F46: =IF(D46=0,0,D46*$C$7) -> 200419.26 | G46: =IF(D46=0,0,E46-F46) -> 336122.64 | H46: =IF(34=Inputs!$C$78,$C$6,0) -> 0 | I46: =IF(D46=0,0,E46+H46) -> 536541.9 | J46: =IF(D46=0,0,MAX(0,D46-G46-H46)) -> 43391715 | K46: =IF(D46=0,0,I46/Inputs!$C$71*(1-Inputs!$C$80)^(34/12)) -> 0.0067364621
B47: 35 | C47: =EDATE($C$12,35) -> 46357 | D47: =IF(35>Inputs!$C$78,0,J46) -> 43391715 | E47: =IF(D47=0,0,MIN($C$8,D47+F47)) -> 536541.9 | F47: =IF(D47=0,0,D47*$C$7) -> 198878.7 | G47: =IF(D47=0,0,E47-F47) -> 337663.21 | H47: =IF(35=Inputs!$C$78,$C$6,0) -> 0 | I47: =IF(D47=0,0,E47+H47) -> 536541.9 | J47: =IF(D47=0,0,MAX(0,D47-G47-H47)) -> 43054052 | K47: =IF(D47=0,0,I47/Inputs!$C$71*(1-Inputs!$C$80)^(35/12)) -> 0.0067164916
B48: 36 | C48: =EDATE($C$12,36) -> 46388 | D48: =IF(36>Inputs!$C$78,0,J47) -> 43054052 | E48: =IF(D48=0,0,MIN($C$8,D48+F48)) -> 536541.9 | F48: =IF(D48=0,0,D48*$C$7) -> 197331.07 | G48: =IF(D48=0,0,E48-F48) -> 339210.83 | H48: =IF(36=Inputs!$C$78,$C$6,0) -> 0 | I48: =IF(D48=0,0,E48+H48) -> 536541.9 | J48: =IF(D48=0,0,MAX(0,D48-G48-H48)) -> 42714841 | K48: =IF(D48=0,0,I48/Inputs!$C$71*(1-Inputs!$C$80)^(36/12)) -> 0.0066965804
B49: 37 | C49: =EDATE($C$12,37) -> 46419 | D49: =IF(37>Inputs!$C$78,0,J48) -> 42714841 | E49: =IF(D49=0,0,MIN($C$8,D49+F49)) -> 536541.9 | F49: =IF(D49=0,0,D49*$C$7) -> 195776.36 | G49: =IF(D49=0,0,E49-F49) -> 340765.55 | H49: =IF(37=Inputs!$C$78,$C$6,0) -> 0 | I49: =IF(D49=0,0,E49+H49) -> 536541.9 | J49: =IF(D49=0,0,MAX(0,D49-G49-H49)) -> 42374076 | K49: =IF(D49=0,0,I49/Inputs!$C$71*(1-Inputs!$C$80)^(37/12)) -> 0.0066767282
B50: 38 | C50: =EDATE($C$12,38) -> 46447 | D50: =IF(38>Inputs!$C$78,0,J49) -> 42374076 | E50: =IF(D50=0,0,MIN($C$8,D50+F50)) -> 536541.9 | F50: =IF(D50=0,0,D50*$C$7) -> 194214.51 | G50: =IF(D50=0,0,E50-F50) -> 342327.39 | H50: =IF(38=Inputs!$C$78,$C$6,0) -> 0 | I50: =IF(D50=0,0,E50+H50) -> 536541.9 | J50: =IF(D50=0,0,MAX(0,D50-G50-H50)) -> 42031748 | K50: =IF(D50=0,0,I50/Inputs!$C$71*(1-Inputs!$C$80)^(38/12)) -> 0.0066569348
B51: 39 | C51: =EDATE($C$12,39) -> 46478 | D51: =IF(39>Inputs!$C$78,0,J50) -> 42031748 | E51: =IF(D51=0,0,MIN($C$8,D51+F51)) -> 536541.9 | F51: =IF(D51=0,0,D51*$C$7) -> 192645.51 | G51: =IF(D51=0,0,E51-F51) -> 343896.39 | H51: =IF(39=Inputs!$C$78,$C$6,0) -> 0 | I51: =IF(D51=0,0,E51+H51) -> 536541.9 | J51: =IF(D51=0,0,MAX(0,D51-G51-H51)) -> 41687852 | K51: =IF(D51=0,0,I51/Inputs!$C$71*(1-Inputs!$C$80)^(39/12)) -> 0.0066372002
B52: 40 | C52: =EDATE($C$12,40) -> 46508 | D52: =IF(40>Inputs!$C$78,0,J51) -> 41687852 | E52: =IF(D52=0,0,MIN($C$8,D52+F52)) -> 536541.9 | F52: =IF(D52=0,0,D52*$C$7) -> 191069.32 | G52: =IF(D52=0,0,E52-F52) -> 345472.58 | H52: =IF(40=Inputs!$C$78,$C$6,0) -> 0 | I52: =IF(D52=0,0,E52+H52) -> 536541.9 | J52: =IF(D52=0,0,MAX(0,D52-G52-H52)) -> 41342379 | K52: =IF(D52=0,0,I52/Inputs!$C$71*(1-Inputs!$C$80)^(40/12)) -> 0.006617524
B53: 41 | C53: =EDATE($C$12,41) -> 46539 | D53: =IF(41>Inputs!$C$78,0,J52) -> 41342379 | E53: =IF(D53=0,0,MIN($C$8,D53+F53)) -> 536541.9 | F53: =IF(D53=0,0,D53*$C$7) -> 189485.91 | G53: =IF(D53=0,0,E53-F53) -> 347056 | H53: =IF(41=Inputs!$C$78,$C$6,0) -> 0 | I53: =IF(D53=0,0,E53+H53) -> 536541.9 | J53: =IF(D53=0,0,MAX(0,D53-G53-H53)) -> 40995323 | K53: =IF(D53=0,0,I53/Inputs!$C$71*(1-Inputs!$C$80)^(41/12)) -> 0.0065979062
B54: 42 | C54: =EDATE($C$12,42) -> 46569 | D54: =IF(42>Inputs!$C$78,0,J53) -> 40995323 | E54: =IF(D54=0,0,MIN($C$8,D54+F54)) -> 536541.9 | F54: =IF(D54=0,0,D54*$C$7) -> 187895.23 | G54: =IF(D54=0,0,E54-F54) -> 348646.67 | H54: =IF(42=Inputs!$C$78,$C$6,0) -> 0 | I54: =IF(D54=0,0,E54+H54) -> 536541.9 | J54: =IF(D54=0,0,MAX(0,D54-G54-H54)) -> 40646677 | K54: =IF(D54=0,0,I54/Inputs!$C$71*(1-Inputs!$C$80)^(42/12)) -> 0.0065783465
B55: 43 | C55: =EDATE($C$12,43) -> 46600 | D55: =IF(43>Inputs!$C$78,0,J54) -> 40646677 | E55: =IF(D55=0,0,MIN($C$8,D55+F55)) -> 536541.9 | F55: =IF(D55=0,0,D55*$C$7) -> 186297.27 | G55: =IF(D55=0,0,E55-F55) -> 350244.63 | H55: =IF(43=Inputs!$C$78,$C$6,0) -> 0 | I55: =IF(D55=0,0,E55+H55) -> 536541.9 | J55: =IF(D55=0,0,MAX(0,D55-G55-H55)) -> 40296432 | K55: =IF(D55=0,0,I55/Inputs!$C$71*(1-Inputs!$C$80)^(43/12)) -> 0.0065588448
B56: 44 | C56: =EDATE($C$12,44) -> 46631 | D56: =IF(44>Inputs!$C$78,0,J55) -> 40296432 | E56: =IF(D56=0,0,MIN($C$8,D56+F56)) -> 536541.9 | F56: =IF(D56=0,0,D56*$C$7) -> 184691.98 | G56: =IF(D56=0,0,E56-F56) -> 351849.92 | H56: =IF(44=Inputs!$C$78,$C$6,0) -> 0 | I56: =IF(D56=0,0,E56+H56) -> 536541.9 | J56: =IF(D56=0,0,MAX(0,D56-G56-H56)) -> 39944582 | K56: =IF(D56=0,0,I56/Inputs!$C$71*(1-Inputs!$C$80)^(44/12)) -> 0.0065394009
B57: 45 | C57: =EDATE($C$12,45) -> 46661 | D57: =IF(45>Inputs!$C$78,0,J56) -> 39944582 | E57: =IF(D57=0,0,MIN($C$8,D57+F57)) -> 536541.9 | F57: =IF(D57=0,0,D57*$C$7) -> 183079.33 | G57: =IF(D57=0,0,E57-F57) -> 353462.57 | H57: =IF(45=Inputs!$C$78,$C$6,0) -> 0 | I57: =IF(D57=0,0,E57+H57) -> 536541.9 | J57: =IF(D57=0,0,MAX(0,D57-G57-H57)) -> 39591120 | K57: =IF(D57=0,0,I57/Inputs!$C$71*(1-Inputs!$C$80)^(45/12)) -> 0.0065200147
B58: 46 | C58: =EDATE($C$12,46) -> 46692 | D58: =IF(46>Inputs!$C$78,0,J57) -> 39591120 | E58: =IF(D58=0,0,MIN($C$8,D58+F58)) -> 536541.9 | F58: =IF(D58=0,0,D58*$C$7) -> 181459.3 | G58: =IF(D58=0,0,E58-F58) -> 355082.6 | H58: =IF(46=Inputs!$C$78,$C$6,0) -> 0 | I58: =IF(D58=0,0,E58+H58) -> 536541.9 | J58: =IF(D58=0,0,MAX(0,D58-G58-H58)) -> 39236037 | K58: =IF(D58=0,0,I58/Inputs!$C$71*(1-Inputs!$C$80)^(46/12)) -> 0.0065006859
B59: 47 | C59: =EDATE($C$12,47) -> 46722 | D59: =IF(47>Inputs!$C$78,0,J58) -> 39236037 | E59: =IF(D59=0,0,MIN($C$8,D59+F59)) -> 536541.9 | F59: =IF(D59=0,0,D59*$C$7) -> 179831.84 | G59: =IF(D59=0,0,E59-F59) -> 356710.06 | H59: =IF(47=Inputs!$C$78,$C$6,0) -> 0 | I59: =IF(D59=0,0,E59+H59) -> 536541.9 | J59: =IF(D59=0,0,MAX(0,D59-G59-H59)) -> 38879327 | K59: =IF(D59=0,0,I59/Inputs!$C$71*(1-Inputs!$C$80)^(47/12)) -> 0.0064814144
B60: 48 | C60: =EDATE($C$12,48) -> 46753 | D60: =IF(48>Inputs!$C$78,0,J59) -> 38879327 | E60: =IF(D60=0,0,MIN($C$8,D60+F60)) -> 536541.9 | F60: =IF(D60=0,0,D60*$C$7) -> 178196.91 | G60: =IF(D60=0,0,E60-F60) -> 358344.99 | H60: =IF(48=Inputs!$C$78,$C$6,0) -> 0 | I60: =IF(D60=0,0,E60+H60) -> 536541.9 | J60: =IF(D60=0,0,MAX(0,D60-G60-H60)) -> 38520982 | K60: =IF(D60=0,0,I60/Inputs!$C$71*(1-Inputs!$C$80)^(48/12)) -> 0.0064622001
B61: 49 | C61: =EDATE($C$12,49) -> 46784 | D61: =IF(49>Inputs!$C$78,0,J60) -> 38520982 | E61: =IF(D61=0,0,MIN($C$8,D61+F61)) -> 536541.9 | F61: =IF(D61=0,0,D61*$C$7) -> 176554.5 | G61: =IF(D61=0,0,E61-F61) -> 359987.4 | H61: =IF(49=Inputs!$C$78,$C$6,0) -> 0 | I61: =IF(D61=0,0,E61+H61) -> 536541.9 | J61: =IF(D61=0,0,MAX(0,D61-G61-H61)) -> 38160995 | K61: =IF(D61=0,0,I61/Inputs!$C$71*(1-Inputs!$C$80)^(49/12)) -> 0.0064430427
B62: 50 | C62: =EDATE($C$12,50) -> 46813 | D62: =IF(50>Inputs!$C$78,0,J61) -> 38160995 | E62: =IF(D62=0,0,MIN($C$8,D62+F62)) -> 536541.9 | F62: =IF(D62=0,0,D62*$C$7) -> 174904.56 | G62: =IF(D62=0,0,E62-F62) -> 361637.34 | H62: =IF(50=Inputs!$C$78,$C$6,0) -> 0 | I62: =IF(D62=0,0,E62+H62) -> 536541.9 | J62: =IF(D62=0,0,MAX(0,D62-G62-H62)) -> 37799357 | K62: =IF(D62=0,0,I62/Inputs!$C$71*(1-Inputs!$C$80)^(50/12)) -> 0.0064239421
B63: 51 | C63: =EDATE($C$12,51) -> 46844 | D63: =IF(51>Inputs!$C$78,0,J62) -> 37799357 | E63: =IF(D63=0,0,MIN($C$8,D63+F63)) -> 536541.9 | F63: =IF(D63=0,0,D63*$C$7) -> 173247.05 | G63: =IF(D63=0,0,E63-F63) -> 363294.85 | H63: =IF(51=Inputs!$C$78,$C$6,0) -> 0 | I63: =IF(D63=0,0,E63+H63) -> 536541.9 | J63: =IF(D63=0,0,MAX(0,D63-G63-H63)) -> 37436062 | K63: =IF(D63=0,0,I63/Inputs!$C$71*(1-Inputs!$C$80)^(51/12)) -> 0.0064048982
B64: 52 | C64: =EDATE($C$12,52) -> 46874 | D64: =IF(52>Inputs!$C$78,0,J63) -> 37436062 | E64: =IF(D64=0,0,MIN($C$8,D64+F64)) -> 536541.9 | F64: =IF(D64=0,0,D64*$C$7) -> 171581.95 | G64: =IF(D64=0,0,E64-F64) -> 364959.95 | H64: =IF(52=Inputs!$C$78,$C$6,0) -> 0 | I64: =IF(D64=0,0,E64+H64) -> 536541.9 | J64: =IF(D64=0,0,MAX(0,D64-G64-H64)) -> 37071102 | K64: =IF(D64=0,0,I64/Inputs!$C$71*(1-Inputs!$C$80)^(52/12)) -> 0.0063859107
B65: 53 | C65: =EDATE($C$12,53) -> 46905 | D65: =IF(53>Inputs!$C$78,0,J64) -> 37071102 | E65: =IF(D65=0,0,MIN($C$8,D65+F65)) -> 536541.9 | F65: =IF(D65=0,0,D65*$C$7) -> 169909.22 | G65: =IF(D65=0,0,E65-F65) -> 366632.68 | H65: =IF(53=Inputs!$C$78,$C$6,0) -> 0 | I65: =IF(D65=0,0,E65+H65) -> 536541.9 | J65: =IF(D65=0,0,MAX(0,D65-G65-H65)) -> 36704470 | K65: =IF(D65=0,0,I65/Inputs!$C$71*(1-Inputs!$C$80)^(53/12)) -> 0.0063669794
B66: 54 | C66: =EDATE($C$12,54) -> 46935 | D66: =IF(54>Inputs!$C$78,0,J65) -> 36704470 | E66: =IF(D66=0,0,MIN($C$8,D66+F66)) -> 536541.9 | F66: =IF(D66=0,0,D66*$C$7) -> 168228.82 | G66: =IF(D66=0,0,E66-F66) -> 368313.08 | H66: =IF(54=Inputs!$C$78,$C$6,0) -> 0 | I66: =IF(D66=0,0,E66+H66) -> 536541.9 | J66: =IF(D66=0,0,MAX(0,D66-G66-H66)) -> 36336157 | K66: =IF(D66=0,0,I66/Inputs!$C$71*(1-Inputs!$C$80)^(54/12)) -> 0.0063481044
B67: 55 | C67: =EDATE($C$12,55) -> 46966 | D67: =IF(55>Inputs!$C$78,0,J66) -> 36336157 | E67: =IF(D67=0,0,MIN($C$8,D67+F67)) -> 536541.9 | F67: =IF(D67=0,0,D67*$C$7) -> 166540.72 | G67: =IF(D67=0,0,E67-F67) -> 370001.18 | H67: =IF(55=Inputs!$C$78,$C$6,0) -> 0 | I67: =IF(D67=0,0,E67+H67) -> 536541.9 | J67: =IF(D67=0,0,MAX(0,D67-G67-H67)) -> 35966155 | K67: =IF(D67=0,0,I67/Inputs!$C$71*(1-Inputs!$C$80)^(55/12)) -> 0.0063292852
B68: 56 | C68: =EDATE($C$12,56) -> 46997 | D68: =IF(56>Inputs!$C$78,0,J67) -> 35966155 | E68: =IF(D68=0,0,MIN($C$8,D68+F68)) -> 536541.9 | F68: =IF(D68=0,0,D68*$C$7) -> 164844.88 | G68: =IF(D68=0,0,E68-F68) -> 371697.02 | H68: =IF(56=Inputs!$C$78,$C$6,0) -> 0 | I68: =IF(D68=0,0,E68+H68) -> 536541.9 | J68: =IF(D68=0,0,MAX(0,D68-G68-H68)) -> 35594458 | K68: =IF(D68=0,0,I68/Inputs!$C$71*(1-Inputs!$C$80)^(56/12)) -> 0.0063105219
B69: 57 | C69: =EDATE($C$12,57) -> 47027 | D69: =IF(57>Inputs!$C$78,0,J68) -> 35594458 | E69: =IF(D69=0,0,MIN($C$8,D69+F69)) -> 536541.9 | F69: =IF(D69=0,0,D69*$C$7) -> 163141.27 | G69: =IF(D69=0,0,E69-F69) -> 373400.63 | H69: =IF(57=Inputs!$C$78,$C$6,0) -> 0 | I69: =IF(D69=0,0,E69+H69) -> 536541.9 | J69: =IF(D69=0,0,MAX(0,D69-G69-H69)) -> 35221058 | K69: =IF(D69=0,0,I69/Inputs!$C$71*(1-Inputs!$C$80)^(57/12)) -> 0.0062918141
B70: 58 | C70: =EDATE($C$12,58) -> 47058 | D70: =IF(58>Inputs!$C$78,0,J69) -> 35221058 | E70: =IF(D70=0,0,MIN($C$8,D70+F70)) -> 536541.9 | F70: =IF(D70=0,0,D70*$C$7) -> 161429.85 | G70: =IF(D70=0,0,E70-F70) -> 375112.05 | H70: =IF(58=Inputs!$C$78,$C$6,0) -> 0 | I70: =IF(D70=0,0,E70+H70) -> 536541.9 | J70: =IF(D70=0,0,MAX(0,D70-G70-H70)) -> 34845946 | K70: =IF(D70=0,0,I70/Inputs!$C$71*(1-Inputs!$C$80)^(58/12)) -> 0.0062731619
B71: 59 | C71: =EDATE($C$12,59) -> 47088 | D71: =IF(59>Inputs!$C$78,0,J70) -> 34845946 | E71: =IF(D71=0,0,MIN($C$8,D71+F71)) -> 536541.9 | F71: =IF(D71=0,0,D71*$C$7) -> 159710.58 | G71: =IF(D71=0,0,E71-F71) -> 376831.32 | H71: =IF(59=Inputs!$C$78,$C$6,0) -> 0 | I71: =IF(D71=0,0,E71+H71) -> 536541.9 | J71: =IF(D71=0,0,MAX(0,D71-G71-H71)) -> 34469114 | K71: =IF(D71=0,0,I71/Inputs!$C$71*(1-Inputs!$C$80)^(59/12)) -> 0.0062545649
B72: 60 | C72: =EDATE($C$12,60) -> 47119 | D72: =IF(60>Inputs!$C$78,0,J71) -> 34469114 | E72: =IF(D72=0,0,MIN($C$8,D72+F72)) -> 536541.9 | F72: =IF(D72=0,0,D72*$C$7) -> 157983.44 | G72: =IF(D72=0,0,E72-F72) -> 378558.46 | H72: =IF(60=Inputs!$C$78,$C$6,0) -> 0 | I72: =IF(D72=0,0,E72+H72) -> 536541.9 | J72: =IF(D72=0,0,MAX(0,D72-G72-H72)) -> 34090556 | K72: =IF(D72=0,0,I72/Inputs!$C$71*(1-Inputs!$C$80)^(60/12)) -> 0.0062360231
B73: 61 | C73: =EDATE($C$12,61) -> 47150 | D73: =IF(61>Inputs!$C$78,0,J72) -> 34090556 | E73: =IF(D73=0,0,MIN($C$8,D73+F73)) -> 536541.9 | F73: =IF(D73=0,0,D73*$C$7) -> 156248.38 | G73: =IF(D73=0,0,E73-F73) -> 380293.52 | H73: =IF(61=Inputs!$C$78,$C$6,0) -> 0 | I73: =IF(D73=0,0,E73+H73) -> 536541.9 | J73: =IF(D73=0,0,MAX(0,D73-G73-H73)) -> 33710262 | K73: =IF(D73=0,0,I73/Inputs!$C$71*(1-Inputs!$C$80)^(61/12)) -> 0.0062175362
B74: 62 | C74: =EDATE($C$12,62) -> 47178 | D74: =IF(62>Inputs!$C$78,0,J73) -> 33710262 | E74: =IF(D74=0,0,MIN($C$8,D74+F74)) -> 536541.9 | F74: =IF(D74=0,0,D74*$C$7) -> 154505.37 | G74: =IF(D74=0,0,E74-F74) -> 382036.53 | H74: =IF(62=Inputs!$C$78,$C$6,0) -> 0 | I74: =IF(D74=0,0,E74+H74) -> 536541.9 | J74: =IF(D74=0,0,MAX(0,D74-G74-H74)) -> 33328226 | K74: =IF(D74=0,0,I74/Inputs!$C$71*(1-Inputs!$C$80)^(62/12)) -> 0.0061991041
B75: 63 | C75: =EDATE($C$12,63) -> 47209 | D75: =IF(63>Inputs!$C$78,0,J74) -> 33328226 | E75: =IF(D75=0,0,MIN($C$8,D75+F75)) -> 536541.9 | F75: =IF(D75=0,0,D75*$C$7) -> 152754.37 | G75: =IF(D75=0,0,E75-F75) -> 383787.53 | H75: =IF(63=Inputs!$C$78,$C$6,0) -> 0 | I75: =IF(D75=0,0,E75+H75) -> 536541.9 | J75: =IF(D75=0,0,MAX(0,D75-G75-H75)) -> 32944438 | K75: =IF(D75=0,0,I75/Inputs!$C$71*(1-Inputs!$C$80)^(63/12)) -> 0.0061807267
B76: 64 | C76: =EDATE($C$12,64) -> 47239 | D76: =IF(64>Inputs!$C$78,0,J75) -> 32944438 | E76: =IF(D76=0,0,MIN($C$8,D76+F76)) -> 536541.9 | F76: =IF(D76=0,0,D76*$C$7) -> 150995.34 | G76: =IF(D76=0,0,E76-F76) -> 385546.56 | H76: =IF(64=Inputs!$C$78,$C$6,0) -> 0 | I76: =IF(D76=0,0,E76+H76) -> 536541.9 | J76: =IF(D76=0,0,MAX(0,D76-G76-H76)) -> 32558892 | K76: =IF(D76=0,0,I76/Inputs!$C$71*(1-Inputs!$C$80)^(64/12)) -> 0.0061624038
B77: 65 | C77: =EDATE($C$12,65) -> 47270 | D77: =IF(65>Inputs!$C$78,0,J76) -> 32558892 | E77: =IF(D77=0,0,MIN($C$8,D77+F77)) -> 536541.9 | F77: =IF(D77=0,0,D77*$C$7) -> 149228.25 | G77: =IF(D77=0,0,E77-F77) -> 387313.65 | H77: =IF(65=Inputs!$C$78,$C$6,0) -> 0 | I77: =IF(D77=0,0,E77+H77) -> 536541.9 | J77: =IF(D77=0,0,MAX(0,D77-G77-H77)) -> 32171578 | K77: =IF(D77=0,0,I77/Inputs!$C$71*(1-Inputs!$C$80)^(65/12)) -> 0.0061441352
B78: 66 | C78: =EDATE($C$12,66) -> 47300 | D78: =IF(66>Inputs!$C$78,0,J77) -> 32171578 | E78: =IF(D78=0,0,MIN($C$8,D78+F78)) -> 536541.9 | F78: =IF(D78=0,0,D78*$C$7) -> 147453.07 | G78: =IF(D78=0,0,E78-F78) -> 389088.83 | H78: =IF(66=Inputs!$C$78,$C$6,0) -> 0 | I78: =IF(D78=0,0,E78+H78) -> 536541.9 | J78: =IF(D78=0,0,MAX(0,D78-G78-H78)) -> 31782489 | K78: =IF(D78=0,0,I78/Inputs!$C$71*(1-Inputs!$C$80)^(66/12)) -> 0.0061259207
B79: 67 | C79: =EDATE($C$12,67) -> 47331 | D79: =IF(67>Inputs!$C$78,0,J78) -> 31782489 | E79: =IF(D79=0,0,MIN($C$8,D79+F79)) -> 536541.9 | F79: =IF(D79=0,0,D79*$C$7) -> 145669.74 | G79: =IF(D79=0,0,E79-F79) -> 390872.16 | H79: =IF(67=Inputs!$C$78,$C$6,0) -> 0 | I79: =IF(D79=0,0,E79+H79) -> 536541.9 | J79: =IF(D79=0,0,MAX(0,D79-G79-H79)) -> 31391617 | K79: =IF(D79=0,0,I79/Inputs!$C$71*(1-Inputs!$C$80)^(67/12)) -> 0.0061077602
B80: 68 | C80: =EDATE($C$12,68) -> 47362 | D80: =IF(68>Inputs!$C$78,0,J79) -> 31391617 | E80: =IF(D80=0,0,MIN($C$8,D80+F80)) -> 536541.9 | F80: =IF(D80=0,0,D80*$C$7) -> 143878.25 | G80: =IF(D80=0,0,E80-F80) -> 392663.66 | H80: =IF(68=Inputs!$C$78,$C$6,0) -> 0 | I80: =IF(D80=0,0,E80+H80) -> 536541.9 | J80: =IF(D80=0,0,MAX(0,D80-G80-H80)) -> 30998954 | K80: =IF(D80=0,0,I80/Inputs!$C$71*(1-Inputs!$C$80)^(68/12)) -> 0.0060896536
B81: 69 | C81: =EDATE($C$12,69) -> 47392 | D81: =IF(69>Inputs!$C$78,0,J80) -> 30998954 | E81: =IF(D81=0,0,MIN($C$8,D81+F81)) -> 536541.9 | F81: =IF(D81=0,0,D81*$C$7) -> 142078.54 | G81: =IF(D81=0,0,E81-F81) -> 394463.36 | H81: =IF(69=Inputs!$C$78,$C$6,0) -> 0 | I81: =IF(D81=0,0,E81+H81) -> 536541.9 | J81: =IF(D81=0,0,MAX(0,D81-G81-H81)) -> 30604490 | K81: =IF(D81=0,0,I81/Inputs!$C$71*(1-Inputs!$C$80)^(69/12)) -> 0.0060716007
B82: 70 | C82: =EDATE($C$12,70) -> 47423 | D82: =IF(70>Inputs!$C$78,0,J81) -> 30604490 | E82: =IF(D82=0,0,MIN($C$8,D82+F82)) -> 536541.9 | F82: =IF(D82=0,0,D82*$C$7) -> 140270.58 | G82: =IF(D82=0,0,E82-F82) -> 396271.32 | H82: =IF(70=Inputs!$C$78,$C$6,0) -> 0 | I82: =IF(D82=0,0,E82+H82) -> 536541.9 | J82: =IF(D82=0,0,MAX(0,D82-G82-H82)) -> 30208219 | K82: =IF(D82=0,0,I82/Inputs!$C$71*(1-Inputs!$C$80)^(70/12)) -> 0.0060536012
B83: 71 | C83: =EDATE($C$12,71) -> 47453 | D83: =IF(71>Inputs!$C$78,0,J82) -> 30208219 | E83: =IF(D83=0,0,MIN($C$8,D83+F83)) -> 536541.9 | F83: =IF(D83=0,0,D83*$C$7) -> 138454.34 | G83: =IF(D83=0,0,E83-F83) -> 398087.56 | H83: =IF(71=Inputs!$C$78,$C$6,0) -> 0 | I83: =IF(D83=0,0,E83+H83) -> 536541.9 | J83: =IF(D83=0,0,MAX(0,D83-G83-H83)) -> 29810131 | K83: =IF(D83=0,0,I83/Inputs!$C$71*(1-Inputs!$C$80)^(71/12)) -> 0.0060356551
B84: 72 | C84: =EDATE($C$12,72) -> 47484 | D84: =IF(72>Inputs!$C$78,0,J83) -> 29810131 | E84: =IF(D84=0,0,MIN($C$8,D84+F84)) -> 536541.9 | F84: =IF(D84=0,0,D84*$C$7) -> 136629.77 | G84: =IF(D84=0,0,E84-F84) -> 399912.13 | H84: =IF(72=Inputs!$C$78,$C$6,0) -> 0 | I84: =IF(D84=0,0,E84+H84) -> 536541.9 | J84: =IF(D84=0,0,MAX(0,D84-G84-H84)) -> 29410219 | K84: =IF(D84=0,0,I84/Inputs!$C$71*(1-Inputs!$C$80)^(72/12)) -> 0.0060177623
B85: 73 | C85: =EDATE($C$12,73) -> 47515 | D85: =IF(73>Inputs!$C$78,0,J84) -> 29410219 | E85: =IF(D85=0,0,MIN($C$8,D85+F85)) -> 536541.9 | F85: =IF(D85=0,0,D85*$C$7) -> 134796.84 | G85: =IF(D85=0,0,E85-F85) -> 401745.06 | H85: =IF(73=Inputs!$C$78,$C$6,0) -> 0 | I85: =IF(D85=0,0,E85+H85) -> 536541.9 | J85: =IF(D85=0,0,MAX(0,D85-G85-H85)) -> 29008474 | K85: =IF(D85=0,0,I85/Inputs!$C$71*(1-Inputs!$C$80)^(73/12)) -> 0.0059999224
B86: 74 | C86: =EDATE($C$12,74) -> 47543 | D86: =IF(74>Inputs!$C$78,0,J85) -> 29008474 | E86: =IF(D86=0,0,MIN($C$8,D86+F86)) -> 536541.9 | F86: =IF(D86=0,0,D86*$C$7) -> 132955.51 | G86: =IF(D86=0,0,E86-F86) -> 403586.39 | H86: =IF(74=Inputs!$C$78,$C$6,0) -> 0 | I86: =IF(D86=0,0,E86+H86) -> 536541.9 | J86: =IF(D86=0,0,MAX(0,D86-G86-H86)) -> 28604888 | K86: =IF(D86=0,0,I86/Inputs!$C$71*(1-Inputs!$C$80)^(74/12)) -> 0.0059821355
B87: 75 | C87: =EDATE($C$12,75) -> 47574 | D87: =IF(75>Inputs!$C$78,0,J86) -> 28604888 | E87: =IF(D87=0,0,MIN($C$8,D87+F87)) -> 536541.9 | F87: =IF(D87=0,0,D87*$C$7) -> 131105.74 | G87: =IF(D87=0,0,E87-F87) -> 405436.17 | H87: =IF(75=Inputs!$C$78,$C$6,0) -> 0 | I87: =IF(D87=0,0,E87+H87) -> 536541.9 | J87: =IF(D87=0,0,MAX(0,D87-G87-H87)) -> 28199452 | K87: =IF(D87=0,0,I87/Inputs!$C$71*(1-Inputs!$C$80)^(75/12)) -> 0.0059644013
B88: 76 | C88: =EDATE($C$12,76) -> 47604 | D88: =IF(76>Inputs!$C$78,0,J87) -> 28199452 | E88: =IF(D88=0,0,MIN($C$8,D88+F88)) -> 536541.9 | F88: =IF(D88=0,0,D88*$C$7) -> 129247.49 | G88: =IF(D88=0,0,E88-F88) -> 407294.41 | H88: =IF(76=Inputs!$C$78,$C$6,0) -> 0 | I88: =IF(D88=0,0,E88+H88) -> 536541.9 | J88: =IF(D88=0,0,MAX(0,D88-G88-H88)) -> 27792157 | K88: =IF(D88=0,0,I88/Inputs!$C$71*(1-Inputs!$C$80)^(76/12)) -> 0.0059467197
B89: 77 | C89: =EDATE($C$12,77) -> 47635 | D89: =IF(77>Inputs!$C$78,0,J88) -> 27792157 | E89: =IF(D89=0,0,MIN($C$8,D89+F89)) -> 536541.9 | F89: =IF(D89=0,0,D89*$C$7) -> 127380.72 | G89: =IF(D89=0,0,E89-F89) -> 409161.18 | H89: =IF(77=Inputs!$C$78,$C$6,0) -> 0 | I89: =IF(D89=0,0,E89+H89) -> 536541.9 | J89: =IF(D89=0,0,MAX(0,D89-G89-H89)) -> 27382996 | K89: =IF(D89=0,0,I89/Inputs!$C$71*(1-Inputs!$C$80)^(77/12)) -> 0.0059290904
B90: 78 | C90: =EDATE($C$12,78) -> 47665 | D90: =IF(78>Inputs!$C$78,0,J89) -> 27382996 | E90: =IF(D90=0,0,MIN($C$8,D90+F90)) -> 536541.9 | F90: =IF(D90=0,0,D90*$C$7) -> 125505.4 | G90: =IF(D90=0,0,E90-F90) -> 411036.5 | H90: =IF(78=Inputs!$C$78,$C$6,0) -> 0 | I90: =IF(D90=0,0,E90+H90) -> 536541.9 | J90: =IF(D90=0,0,MAX(0,D90-G90-H90)) -> 26971959 | K90: =IF(D90=0,0,I90/Inputs!$C$71*(1-Inputs!$C$80)^(78/12)) -> 0.0059115135
B91: 79 | C91: =EDATE($C$12,79) -> 47696 | D91: =IF(79>Inputs!$C$78,0,J90) -> 26971959 | E91: =IF(D91=0,0,MIN($C$8,D91+F91)) -> 536541.9 | F91: =IF(D91=0,0,D91*$C$7) -> 123621.48 | G91: =IF(D91=0,0,E91-F91) -> 412920.42 | H91: =IF(79=Inputs!$C$78,$C$6,0) -> 0 | I91: =IF(D91=0,0,E91+H91) -> 536541.9 | J91: =IF(D91=0,0,MAX(0,D91-G91-H91)) -> 26559039 | K91: =IF(D91=0,0,I91/Inputs!$C$71*(1-Inputs!$C$80)^(79/12)) -> 0.0058939886
B92: 80 | C92: =EDATE($C$12,80) -> 47727 | D92: =IF(80>Inputs!$C$78,0,J91) -> 26559039 | E92: =IF(D92=0,0,MIN($C$8,D92+F92)) -> 536541.9 | F92: =IF(D92=0,0,D92*$C$7) -> 121728.93 | G92: =IF(D92=0,0,E92-F92) -> 414812.97 | H92: =IF(80=Inputs!$C$78,$C$6,0) -> 0 | I92: =IF(D92=0,0,E92+H92) -> 536541.9 | J92: =IF(D92=0,0,MAX(0,D92-G92-H92)) -> 26144226 | K92: =IF(D92=0,0,I92/Inputs!$C$71*(1-Inputs!$C$80)^(80/12)) -> 0.0058765157
B93: 81 | C93: =EDATE($C$12,81) -> 47757 | D93: =IF(81>Inputs!$C$78,0,J92) -> 26144226 | E93: =IF(D93=0,0,MIN($C$8,D93+F93)) -> 536541.9 | F93: =IF(D93=0,0,D93*$C$7) -> 119827.7 | G93: =IF(D93=0,0,E93-F93) -> 416714.2 | H93: =IF(81=Inputs!$C$78,$C$6,0) -> 0 | I93: =IF(D93=0,0,E93+H93) -> 536541.9 | J93: =IF(D93=0,0,MAX(0,D93-G93-H93)) -> 25727512 | K93: =IF(D93=0,0,I93/Inputs!$C$71*(1-Inputs!$C$80)^(81/12)) -> 0.0058590946
B94: 82 | C94: =EDATE($C$12,82) -> 47788 | D94: =IF(82>Inputs!$C$78,0,J93) -> 25727512 | E94: =IF(D94=0,0,MIN($C$8,D94+F94)) -> 536541.9 | F94: =IF(D94=0,0,D94*$C$7) -> 117917.76 | G94: =IF(D94=0,0,E94-F94) -> 418624.14 | H94: =IF(82=Inputs!$C$78,$C$6,0) -> 0 | I94: =IF(D94=0,0,E94+H94) -> 536541.9 | J94: =IF(D94=0,0,MAX(0,D94-G94-H94)) -> 25308888 | K94: =IF(D94=0,0,I94/Inputs!$C$71*(1-Inputs!$C$80)^(82/12)) -> 0.0058417252
B95: 83 | C95: =EDATE($C$12,83) -> 47818 | D95: =IF(83>Inputs!$C$78,0,J94) -> 25308888 | E95: =IF(D95=0,0,MIN($C$8,D95+F95)) -> 536541.9 | F95: =IF(D95=0,0,D95*$C$7) -> 115999.07 | G95: =IF(D95=0,0,E95-F95) -> 420542.83 | H95: =IF(83=Inputs!$C$78,$C$6,0) -> 0 | I95: =IF(D95=0,0,E95+H95) -> 536541.9 | J95: =IF(D95=0,0,MAX(0,D95-G95-H95)) -> 24888345 | K95: =IF(D95=0,0,I95/Inputs!$C$71*(1-Inputs!$C$80)^(83/12)) -> 0.0058244072
B96: 84 | C96: =EDATE($C$12,84) -> 47849 | D96: =IF(84>Inputs!$C$78,0,J95) -> 24888345 | E96: =IF(D96=0,0,MIN($C$8,D96+F96)) -> 536541.9 | F96: =IF(D96=0,0,D96*$C$7) -> 114071.58 | G96: =IF(D96=0,0,E96-F96) -> 422470.32 | H96: =IF(84=Inputs!$C$78,$C$6,0) -> 0 | I96: =IF(D96=0,0,E96+H96) -> 536541.9 | J96: =IF(D96=0,0,MAX(0,D96-G96-H96)) -> 24465875 | K96: =IF(D96=0,0,I96/Inputs!$C$71*(1-Inputs!$C$80)^(84/12)) -> 0.0058071406
B97: 85 | C97: =EDATE($C$12,85) -> 47880 | D97: =IF(85>Inputs!$C$78,0,J96) -> 24465875 | E97: =IF(D97=0,0,MIN($C$8,D97+F97)) -> 536541.9 | F97: =IF(D97=0,0,D97*$C$7) -> 112135.26 | G97: =IF(D97=0,0,E97-F97) -> 424406.64 | H97: =IF(85=Inputs!$C$78,$C$6,0) -> 0 | I97: =IF(D97=0,0,E97+H97) -> 536541.9 | J97: =IF(D97=0,0,MAX(0,D97-G97-H97)) -> 24041468 | K97: =IF(D97=0,0,I97/Inputs!$C$71*(1-Inputs!$C$80)^(85/12)) -> 0.0057899252
B98: 86 | C98: =EDATE($C$12,86) -> 47908 | D98: =IF(86>Inputs!$C$78,0,J97) -> 24041468 | E98: =IF(D98=0,0,MIN($C$8,D98+F98)) -> 536541.9 | F98: =IF(D98=0,0,D98*$C$7) -> 110190.06 | G98: =IF(D98=0,0,E98-F98) -> 426351.84 | H98: =IF(86=Inputs!$C$78,$C$6,0) -> 0 | I98: =IF(D98=0,0,E98+H98) -> 536541.9 | J98: =IF(D98=0,0,MAX(0,D98-G98-H98)) -> 23615116 | K98: =IF(D98=0,0,I98/Inputs!$C$71*(1-Inputs!$C$80)^(86/12)) -> 0.0057727608
B99: 87 | C99: =EDATE($C$12,87) -> 47939 | D99: =IF(87>Inputs!$C$78,0,J98) -> 23615116 | E99: =IF(D99=0,0,MIN($C$8,D99+F99)) -> 536541.9 | F99: =IF(D99=0,0,D99*$C$7) -> 108235.95 | G99: =IF(D99=0,0,E99-F99) -> 428305.95 | H99: =IF(87=Inputs!$C$78,$C$6,0) -> 0 | I99: =IF(D99=0,0,E99+H99) -> 536541.9 | J99: =IF(D99=0,0,MAX(0,D99-G99-H99)) -> 23186810 | K99: =IF(D99=0,0,I99/Inputs!$C$71*(1-Inputs!$C$80)^(87/12)) -> 0.0057556472
B100: 88 | C100: =EDATE($C$12,88) -> 47969 | D100: =IF(88>Inputs!$C$78,0,J99) -> 23186810 | E100: =IF(D100=0,0,MIN($C$8,D100+F100)) -> 536541.9 | F100: =IF(D100=0,0,D100*$C$7) -> 106272.88 | G100: =IF(D100=0,0,E100-F100) -> 430269.02 | H100: =IF(88=Inputs!$C$78,$C$6,0) -> 0 | I100: =IF(D100=0,0,E100+H100) -> 536541.9 | J100: =IF(D100=0,0,MAX(0,D100-G100-H100)) -> 22756541 | K100: =IF(D100=0,0,I100/Inputs!$C$71*(1-Inputs!$C$80)^(88/12)) -> 0.0057385845
B101: 89 | C101: =EDATE($C$12,89) -> 48000 | D101: =IF(89>Inputs!$C$78,0,J100) -> 22756541 | E101: =IF(D101=0,0,MIN($C$8,D101+F101)) -> 536541.9 | F101: =IF(D101=0,0,D101*$C$7) -> 104300.81 | G101: =IF(D101=0,0,E101-F101) -> 432241.09 | H101: =IF(89=Inputs!$C$78,$C$6,0) -> 0 | I101: =IF(D101=0,0,E101+H101) -> 536541.9 | J101: =IF(D101=0,0,MAX(0,D101-G101-H101)) -> 22324300 | K101: =IF(D101=0,0,I101/Inputs!$C$71*(1-Inputs!$C$80)^(89/12)) -> 0.0057215723
B102: 90 | C102: =EDATE($C$12,90) -> 48030 | D102: =IF(90>Inputs!$C$78,0,J101) -> 22324300 | E102: =IF(D102=0,0,MIN($C$8,D102+F102)) -> 536541.9 | F102: =IF(D102=0,0,D102*$C$7) -> 102319.71 | G102: =IF(D102=0,0,E102-F102) -> 434222.19 | H102: =IF(90=Inputs!$C$78,$C$6,0) -> 0 | I102: =IF(D102=0,0,E102+H102) -> 536541.9 | J102: =IF(D102=0,0,MAX(0,D102-G102-H102)) -> 21890078 | K102: =IF(D102=0,0,I102/Inputs!$C$71*(1-Inputs!$C$80)^(90/12)) -> 0.0057046105
B103: 91 | C103: =EDATE($C$12,91) -> 48061 | D103: =IF(91>Inputs!$C$78,0,J102) -> 21890078 | E103: =IF(D103=0,0,MIN($C$8,D103+F103)) -> 536541.9 | F103: =IF(D103=0,0,D103*$C$7) -> 100329.52 | G103: =IF(D103=0,0,E103-F103) -> 436212.38 | H103: =IF(91=Inputs!$C$78,$C$6,0) -> 0 | I103: =IF(D103=0,0,E103+H103) -> 536541.9 | J103: =IF(D103=0,0,MAX(0,D103-G103-H103)) -> 21453865 | K103: =IF(D103=0,0,I103/Inputs!$C$71*(1-Inputs!$C$80)^(91/12)) -> 0.005687699
...

Sheet Calculations
A1: AVIATION LEASE CASH FLOW MODEL | Monthly Calculations
B3: Month | C3: Date | D3: Lessee Status | E3: Monthly Lease Rev ($) | F3: Monthly OpEx ($) | G3: Maint. Reserve ($) | H3: NOI ($) | I3: Debt Service ($) | J3: CFADS ($) | K3: DSCR | L3: Cum. CFADS ($)
B4: 1 | C4: =EDATE(DATE(2024,1,1),0) -> 45292 | D4: =IF(1>Inputs!$C$74,"Expired",IF(Inputs!$C$68>0,IF(1<Inputs!$C$68,"Paying",IF(1<Inputs!$C$68+Inputs!$C$85,"Default","Re-Lease")),"Paying")) -> Paying | E4: =IF(D4="Expired",0,IF(D4="Default",0,IF(D4="Re-Lease",Inputs!$C$71*Inputs!$C$86,Inputs!$C$73))) -> 561600 | F4: =(Inputs!$C$82*(1+Inputs!$C$83)^0)/12+IF(1=Inputs!$C$68,Inputs!$C$69/12,0) -> 85833.333 | G4: =IF(D4="Expired",0,(IF(Inputs!$C$5=1,(Inputs!C38+Inputs!C39)/12,(Inputs!F38+Inputs!F39)/12)*(1+Inputs!$C$83)^0)) -> 52500 | H4: =E4-F4-G4 -> 423266.67 | I4: ='Debt Schedule'!I13 -> 536541.9 | J4: =H4-I4 -> -113275.23 | K4: =IFERROR(H4/I4,"-") -> 0.78887905 | L4: =SUM($J$4:J4) -> -113275.23
B5: 2 | C5: =EDATE(DATE(2024,1,1),1) -> 45323 | D5: =IF(2>Inputs!$C$74,"Expired",IF(Inputs!$C$68>0,IF(2<Inputs!$C$68,"Paying",IF(2<Inputs!$C$68+Inputs!$C$85,"Default","Re-Lease")),"Paying")) -> Paying | E5: =IF(D5="Expired",0,IF(D5="Default",0,IF(D5="Re-Lease",Inputs!$C$71*Inputs!$C$86,Inputs!$C$73))) -> 561600 | F5: =(Inputs!$C$82*(1+Inputs!$C$83)^0)/12+IF(2=Inputs!$C$68,Inputs!$C$69/12,0) -> 85833.333 | G5: =IF(D5="Expired",0,(IF(Inputs!$C$5=1,(Inputs!C38+Inputs!C39)/12,(Inputs!F38+Inputs!F39)/12)*(1+Inputs!$C$83)^0)) -> 52500 | H5: =E5-F5-G5 -> 423266.67 | I5: ='Debt Schedule'!I14 -> 536541.9 | J5: =H5-I5 -> -113275.23 | K5: =IFERROR(H5/I5,"-") -> 0.78887905 | L5: =SUM($J$4:J5) -> -226550.47
B6: 3 | C6: =EDATE(DATE(2024,1,1),2) -> 45352 | D6: =IF(3>Inputs!$C$74,"Expired",IF(Inputs!$C$68>0,IF(3<Inputs!$C$68,"Paying",IF(3<Inputs!$C$68+Inputs!$C$85,"Default","Re-Lease")),"Paying")) -> Paying | E6: =IF(D6="Expired",0,IF(D6="Default",0,IF(D6="Re-Lease",Inputs!$C$71*Inputs!$C$86,Inputs!$C$73))) -> 561600 | F6: =(Inputs!$C$82*(1+Inputs!$C$83)^0)/12+IF(3=Inputs!$C$68,Inputs!$C$69/12,0) -> 85833.333 | G6: =IF(D6="Expired",0,(IF(Inputs!$C$5=1,(Inputs!C38+Inputs!C39)/12,(Inputs!F38+Inputs!F39)/12)*(1+Inputs!$C$83)^0)) -> 52500 | H6: =E6-F6-G6 -> 423266.67 | I6: ='Debt Schedule'!I15 -> 536541.9 | J6: =H6-I6 -> -113275.23 | K6: =IFERROR(H6/I6,"-") -> 0.78887905 | L6: =SUM($J$4:J6) -> -339825.7
B7: 4 | C7: =EDATE(DATE(2024,1,1),3) -> 45383 | D7: =IF(4>Inputs!$C$74,"Expired",IF(Inputs!$C$68>0,IF(4<Inputs!$C$68,"Paying",IF(4<Inputs!$C$68+Inputs!$C$85,"Default","Re-Lease")),"Paying")) -> Paying | E7: =IF(D7="Expired",0,IF(D7="Default",0,IF(D7="Re-Lease",Inputs!$C$71*Inputs!$C$86,Inputs!$C$73))) -> 561600 | F7: =(Inputs!$C$82*(1+Inputs!$C$83)^0)/12+IF(4=Inputs!$C$68,Inputs!$C$69/12,0) -> 85833.333 | G7: =IF(D7="Expired",0,(IF(Inputs!$C$5=1,(Inputs!C38+Inputs!C39)/12,(Inputs!F38+Inputs!F39)/12)*(1+Inputs!$C$83)^0)) -> 52500 | H7: =E7-F7-G7 -> 423266.67 | I7: ='Debt Schedule'!I16 -> 536541.9 | J7: =H7-I7 -> -113275.23 | K7: =IFERROR(H7/I7,"-") -> 0.78887905 | L7: =SUM($J$4:J7) -> -453100.94
B8: 5 | C8: =EDATE(DATE(2024,1,1),4) -> 45413 | D8: =IF(5>Inputs!$C$74,"Expired",IF(Inputs!$C$68>0,IF(5<Inputs!$C$68,"Paying",IF(5<Inputs!$C$68+Inputs!$C$85,"Default","Re-Lease")),"Paying")) -> Paying | E8: =IF(D8="Expired",0,IF(D8="Default",0,IF(D8="Re-Lease",Inputs!$C$71*Inputs!$C$86,Inputs!$C$73))) -> 561600 | F8: =(Inputs!$C$82*(1+Inputs!$C$83)^0)/12+IF(5=Inputs!$C$68,Inputs!$C$69/12,0) -> 85833.333 | G8: =IF(D8="Expired",0,(IF(Inputs!$C$5=1,(Inputs!C38+Inputs!C39)/12,(Inputs!F38+Inputs!F39)/12)*(1+Inputs!$C$83)^0)) -> 52500 | H8: =E8-F8-G8 -> 423266.67 | I8: ='Debt Schedule'!I17 -> 536541.9 | J8: =H8-I8 -> -113275.23 | K8: =IFERROR(H8/I8,"-") -> 0.78887905 | L8: =SUM($J$4:J8) -> -566376.17
B9: 6 | C9: =EDATE(DATE(2024,1,1),5) -> 45444 | D9: =IF(6>Inputs!$C$74,"Expired",IF(Inputs!$C$68>0,IF(6<Inputs!$C$68,"Paying",IF(6<Inputs!$C$68+Inputs!$C$85,"Default","Re-Lease")),"Paying")) -> Paying | E9: =IF(D9="Expired",0,IF(D9="Default",0,IF(D9="Re-Lease",Inputs!$C$71*Inputs!$C$86,Inputs!$C$73))) -> 561600 | F9: =(Inputs!$C$82*(1+Inputs!$C$83)^0)/12+IF(6=Inputs!$C$68,Inputs!$C$69/12,0) -> 85833.333 | G9: =IF(D9="Expired",0,(IF(Inputs!$C$5=1,(Inputs!C38+Inputs!C39)/12,(Inputs!F38+Inputs!F39)/12)*(1+Inputs!$C$83)^0)) -> 52500 | H9: =E9-F9-G9 -> 423266.67 | I9: ='Debt Schedule'!I18 -> 536541.9 | J9: =H9-I9 -> -113275.23 | K9: =IFERROR(H9/I9,"-") -> 0.78887905 | L9: =SUM($J$4:J9) -> -679651.41
B10: 7 | C10: =EDATE(DATE(2024,1,1),6) -> 45474 | D10: =IF(7>Inputs!$C$74,"Expired",IF(Inputs!$C$68>0,IF(7<Inputs!$C$68,"Paying",IF(7<Inputs!$C$68+Inputs!$C$85,"Default","Re-Lease")),"Paying")) -> Paying | E10: =IF(D10="Expired",0,IF(D10="Default",0,IF(D10="Re-Lease",Inputs!$C$71*Inputs!$C$86,Inputs!$C$73))) -> 561600 | F10: =(Inputs!$C$82*(1+Inputs!$C$83)^0)/12+IF(7=Inputs!$C$68,Inputs!$C$69/12,0) -> 85833.333 | G10: =IF(D10="Expired",0,(IF(Inputs!$C$5=1,(Inputs!C38+Inputs!C39)/12,(Inputs!F38+Inputs!F39)/12)*(1+Inputs!$C$83)^0)) -> 52500 | H10: =E10-F10-G10 -> 423266.67 | I10: ='Debt Schedule'!I19 -> 536541.9 | J10: =H10-I10 -> -113275.23 | K10: =IFERROR(H10/I10,"-") -> 0.78887905 | L10: =SUM($J$4:J10) -> -792926.64
B11: 8 | C11: =EDATE(DATE(2024,1,1),7) -> 45505 | D11: =IF(8>Inputs!$C$74,"Expired",IF(Inputs!$C$68>0,IF(8<Inputs!$C$68,"Paying",IF(8<Inputs!$C$68+Inputs!$C$85,"Default","Re-Lease")),"Paying")) -> Paying | E11: =IF(D11="Expired",0,IF(D11="Default",0,IF(D11="Re-Lease",Inputs!$C$71*Inputs!$C$86,Inputs!$C$73))) -> 561600 | F11: =(Inputs!$C$82*(1+Inputs!$C$83)^0)/12+IF(8=Inputs!$C$68,Inputs!$C$69/12,0) -> 85833.333 | G11: =IF(D11="Expired",0,(IF(Inputs!$C$5=1,(Inputs!C38+Inputs!C39)/12,(Inputs!F38+Inputs!F39)/12)*(1+Inputs!$C$83)^0)) -> 52500 | H11: =E11-F11-G11 -> 423266.67 | I11: ='Debt Schedule'!I20 -> 536541.9 | J11: =H11-I11 -> -113275.23 | K11: =IFERROR(H11/I11,"-") -> 0.78887905 | L11: =SUM($J$4:J11) -> -906201.87
B12: 9 | C12: =EDATE(DATE(2024,1,1),8) -> 45536 | D12: =IF(9>Inputs!$C$74,"Expired",IF(Inputs!$C$68>0,IF(9<Inputs!$C$68,"Paying",IF(9<Inputs!$C$68+Inputs!$C$85,"Default","Re-Lease")),"Paying")) -> Paying | E12: =IF(D12="Expired",0,IF(D12="Default",0,IF(D12="Re-Lease",Inputs!$C$71*Inputs!$C$86,Inputs!$C$73))) -> 561600 | F12: =(Inputs!$C$82*(1+Inputs!$C$83)^0)/12+IF(9=Inputs!$C$68,Inputs!$C$69/12,0) -> 85833.333 | G12: =IF(D12="Expired",0,(IF(Inputs!$C$5=1,(Inputs!C38+Inputs!C39)/12,(Inputs!F38+Inputs!F39)/12)*(1+Inputs!$C$83)^0)) -> 52500 | H12: =E12-F12-G12 -> 423266.67 | I12: ='Debt Schedule'!I21 -> 536541.9 | J12: =H12-I12 -> -113275.23 | K12: =IFERROR(H12/I12,"-") -> 0.78887905 | L12: =SUM($J$4:J12) -> -1019477.1
B13: 10 | C13: =EDATE(DATE(2024,1,1),9) -> 45566 | D13: =IF(10>Inputs!$C$74,"Expired",IF(Inputs!$C$68>0,IF(10<Inputs!$C$68,"Paying",IF(10<Inputs!$C$68+Inputs!$C$85,"Default","Re-Lease")),"Paying")) -> Paying | E13: =IF(D13="Expired",0,IF(D13="Default",0,IF(D13="Re-Lease",Inputs!$C$71*Inputs!$C$86,Inputs!$C$73))) -> 561600 | F13: =(Inputs!$C$82*(1+Inputs!$C$83)^0)/12+IF(10=Inputs!$C$68,Inputs!$C$69/12,0) -> 85833.333 | G13: =IF(D13="Expired",0,(IF(Inputs!$C$5=1,(Inputs!C38+Inputs!C39)/12,(Inputs!F38+Inputs!F39)/12)*(1+Inputs!$C$83)^0)) -> 52500 | H13: =E13-F13-G13 -> 423266.67 | I13: ='Debt Schedule'!I22 -> 536541.9 | J13: =H13-I13 -> -113275.23 | K13: =IFERROR(H13/I13,"-") -> 0.78887905 | L13: =SUM($J$4:J13) -> -1132752.3
B14: 11 | C14: =EDATE(DATE(2024,1,1),10) -> 45597 | D14: =IF(11>Inputs!$C$74,"Expired",IF(Inputs!$C$68>0,IF(11<Inputs!$C$68,"Paying",IF(11<Inputs!$C$68+Inputs!$C$85,"Default","Re-Lease")),"Paying")) -> Paying | E14: =IF(D14="Expired",0,IF(D14="Default",0,IF(D14="Re-Lease",Inputs!$C$71*Inputs!$C$86,Inputs!$C$73))) -> 561600 | F14: =(Inputs!$C$82*(1+Inputs!$C$83)^0)/12+IF(11=Inputs!$C$68,Inputs!$C$69/12,0) -> 85833.333 | G14: =IF(D14="Expired",0,(IF(Inputs!$C$5=1,(Inputs!C38+Inputs!C39)/12,(Inputs!F38+Inputs!F39)/12)*(1+Inputs!$C$83)^0)) -> 52500 | H14: =E14-F14-G14 -> 423266.67 | I14: ='Debt Schedule'!I23 -> 536541.9 | J14: =H14-I14 -> -113275.23 | K14: =IFERROR(H14/I14,"-") -> 0.78887905 | L14: =SUM($J$4:J14) -> -1246027.6
B15: 12 | C15: =EDATE(DATE(2024,1,1),11) -> 45627 | D15: =IF(12>Inputs!$C$74,"Expired",IF(Inputs!$C$68>0,IF(12<Inputs!$C$68,"Paying",IF(12<Inputs!$C$68+Inputs!$C$85,"Default","Re-Lease")),"Paying")) -> Paying | E15: =IF(D15="Expired",0,IF(D15="Default",0,IF(D15="Re-Lease",Inputs!$C$71*Inputs!$C$86,Inputs!$C$73))) -> 561600 | F15: =(Inputs!$C$82*(1+Inputs!$C$83)^0)/12+IF(12=Inputs!$C$68,Inputs!$C$69/12,0) -> 85833.333 | G15: =IF(D15="Expired",0,(IF(Inputs!$C$5=1,(Inputs!C38+Inputs!C39)/12,(Inputs!F38+Inputs!F39)/12)*(1+Inputs!$C$83)^0)) -> 52500 | H15: =E15-F15-G15 -> 423266.67 | I15: ='Debt Schedule'!I24 -> 536541.9 | J15: =H15-I15 -> -113275.23 | K15: =IFERROR(H15/I15,"-") -> 0.78887905 | L15: =SUM($J$4:J15) -> -1359302.8
B16: 13 | C16: =EDATE(DATE(2024,1,1),12) -> 45658 | D16: =IF(13>Inputs!$C$74,"Expired",IF(Inputs!$C$68>0,IF(13<Inputs!$C$68,"Paying",IF(13<Inputs!$C$68+Inputs!$C$85,"Default","Re-Lease")),"Paying")) -> Paying | E16: =IF(D16="Expired",0,IF(D16="Default",0,IF(D16="Re-Lease",Inputs!$C$71*Inputs!$C$86,Inputs!$C$73))) -> 561600 | F16: =(Inputs!$C$82*(1+Inputs!$C$83)^1)/12+IF(13=Inputs!$C$68,Inputs!$C$69/12,0) -> 87979.167 | G16: =IF(D16="Expired",0,(IF(Inputs!$C$5=1,(Inputs!C38+Inputs!C39)/12,(Inputs!F38+Inputs!F39)/12)*(1+Inputs!$C$83)^1)) -> 53812.5 | H16: =E16-F16-G16 -> 419808.33 | I16: ='Debt Schedule'!I25 -> 536541.9 | J16: =H16-I16 -> -116733.57 | K16: =IFERROR(H16/I16,"-") -> 0.78243345 | L16: =SUM($J$4:J16) -> -1476036.4
B17: 14 | C17: =EDATE(DATE(2024,1,1),13) -> 45689 | D17: =IF(14>Inputs!$C$74,"Expired",IF(Inputs!$C$68>0,IF(14<Inputs!$C$68,"Paying",IF(14<Inputs!$C$68+Inputs!$C$85,"Default","Re-Lease")),"Paying")) -> Paying | E17: =IF(D17="Expired",0,IF(D17="Default",0,IF(D17="Re-Lease",Inputs!$C$71*Inputs!$C$86,Inputs!$C$73))) -> 561600 | F17: =(Inputs!$C$82*(1+Inputs!$C$83)^1)/12+IF(14=Inputs!$C$68,Inputs!$C$69/12,0) -> 87979.167 | G17: =IF(D17="Expired",0,(IF(Inputs!$C$5=1,(Inputs!C38+Inputs!C39)/12,(Inputs!F38+Inputs!F39)/12)*(1+Inputs!$C$83)^1)) -> 53812.5 | H17: =E17-F17-G17 -> 419808.33 | I17: ='Debt Schedule'!I26 -> 536541.9 | J17: =H17-I17 -> -116733.57 | K17: =IFERROR(H17/I17,"-") -> 0.78243345 | L17: =SUM($J$4:J17) -> -1592769.9
B18: 15 | C18: =EDATE(DATE(2024,1,1),14) -> 45717 | D18: =IF(15>Inputs!$C$74,"Expired",IF(Inputs!$C$68>0,IF(15<Inputs!$C$68,"Paying",IF(15<Inputs!$C$68+Inputs!$C$85,"Default","Re-Lease")),"Paying")) -> Paying | E18: =IF(D18="Expired",0,IF(D18="Default",0,IF(D18="Re-Lease",Inputs!$C$71*Inputs!$C$86,Inputs!$C$73))) -> 561600 | F18: =(Inputs!$C$82*(1+Inputs!$C$83)^1)/12+IF(15=Inputs!$C$68,Inputs!$C$69/12,0) -> 87979.167 | G18: =IF(D18="Expired",0,(IF(Inputs!$C$5=1,(Inputs!C38+Inputs!C39)/12,(Inputs!F38+Inputs!F39)/12)*(1+Inputs!$C$83)^1)) -> 53812.5 | H18: =E18-F18-G18 -> 419808.33 | I18: ='Debt Schedule'!I27 -> 536541.9 | J18: =H18-I18 -> -116733.57 | K18: =IFERROR(H18/I18,"-") -> 0.78243345 | L18: =SUM($J$4:J18) -> -1709503.5
B19: 16 | C19: =EDATE(DATE(2024,1,1),15) -> 45748 | D19: =IF(16>Inputs!$C$74,"Expired",IF(Inputs!$C$68>0,IF(16<Inputs!$C$68,"Paying",IF(16<Inputs!$C$68+Inputs!$C$85,"Default","Re-Lease")),"Paying")) -> Paying | E19: =IF(D19="Expired",0,IF(D19="Default",0,IF(D19="Re-Lease",Inputs!$C$71*Inputs!$C$86,Inputs!$C$73))) -> 561600 | F19: =(Inputs!$C$82*(1+Inputs!$C$83)^1)/12+IF(16=Inputs!$C$68,Inputs!$C$69/12,0) -> 87979.167 | G19: =IF(D19="Expired",0,(IF(Inputs!$C$5=1,(Inputs!C38+Inputs!C39)/12,(Inputs!F38+Inputs!F39)/12)*(1+Inputs!$C$83)^1)) -> 53812.5 | H19: =E19-F19-G19 -> 419808.33 | I19: ='Debt Schedule'!I28 -> 536541.9 | J19: =H19-I19 -> -116733.57 | K19: =IFERROR(H19/I19,"-") -> 0.78243345 | L19: =SUM($J$4:J19) -> -1826237.1
B20: 17 | C20: =EDATE(DATE(2024,1,1),16) -> 45778 | D20: =IF(17>Inputs!$C$74,"Expired",IF(Inputs!$C$68>0,IF(17<Inputs!$C$68,"Paying",IF(17<Inputs!$C$68+Inputs!$C$85,"Default","Re-Lease")),"Paying")) -> Paying | E20: =IF(D20="Expired",0,IF(D20="Default",0,IF(D20="Re-Lease",Inputs!$C$71*Inputs!$C$86,Inputs!$C$73))) -> 561600 | F20: =(Inputs!$C$82*(1+Inputs!$C$83)^1)/12+IF(17=Inputs!$C$68,Inputs!$C$69/12,0) -> 87979.167 | G20: =IF(D20="Expired",0,(IF(Inputs!$C$5=1,(Inputs!C38+Inputs!C39)/12,(Inputs!F38+Inputs!F39)/12)*(1+Inputs!$C$83)^1)) -> 53812.5 | H20: =E20-F20-G20 -> 419808.33 | I20: ='Debt Schedule'!I29 -> 536541.9 | J20: =H20-I20 -> -116733.57 | K20: =IFERROR(H20/I20,"-") -> 0.78243345 | L20: =SUM($J$4:J20) -> -1942970.7
B21: 18 | C21: =EDATE(DATE(2024,1,1),17) -> 45809 | D21: =IF(18>Inputs!$C$74,"Expired",IF(Inputs!$C$68>0,IF(18<Inputs!$C$68,"Paying",IF(18<Inputs!$C$68+Inputs!$C$85,"Default","Re-Lease")),"Paying")) -> Paying | E21: =IF(D21="Expired",0,IF(D21="Default",0,IF(D21="Re-Lease",Inputs!$C$71*Inputs!$C$86,Inputs!$C$73))) -> 561600 | F21: =(Inputs!$C$82*(1+Inputs!$C$83)^1)/12+IF(18=Inputs!$C$68,Inputs!$C$69/12,0) -> 87979.167 | G21: =IF(D21="Expired",0,(IF(Inputs!$C$5=1,(Inputs!C38+Inputs!C39)/12,(Inputs!F38+Inputs!F39)/12)*(1+Inputs!$C$83)^1)) -> 53812.5 | H21: =E21-F21-G21 -> 419808.33 | I21: ='Debt Schedule'!I30 -> 536541.9 | J21: =H21-I21 -> -116733.57 | K21: =IFERROR(H21/I21,"-") -> 0.78243345 | L21: =SUM($J$4:J21) -> -2059704.2
B22: 19 | C22: =EDATE(DATE(2024,1,1),18) -> 45839 | D22: =IF(19>Inputs!$C$74,"Expired",IF(Inputs!$C$68>0,IF(19<Inputs!$C$68,"Paying",IF(19<Inputs!$C$68+Inputs!$C$85,"Default","Re-Lease")),"Paying")) -> Paying | E22: =IF(D22="Expired",0,IF(D22="Default",0,IF(D22="Re-Lease",Inputs!$C$71*Inputs!$C$86,Inputs!$C$73))) -> 561600 | F22: =(Inputs!$C$82*(1+Inputs!$C$83)^1)/12+IF(19=Inputs!$C$68,Inputs!$C$69/12,0) -> 87979.167 | G22: =IF(D22="Expired",0,(IF(Inputs!$C$5=1,(Inputs!C38+Inputs!C39)/12,(Inputs!F38+Inputs!F39)/12)*(1+Inputs!$C$83)^1)) -> 53812.5 | H22: =E22-F22-G22 -> 419808.33 | I22: ='Debt Schedule'!I31 -> 536541.9 | J22: =H22-I22 -> -116733.57 | K22: =IFERROR(H22/I22,"-") -> 0.78243345 | L22: =SUM($J$4:J22) -> -2176437.8
B23: 20 | C23: =EDATE(DATE(2024,1,1),19) -> 45870 | D23: =IF(20>Inputs!$C$74,"Expired",IF(Inputs!$C$68>0,IF(20<Inputs!$C$68,"Paying",IF(20<Inputs!$C$68+Inputs!$C$85,"Default","Re-Lease")),"Paying")) -> Paying | E23: =IF(D23="Expired",0,IF(D23="Default",0,IF(D23="Re-Lease",Inputs!$C$71*Inputs!$C$86,Inputs!$C$73))) -> 561600 | F23: =(Inputs!$C$82*(1+Inputs!$C$83)^1)/12+IF(20=Inputs!$C$68,Inputs!$C$69/12,0) -> 87979.167 | G23: =IF(D23="Expired",0,(IF(Inputs!$C$5=1,(Inputs!C38+Inputs!C39)/12,(Inputs!F38+Inputs!F39)/12)*(1+Inputs!$C$83)^1)) -> 53812.5 | H23: =E23-F23-G23 -> 419808.33 | I23: ='Debt Schedule'!I32 -> 536541.9 | J23: =H23-I23 -> -116733.57 | K23: =IFERROR(H23/I23,"-") -> 0.78243345 | L23: =SUM($J$4:J23) -> -2293171.4
B24: 21 | C24: =EDATE(DATE(2024,1,1),20) -> 45901 | D24: =IF(21>Inputs!$C$74,"Expired",IF(Inputs!$C$68>0,IF(21<Inputs!$C$68,"Paying",IF(21<Inputs!$C$68+Inputs!$C$85,"Default","Re-Lease")),"Paying")) -> Paying | E24: =IF(D24="Expired",0,IF(D24="Default",0,IF(D24="Re-Lease",Inputs!$C$71*Inputs!$C$86,Inputs!$C$73))) -> 561600 | F24: =(Inputs!$C$82*(1+Inputs!$C$83)^1)/12+IF(21=Inputs!$C$68,Inputs!$C$69/12,0) -> 87979.167 | G24: =IF(D24="Expired",0,(IF(Inputs!$C$5=1,(Inputs!C38+Inputs!C39)/12,(Inputs!F38+Inputs!F39)/12)*(1+Inputs!$C$83)^1)) -> 53812.5 | H24: =E24-F24-G24 -> 419808.33 | I24: ='Debt Schedule'!I33 -> 536541.9 | J24: =H24-I24 -> -116733.57 | K24: =IFERROR(H24/I24,"-") -> 0.78243345 | L24: =SUM($J$4:J24) -> -2409904.9
B25: 22 | C25: =EDATE(DATE(2024,1,1),21) -> 45931 | D25: =IF(22>Inputs!$C$74,"Expired",IF(Inputs!$C$68>0,IF(22<Inputs!$C$68,"Paying",IF(22<Inputs!$C$68+Inputs!$C$85,"Default","Re-Lease")),"Paying")) -> Paying | E25: =IF(D25="Expired",0,IF(D25="Default",0,IF(D25="Re-Lease",Inputs!$C$71*Inputs!$C$86,Inputs!$C$73))) -> 561600 | F25: =(Inputs!$C$82*(1+Inputs!$C$83)^1)/12+IF(22=Inputs!$C$68,Inputs!$C$69/12,0) -> 87979.167 | G25: =IF(D25="Expired",0,(IF(Inputs!$C$5=1,(Inputs!C38+Inputs!C39)/12,(Inputs!F38+Inputs!F39)/12)*(1+Inputs!$C$83)^1)) -> 53812.5 | H25: =E25-F25-G25 -> 419808.33 | I25: ='Debt Schedule'!I34 -> 536541.9 | J25: =H25-I25 -> -116733.57 | K25: =IFERROR(H25/I25,"-") -> 0.78243345 | L25: =SUM($J$4:J25) -> -2526638.5
B26: 23 | C26: =EDATE(DATE(2024,1,1),22) -> 45962 | D26: =IF(23>Inputs!$C$74,"Expired",IF(Inputs!$C$68>0,IF(23<Inputs!$C$68,"Paying",IF(23<Inputs!$C$68+Inputs!$C$85,"Default","Re-Lease")),"Paying")) -> Paying | E26: =IF(D26="Expired",0,IF(D26="Default",0,IF(D26="Re-Lease",Inputs!$C$71*Inputs!$C$86,Inputs!$C$73))) -> 561600 | F26: =(Inputs!$C$82*(1+Inputs!$C$83)^1)/12+IF(23=Inputs!$C$68,Inputs!$C$69/12,0) -> 87979.167 | G26: =IF(D26="Expired",0,(IF(Inputs!$C$5=1,(Inputs!C38+Inputs!C39)/12,(Inputs!F38+Inputs!F39)/12)*(1+Inputs!$C$83)^1)) -> 53812.5 | H26: =E26-F26-G26 -> 419808.33 | I26: ='Debt Schedule'!I35 -> 536541.9 | J26: =H26-I26 -> -116733.57 | K26: =IFERROR(H26/I26,"-") -> 0.78243345 | L26: =SUM($J$4:J26) -> -2643372.1
B27: 24 | C27: =EDATE(DATE(2024,1,1),23) -> 45992 | D27: =IF(24>Inputs!$C$74,"Expired",IF(Inputs!$C$68>0,IF(24<Inputs!$C$68,"Paying",IF(24<Inputs!$C$68+Inputs!$C$85,"Default","Re-Lease")),"Paying")) -> Paying | E27: =IF(D27="Expired",0,IF(D27="Default",0,IF(D27="Re-Lease",Inputs!$C$71*Inputs!$C$86,Inputs!$C$73))) -> 561600 | F27: =(Inputs!$C$82*(1+Inputs!$C$83)^1)/12+IF(24=Inputs!$C$68,Inputs!$C$69/12,0) -> 87979.167 | G27: =IF(D27="Expired",0,(IF(Inputs!$C$5=1,(Inputs!C38+Inputs!C39)/12,(Inputs!F38+Inputs!F39)/12)*(1+Inputs!$C$83)^1)) -> 53812.5 | H27: =E27-F27-G27 -> 419808.33 | I27: ='Debt Schedule'!I36 -> 536541.9 | J27: =H27-I27 -> -116733.57 | K27: =IFERROR(H27/I27,"-") -> 0.78243345 | L27: =SUM($J$4:J27) -> -2760105.6
B28: 25 | C28: =EDATE(DATE(2024,1,1),24) -> 46023 | D28: =IF(25>Inputs!$C$74,"Expired",IF(Inputs!$C$68>0,IF(25<Inputs!$C$68,"Paying",IF(25<Inputs!$C$68+Inputs!$C$85,"Default","Re-Lease")),"Paying")) -> Paying | E28: =IF(D28="Expired",0,IF(D28="Default",0,IF(D28="Re-Lease",Inputs!$C$71*Inputs!$C$86,Inputs!$C$73))) -> 561600 | F28: =(Inputs!$C$82*(1+Inputs!$C$83)^2)/12+IF(25=Inputs!$C$68,Inputs!$C$69/12,0) -> 90178.646 | G28: =IF(D28="Expired",0,(IF(Inputs!$C$5=1,(Inputs!C38+Inputs!C39)/12,(Inputs!F38+Inputs!F39)/12)*(1+Inputs!$C$83)^2)) -> 55157.812 | H28: =E28-F28-G28 -> 416263.54 | I28: ='Debt Schedule'!I37 -> 536541.9 | J28: =H28-I28 -> -120278.36 | K28: =IFERROR(H28/I28,"-") -> 0.77582672 | L28: =SUM($J$4:J28) -> -2880384
B29: 26 | C29: =EDATE(DATE(2024,1,1),25) -> 46054 | D29: =IF(26>Inputs!$C$74,"Expired",IF(Inputs!$C$68>0,IF(26<Inputs!$C$68,"Paying",IF(26<Inputs!$C$68+Inputs!$C$85,"Default","Re-Lease")),"Paying")) -> Paying | E29: =IF(D29="Expired",0,IF(D29="Default",0,IF(D29="Re-Lease",Inputs!$C$71*Inputs!$C$86,Inputs!$C$73))) -> 561600 | F29: =(Inputs!$C$82*(1+Inputs!$C$83)^2)/12+IF(26=Inputs!$C$68,Inputs!$C$69/12,0) -> 90178.646 | G29: =IF(D29="Expired",0,(IF(Inputs!$C$5=1,(Inputs!C38+Inputs!C39)/12,(Inputs!F38+Inputs!F39)/12)*(1+Inputs!$C$83)^2)) -> 55157.812 | H29: =E29-F29-G29 -> 416263.54 | I29: ='Debt Schedule'!I38 -> 536541.9 | J29: =H29-I29 -> -120278.36 | K29: =IFERROR(H29/I29,"-") -> 0.77582672 | L29: =SUM($J$4:J29) -> -3000662.3
B30: 27 | C30: =EDATE(DATE(2024,1,1),26) -> 46082 | D30: =IF(27>Inputs!$C$74,"Expired",IF(Inputs!$C$68>0,IF(27<Inputs!$C$68,"Paying",IF(27<Inputs!$C$68+Inputs!$C$85,"Default","Re-Lease")),"Paying")) -> Paying | E30: =IF(D30="Expired",0,IF(D30="Default",0,IF(D30="Re-Lease",Inputs!$C$71*Inputs!$C$86,Inputs!$C$73))) -> 561600 | F30: =(Inputs!$C$82*(1+Inputs!$C$83)^2)/12+IF(27=Inputs!$C$68,Inputs!$C$69/12,0) -> 90178.646 | G30: =IF(D30="Expired",0,(IF(Inputs!$C$5=1,(Inputs!C38+Inputs!C39)/12,(Inputs!F38+Inputs!F39)/12)*(1+Inputs!$C$83)^2)) -> 55157.812 | H30: =E30-F30-G30 -> 416263.54 | I30: ='Debt Schedule'!I39 -> 536541.9 | J30: =H30-I30 -> -120278.36 | K30: =IFERROR(H30/I30,"-") -> 0.77582672 | L30: =SUM($J$4:J30) -> -3120940.7
B31: 28 | C31: =EDATE(DATE(2024,1,1),27) -> 46113 | D31: =IF(28>Inputs!$C$74,"Expired",IF(Inputs!$C$68>0,IF(28<Inputs!$C$68,"Paying",IF(28<Inputs!$C$68+Inputs!$C$85,"Default","Re-Lease")),"Paying")) -> Paying | E31: =IF(D31="Expired",0,IF(D31="Default",0,IF(D31="Re-Lease",Inputs!$C$71*Inputs!$C$86,Inputs!$C$73))) -> 561600 | F31: =(Inputs!$C$82*(1+Inputs!$C$83)^2)/12+IF(28=Inputs!$C$68,Inputs!$C$69/12,0) -> 90178.646 | G31: =IF(D31="Expired",0,(IF(Inputs!$C$5=1,(Inputs!C38+Inputs!C39)/12,(Inputs!F38+Inputs!F39)/12)*(1+Inputs!$C$83)^2)) -> 55157.812 | H31: =E31-F31-G31 -> 416263.54 | I31: ='Debt Schedule'!I40 -> 536541.9 | J31: =H31-I31 -> -120278.36 | K31: =IFERROR(H31/I31,"-") -> 0.77582672 | L31: =SUM($J$4:J31) -> -3241219.1
B32: 29 | C32: =EDATE(DATE(2024,1,1),28) -> 46143 | D32: =IF(29>Inputs!$C$74,"Expired",IF(Inputs!$C$68>0,IF(29<Inputs!$C$68,"Paying",IF(29<Inputs!$C$68+Inputs!$C$85,"Default","Re-Lease")),"Paying")) -> Paying | E32: =IF(D32="Expired",0,IF(D32="Default",0,IF(D32="Re-Lease",Inputs!$C$71*Inputs!$C$86,Inputs!$C$73))) -> 561600 | F32: =(Inputs!$C$82*(1+Inputs!$C$83)^2)/12+IF(29=Inputs!$C$68,Inputs!$C$69/12,0) -> 90178.646 | G32: =IF(D32="Expired",0,(IF(Inputs!$C$5=1,(Inputs!C38+Inputs!C39)/12,(Inputs!F38+Inputs!F39)/12)*(1+Inputs!$C$83)^2)) -> 55157.812 | H32: =E32-F32-G32 -> 416263.54 | I32: ='Debt Schedule'!I41 -> 536541.9 | J32: =H32-I32 -> -120278.36 | K32: =IFERROR(H32/I32,"-") -> 0.77582672 | L32: =SUM($J$4:J32) -> -3361497.4
B33: 30 | C33: =EDATE(DATE(2024,1,1),29) -> 46174 | D33: =IF(30>Inputs!$C$74,"Expired",IF(Inputs!$C$68>0,IF(30<Inputs!$C$68,"Paying",IF(30<Inputs!$C$68+Inputs!$C$85,"Default","Re-Lease")),"Paying")) -> Paying | E33: =IF(D33="Expired",0,IF(D33="Default",0,IF(D33="Re-Lease",Inputs!$C$71*Inputs!$C$86,Inputs!$C$73))) -> 561600 | F33: =(Inputs!$C$82*(1+Inputs!$C$83)^2)/12+IF(30=Inputs!$C$68,Inputs!$C$69/12,0) -> 90178.646 | G33: =IF(D33="Expired",0,(IF(Inputs!$C$5=1,(Inputs!C38+Inputs!C39)/12,(Inputs!F38+Inputs!F39)/12)*(1+Inputs!$C$83)^2)) -> 55157.812 | H33: =E33-F33-G33 -> 416263.54 | I33: ='Debt Schedule'!I42 -> 536541.9 | J33: =H33-I33 -> -120278.36 | K33: =IFERROR(H33/I33,"-") -> 0.77582672 | L33: =SUM($J$4:J33) -> -3481775.8
B34: 31 | C34: =EDATE(DATE(2024,1,1),30) -> 46204 | D34: =IF(31>Inputs!$C$74,"Expired",IF(Inputs!$C$68>0,IF(31<Inputs!$C$68,"Paying",IF(31<Inputs!$C$68+Inputs!$C$85,"Default","Re-Lease")),"Paying")) -> Paying | E34: =IF(D34="Expired",0,IF(D34="Default",0,IF(D34="Re-Lease",Inputs!$C$71*Inputs!$C$86,Inputs!$C$73))) -> 561600 | F34: =(Inputs!$C$82*(1+Inputs!$C$83)^2)/12+IF(31=Inputs!$C$68,Inputs!$C$69/12,0) -> 90178.646 | G34: =IF(D34="Expired",0,(IF(Inputs!$C$5=1,(Inputs!C38+Inputs!C39)/12,(Inputs!F38+Inputs!F39)/12)*(1+Inputs!$C$83)^2)) -> 55157.812 | H34: =E34-F34-G34 -> 416263.54 | I34: ='Debt Schedule'!I43 -> 536541.9 | J34: =H34-I34 -> -120278.36 | K34: =IFERROR(H34/I34,"-") -> 0.77582672 | L34: =SUM($J$4:J34) -> -3602054.1
B35: 32 | C35: =EDATE(DATE(2024,1,1),31) -> 46235 | D35: =IF(32>Inputs!$C$74,"Expired",IF(Inputs!$C$68>0,IF(32<Inputs!$C$68,"Paying",IF(32<Inputs!$C$68+Inputs!$C$85,"Default","Re-Lease")),"Paying")) -> Paying | E35: =IF(D35="Expired",0,IF(D35="Default",0,IF(D35="Re-Lease",Inputs!$C$71*Inputs!$C$86,Inputs!$C$73))) -> 561600 | F35: =(Inputs!$C$82*(1+Inputs!$C$83)^2)/12+IF(32=Inputs!$C$68,Inputs!$C$69/12,0) -> 90178.646 | G35: =IF(D35="Expired",0,(IF(Inputs!$C$5=1,(Inputs!C38+Inputs!C39)/12,(Inputs!F38+Inputs!F39)/12)*(1+Inputs!$C$83)^2)) -> 55157.812 | H35: =E35-F35-G35 -> 416263.54 | I35: ='Debt Schedule'!I44 -> 536541.9 | J35: =H35-I35 -> -120278.36 | K35: =IFERROR(H35/I35,"-") -> 0.77582672 | L35: =SUM($J$4:J35) -> -3722332.5
B36: 33 | C36: =EDATE(DATE(2024,1,1),32) -> 46266 | D36: =IF(33>Inputs!$C$74,"Expired",IF(Inputs!$C$68>0,IF(33<Inputs!$C$68,"Paying",IF(33<Inputs!$C$68+Inputs!$C$85,"Default","Re-Lease")),"Paying")) -> Paying | E36: =IF(D36="Expired",0,IF(D36="Default",0,IF(D36="Re-Lease",Inputs!$C$71*Inputs!$C$86,Inputs!$C$73))) -> 561600 | F36: =(Inputs!$C$82*(1+Inputs!$C$83)^2)/12+IF(33=Inputs!$C$68,Inputs!$C$69/12,0) -> 90178.646 | G36: =IF(D36="Expired",0,(IF(Inputs!$C$5=1,(Inputs!C38+Inputs!C39)/12,(Inputs!F38+Inputs!F39)/12)*(1+Inputs!$C$83)^2)) -> 55157.812 | H36: =E36-F36-G36 -> 416263.54 | I36: ='Debt Schedule'!I45 -> 536541.9 | J36: =H36-I36 -> -120278.36 | K36: =IFERROR(H36/I36,"-") -> 0.77582672 | L36: =SUM($J$4:J36) -> -3842610.9
B37: 34 | C37: =EDATE(DATE(2024,1,1),33) -> 46296 | D37: =IF(34>Inputs!$C$74,"Expired",IF(Inputs!$C$68>0,IF(34<Inputs!$C$68,"Paying",IF(34<Inputs!$C$68+Inputs!$C$85,"Default","Re-Lease")),"Paying")) -> Paying | E37: =IF(D37="Expired",0,IF(D37="Default",0,IF(D37="Re-Lease",Inputs!$C$71*Inputs!$C$86,Inputs!$C$73))) -> 561600 | F37: =(Inputs!$C$82*(1+Inputs!$C$83)^2)/12+IF(34=Inputs!$C$68,Inputs!$C$69/12,0) -> 90178.646 | G37: =IF(D37="Expired",0,(IF(Inputs!$C$5=1,(Inputs!C38+Inputs!C39)/12,(Inputs!F38+Inputs!F39)/12)*(1+Inputs!$C$83)^2)) -> 55157.812 | H37: =E37-F37-G37 -> 416263.54 | I37: ='Debt Schedule'!I46 -> 536541.9 | J37: =H37-I37 -> -120278.36 | K37: =IFERROR(H37/I37,"-") -> 0.77582672 | L37: =SUM($J$4:J37) -> -3962889.2
B38: 35 | C38: =EDATE(DATE(2024,1,1),34) -> 46327 | D38: =IF(35>Inputs!$C$74,"Expired",IF(Inputs!$C$68>0,IF(35<Inputs!$C$68,"Paying",IF(35<Inputs!$C$68+Inputs!$C$85,"Default","Re-Lease")),"Paying")) -> Paying | E38: =IF(D38="Expired",0,IF(D38="Default",0,IF(D38="Re-Lease",Inputs!$C$71*Inputs!$C$86,Inputs!$C$73))) -> 561600 | F38: =(Inputs!$C$82*(1+Inputs!$C$83)^2)/12+IF(35=Inputs!$C$68,Inputs!$C$69/12,0) -> 90178.646 | G38: =IF(D38="Expired",0,(IF(Inputs!$C$5=1,(Inputs!C38+Inputs!C39)/12,(Inputs!F38+Inputs!F39)/12)*(1+Inputs!$C$83)^2)) -> 55157.812 | H38: =E38-F38-G38 -> 416263.54 | I38: ='Debt Schedule'!I47 -> 536541.9 | J38: =H38-I38 -> -120278.36 | K38: =IFERROR(H38/I38,"-") -> 0.77582672 | L38: =SUM($J$4:J38) -> -4083167.6
B39: 36 | C39: =EDATE(DATE(2024,1,1),35) -> 46357 | D39: =IF(36>Inputs!$C$74,"Expired",IF(Inputs!$C$68>0,IF(36<Inputs!$C$68,"Paying",IF(36<Inputs!$C$68+Inputs!$C$85,"Default","Re-Lease")),"Paying")) -> Paying | E39: =IF(D39="Expired",0,IF(D39="Default",0,IF(D39="Re-Lease",Inputs!$C$71*Inputs!$C$86,Inputs!$C$73))) -> 561600 | F39: =(Inputs!$C$82*(1+Inputs!$C$83)^2)/12+IF(36=Inputs!$C$68,Inputs!$C$69/12,0) -> 90178.646 | G39: =IF(D39="Expired",0,(IF(Inputs!$C$5=1,(Inputs!C38+Inputs!C39)/12,(Inputs!F38+Inputs!F39)/12)*(1+Inputs!$C$83)^2)) -> 55157.812 | H39: =E39-F39-G39 -> 416263.54 | I39: ='Debt Schedule'!I48 -> 536541.9 | J39: =H39-I39 -> -120278.36 | K39: =IFERROR(H39/I39,"-") -> 0.77582672 | L39: =SUM($J$4:J39) -> -4203445.9
B40: 37 | C40: =EDATE(DATE(2024,1,1),36) -> 46388 | D40: =IF(37>Inputs!$C$74,"Expired",IF(Inputs!$C$68>0,IF(37<Inputs!$C$68,"Paying",IF(37<Inputs!$C$68+Inputs!$C$85,"Default","Re-Lease")),"Paying")) -> Paying | E40: =IF(D40="Expired",0,IF(D40="Default",0,IF(D40="Re-Lease",Inputs!$C$71*Inputs!$C$86,Inputs!$C$73))) -> 561600 | F40: =(Inputs!$C$82*(1+Inputs!$C$83)^3)/12+IF(37=Inputs!$C$68,Inputs!$C$69/12,0) -> 92433.112 | G40: =IF(D40="Expired",0,(IF(Inputs!$C$5=1,(Inputs!C38+Inputs!C39)/12,(Inputs!F38+Inputs!F39)/12)*(1+Inputs!$C$83)^3)) -> 56536.758 | H40: =E40-F40-G40 -> 412630.13 | I40: ='Debt Schedule'!I49 -> 536541.9 | J40: =H40-I40 -> -123911.77 | K40: =IFERROR(H40/I40,"-") -> 0.76905481 | L40: =SUM($J$4:J40) -> -4327357.7
B41: 38 | C41: =EDATE(DATE(2024,1,1),37) -> 46419 | D41: =IF(38>Inputs!$C$74,"Expired",IF(Inputs!$C$68>0,IF(38<Inputs!$C$68,"Paying",IF(38<Inputs!$C$68+Inputs!$C$85,"Default","Re-Lease")),"Paying")) -> Paying | E41: =IF(D41="Expired",0,IF(D41="Default",0,IF(D41="Re-Lease",Inputs!$C$71*Inputs!$C$86,Inputs!$C$73))) -> 561600 | F41: =(Inputs!$C$82*(1+Inputs!$C$83)^3)/12+IF(38=Inputs!$C$68,Inputs!$C$69/12,0) -> 92433.112 | G41: =IF(D41="Expired",0,(IF(Inputs!$C$5=1,(Inputs!C38+Inputs!C39)/12,(Inputs!F38+Inputs!F39)/12)*(1+Inputs!$C$83)^3)) -> 56536.758 | H41: =E41-F41-G41 -> 412630.13 | I41: ='Debt Schedule'!I50 -> 536541.9 | J41: =H41-I41 -> -123911.77 | K41: =IFERROR(H41/I41,"-") -> 0.76905481 | L41: =SUM($J$4:J41) -> -4451269.5
B42: 39 | C42: =EDATE(DATE(2024,1,1),38) -> 46447 | D42: =IF(39>Inputs!$C$74,"Expired",IF(Inputs!$C$68>0,IF(39<Inputs!$C$68,"Paying",IF(39<Inputs!$C$68+Inputs!$C$85,"Default","Re-Lease")),"Paying")) -> Paying | E42: =IF(D42="Expired",0,IF(D42="Default",0,IF(D42="Re-Lease",Inputs!$C$71*Inputs!$C$86,Inputs!$C$73))) -> 561600 | F42: =(Inputs!$C$82*(1+Inputs!$C$83)^3)/12+IF(39=Inputs!$C$68,Inputs!$C$69/12,0) -> 92433.112 | G42: =IF(D42="Expired",0,(IF(Inputs!$C$5=1,(Inputs!C38+Inputs!C39)/12,(Inputs!F38+Inputs!F39)/12)*(1+Inputs!$C$83)^3)) -> 56536.758 | H42: =E42-F42-G42 -> 412630.13 | I42: ='Debt Schedule'!I51 -> 536541.9 | J42: =H42-I42 -> -123911.77 | K42: =IFERROR(H42/I42,"-") -> 0.76905481 | L42: =SUM($J$4:J42) -> -4575181.2
B43: 40 | C43: =EDATE(DATE(2024,1,1),39) -> 46478 | D43: =IF(40>Inputs!$C$74,"Expired",IF(Inputs!$C$68>0,IF(40<Inputs!$C$68,"Paying",IF(40<Inputs!$C$68+Inputs!$C$85,"Default","Re-Lease")),"Paying")) -> Paying | E43: =IF(D43="Expired",0,IF(D43="Default",0,IF(D43="Re-Lease",Inputs!$C$71*Inputs!$C$86,Inputs!$C$73))) -> 561600 | F43: =(Inputs!$C$82*(1+Inputs!$C$83)^3)/12+IF(40=Inputs!$C$68,Inputs!$C$69/12,0) -> 92433.112 | G43: =IF(D43="Expired",0,(IF(Inputs!$C$5=1,(Inputs!C38+Inputs!C39)/12,(Inputs!F38+Inputs!F39)/12)*(1+Inputs!$C$83)^3)) -> 56536.758 | H43: =E43-F43-G43 -> 412630.13 | I43: ='Debt Schedule'!I52 -> 536541.9 | J43: =H43-I43 -> -123911.77 | K43: =IFERROR(H43/I43,"-") -> 0.76905481 | L43: =SUM($J$4:J43) -> -4699093
B44: 41 | C44: =EDATE(DATE(2024,1,1),40) -> 46508 | D44: =IF(41>Inputs!$C$74,"Expired",IF(Inputs!$C$68>0,IF(41<Inputs!$C$68,"Paying",IF(41<Inputs!$C$68+Inputs!$C$85,"Default","Re-Lease")),"Paying")) -> Paying | E44: =IF(D44="Expired",0,IF(D44="Default",0,IF(D44="Re-Lease",Inputs!$C$71*Inputs!$C$86,Inputs!$C$73))) -> 561600 | F44: =(Inputs!$C$82*(1+Inputs!$C$83)^3)/12+IF(41=Inputs!$C$68,Inputs!$C$69/12,0) -> 92433.112 | G44: =IF(D44="Expired",0,(IF(Inputs!$C$5=1,(Inputs!C38+Inputs!C39)/12,(Inputs!F38+Inputs!F39)/12)*(1+Inputs!$C$83)^3)) -> 56536.758 | H44: =E44-F44-G44 -> 412630.13 | I44: ='Debt Schedule'!I53 -> 536541.9 | J44: =H44-I44 -> -123911.77 | K44: =IFERROR(H44/I44,"-") -> 0.76905481 | L44: =SUM($J$4:J44) -> -4823004.8
B45: 42 | C45: =EDATE(DATE(2024,1,1),41) -> 46539 | D45: =IF(42>Inputs!$C$74,"Expired",IF(Inputs!$C$68>0,IF(42<Inputs!$C$68,"Paying",IF(42<Inputs!$C$68+Inputs!$C$85,"Default","Re-Lease")),"Paying")) -> Paying | E45: =IF(D45="Expired",0,IF(D45="Default",0,IF(D45="Re-Lease",Inputs!$C$71*Inputs!$C$86,Inputs!$C$73))) -> 561600 | F45: =(Inputs!$C$82*(1+Inputs!$C$83)^3)/12+IF(42=Inputs!$C$68,Inputs!$C$69/12,0) -> 92433.112 | G45: =IF(D45="Expired",0,(IF(Inputs!$C$5=1,(Inputs!C38+Inputs!C39)/12,(Inputs!F38+Inputs!F39)/12)*(1+Inputs!$C$83)^3)) -> 56536.758 | H45: =E45-F45-G45 -> 412630.13 | I45: ='Debt Schedule'!I54 -> 536541.9 | J45: =H45-I45 -> -123911.77 | K45: =IFERROR(H45/I45,"-") -> 0.76905481 | L45: =SUM($J$4:J45) -> -4946916.6
B46: 43 | C46: =EDATE(DATE(2024,1,1),42) -> 46569 | D46: =IF(43>Inputs!$C$74,"Expired",IF(Inputs!$C$68>0,IF(43<Inputs!$C$68,"Paying",IF(43<Inputs!$C$68+Inputs!$C$85,"Default","Re-Lease")),"Paying")) -> Paying | E46: =IF(D46="Expired",0,IF(D46="Default",0,IF(D46="Re-Lease",Inputs!$C$71*Inputs!$C$86,Inputs!$C$73))) -> 561600 | F46: =(Inputs!$C$82*(1+Inputs!$C$83)^3)/12+IF(43=Inputs!$C$68,Inputs!$C$69/12,0) -> 92433.112 | G46: =IF(D46="Expired",0,(IF(Inputs!$C$5=1,(Inputs!C38+Inputs!C39)/12,(Inputs!F38+Inputs!F39)/12)*(1+Inputs!$C$83)^3)) -> 56536.758 | H46: =E46-F46-G46 -> 412630.13 | I46: ='Debt Schedule'!I55 -> 536541.9 | J46: =H46-I46 -> -123911.77 | K46: =IFERROR(H46/I46,"-") -> 0.76905481 | L46: =SUM($J$4:J46) -> -5070828.3
B47: 44 | C47: =EDATE(DATE(2024,1,1),43) -> 46600 | D47: =IF(44>Inputs!$C$74,"Expired",IF(Inputs!$C$68>0,IF(44<Inputs!$C$68,"Paying",IF(44<Inputs!$C$68+Inputs!$C$85,"Default","Re-Lease")),"Paying")) -> Paying | E47: =IF(D47="Expired",0,IF(D47="Default",0,IF(D47="Re-Lease",Inputs!$C$71*Inputs!$C$86,Inputs!$C$73))) -> 561600 | F47: =(Inputs!$C$82*(1+Inputs!$C$83)^3)/12+IF(44=Inputs!$C$68,Inputs!$C$69/12,0) -> 92433.112 | G47: =IF(D47="Expired",0,(IF(Inputs!$C$5=1,(Inputs!C38+Inputs!C39)/12,(Inputs!F38+Inputs!F39)/12)*(1+Inputs!$C$83)^3)) -> 56536.758 | H47: =E47-F47-G47 -> 412630.13 | I47: ='Debt Schedule'!I56 -> 536541.9 | J47: =H47-I47 -> -123911.77 | K47: =IFERROR(H47/I47,"-") -> 0.76905481 | L47: =SUM($J$4:J47) -> -5194740.1
B48: 45 | C48: =EDATE(DATE(2024,1,1),44) -> 46631 | D48: =IF(45>Inputs!$C$74,"Expired",IF(Inputs!$C$68>0,IF(45<Inputs!$C$68,"Paying",IF(45<Inputs!$C$68+Inputs!$C$85,"Default","Re-Lease")),"Paying")) -> Paying | E48: =IF(D48="Expired",0,IF(D48="Default",0,IF(D48="Re-Lease",Inputs!$C$71*Inputs!$C$86,Inputs!$C$73))) -> 561600 | F48: =(Inputs!$C$82*(1+Inputs!$C$83)^3)/12+IF(45=Inputs!$C$68,Inputs!$C$69/12,0) -> 92433.112 | G48: =IF(D48="Expired",0,(IF(Inputs!$C$5=1,(Inputs!C38+Inputs!C39)/12,(Inputs!F38+Inputs!F39)/12)*(1+Inputs!$C$83)^3)) -> 56536.758 | H48: =E48-F48-G48 -> 412630.13 | I48: ='Debt Schedule'!I57 -> 536541.9 | J48: =H48-I48 -> -123911.77 | K48: =IFERROR(H48/I48,"-") -> 0.76905481 | L48: =SUM($J$4:J48) -> -5318651.9
B49: 46 | C49: =EDATE(DATE(2024,1,1),45) -> 46661 | D49: =IF(46>Inputs!$C$74,"Expired",IF(Inputs!$C$68>0,IF(46<Inputs!$C$68,"Paying",IF(46<Inputs!$C$68+Inputs!$C$85,"Default","Re-Lease")),"Paying")) -> Paying | E49: =IF(D49="Expired",0,IF(D49="Default",0,IF(D49="Re-Lease",Inputs!$C$71*Inputs!$C$86,Inputs!$C$73))) -> 561600 | F49: =(Inputs!$C$82*(1+Inputs!$C$83)^3)/12+IF(46=Inputs!$C$68,Inputs!$C$69/12,0) -> 92433.112 | G49: =IF(D49="Expired",0,(IF(Inputs!$C$5=1,(Inputs!C38+Inputs!C39)/12,(Inputs!F38+Inputs!F39)/12)*(1+Inputs!$C$83)^3)) -> 56536.758 | H49: =E49-F49-G49 -> 412630.13 | I49: ='Debt Schedule'!I58 -> 536541.9 | J49: =H49-I49 -> -123911.77 | K49: =IFERROR(H49/I49,"-") -> 0.76905481 | L49: =SUM($J$4:J49) -> -5442563.6
B50: 47 | C50: =EDATE(DATE(2024,1,1),46) -> 46692 | D50: =IF(47>Inputs!$C$74,"Expired",IF(Inputs!$C$68>0,IF(47<Inputs!$C$68,"Paying",IF(47<Inputs!$C$68+Inputs!$C$85,"Default","Re-Lease")),"Paying")) -> Paying | E50: =IF(D50="Expired",0,IF(D50="Default",0,IF(D50="Re-Lease",Inputs!$C$71*Inputs!$C$86,Inputs!$C$73))) -> 561600 | F50: =(Inputs!$C$82*(1+Inputs!$C$83)^3)/12+IF(47=Inputs!$C$68,Inputs!$C$69/12,0) -> 92433.112 | G50: =IF(D50="Expired",0,(IF(Inputs!$C$5=1,(Inputs!C38+Inputs!C39)/12,(Inputs!F38+Inputs!F39)/12)*(1+Inputs!$C$83)^3)) -> 56536.758 | H50: =E50-F50-G50 -> 412630.13 | I50: ='Debt Schedule'!I59 -> 536541.9 | J50: =H50-I50 -> -123911.77 | K50: =IFERROR(H50/I50,"-") -> 0.76905481 | L50: =SUM($J$4:J50) -> -5566475.4
B51: 48 | C51: =EDATE(DATE(2024,1,1),47) -> 46722 | D51: =IF(48>Inputs!$C$74,"Expired",IF(Inputs!$C$68>0,IF(48<Inputs!$C$68,"Paying",IF(48<Inputs!$C$68+Inputs!$C$85,"Default","Re-Lease")),"Paying")) -> Paying | E51: =IF(D51="Expired",0,IF(D51="Default",0,IF(D51="Re-Lease",Inputs!$C$71*Inputs!$C$86,Inputs!$C$73))) -> 561600 | F51: =(Inputs!$C$82*(1+Inputs!$C$83)^3)/12+IF(48=Inputs!$C$68,Inputs!$C$69/12,0) -> 92433.112 | G51: =IF(D51="Expired",0,(IF(Inputs!$C$5=1,(Inputs!C38+Inputs!C39)/12,(Inputs!F38+Inputs!F39)/12)*(1+Inputs!$C$83)^3)) -> 56536.758 | H51: =E51-F51-G51 -> 412630.13 | I51: ='Debt Schedule'!I60 -> 536541.9 | J51: =H51-I51 -> -123911.77 | K51: =IFERROR(H51/I51,"-") -> 0.76905481 | L51: =SUM($J$4:J51) -> -5690387.2
B52: 49 | C52: =EDATE(DATE(2024,1,1),48) -> 46753 | D52: =IF(49>Inputs!$C$74,"Expired",IF(Inputs!$C$68>0,IF(49<Inputs!$C$68,"Paying",IF(49<Inputs!$C$68+Inputs!$C$85,"Default","Re-Lease")),"Paying")) -> Paying | E52: =IF(D52="Expired",0,IF(D52="Default",0,IF(D52="Re-Lease",Inputs!$C$71*Inputs!$C$86,Inputs!$C$73))) -> 561600 | F52: =(Inputs!$C$82*(1+Inputs!$C$83)^4)/12+IF(49=Inputs!$C$68,Inputs!$C$69/12,0) -> 94743.94 | G52: =IF(D52="Expired",0,(IF(Inputs!$C$5=1,(Inputs!C38+Inputs!C39)/12,(Inputs!F38+Inputs!F39)/12)*(1+Inputs!$C$83)^4)) -> 57950.177 | H52: =E52-F52-G52 -> 408905.88 | I52: ='Debt Schedule'!I61 -> 536541.9 | J52: =H52-I52 -> -127636.02 | K52: =IFERROR(H52/I52,"-") -> 0.76211361 | L52: =SUM($J$4:J52) -> -5818023.2
B53: 50 | C53: =EDATE(DATE(2024,1,1),49) -> 46784 | D53: =IF(50>Inputs!$C$74,"Expired",IF(Inputs!$C$68>0,IF(50<Inputs!$C$68,"Paying",IF(50<Inputs!$C$68+Inputs!$C$85,"Default","Re-Lease")),"Paying")) -> Paying | E53: =IF(D53="Expired",0,IF(D53="Default",0,IF(D53="Re-Lease",Inputs!$C$71*Inputs!$C$86,Inputs!$C$73))) -> 561600 | F53: =(Inputs!$C$82*(1+Inputs!$C$83)^4)/12+IF(50=Inputs!$C$68,Inputs!$C$69/12,0) -> 94743.94 | G53: =IF(D53="Expired",0,(IF(Inputs!$C$5=1,(Inputs!C38+Inputs!C39)/12,(Inputs!F38+Inputs!F39)/12)*(1+Inputs!$C$83)^4)) -> 57950.177 | H53: =E53-F53-G53 -> 408905.88 | I53: ='Debt Schedule'!I62 -> 536541.9 | J53: =H53-I53 -> -127636.02 | K53: =IFERROR(H53/I53,"-") -> 0.76211361 | L53: =SUM($J$4:J53) -> -5945659.2
B54: 51 | C54: =EDATE(DATE(2024,1,1),50) -> 46813 | D54: =IF(51>Inputs!$C$74,"Expired",IF(Inputs!$C$68>0,IF(51<Inputs!$C$68,"Paying",IF(51<Inputs!$C$68+Inputs!$C$85,"Default","Re-Lease")),"Paying")) -> Paying | E54: =IF(D54="Expired",0,IF(D54="Default",0,IF(D54="Re-Lease",Inputs!$C$71*Inputs!$C$86,Inputs!$C$73))) -> 561600 | F54: =(Inputs!$C$82*(1+Inputs!$C$83)^4)/12+IF(51=Inputs!$C$68,Inputs!$C$69/12,0) -> 94743.94 | G54: =IF(D54="Expired",0,(IF(Inputs!$C$5=1,(Inputs!C38+Inputs!C39)/12,(Inputs!F38+Inputs!F39)/12)*(1+Inputs!$C$83)^4)) -> 57950.177 | H54: =E54-F54-G54 -> 408905.88 | I54: ='Debt Schedule'!I63 -> 536541.9 | J54: =H54-I54 -> -127636.02 | K54: =IFERROR(H54/I54,"-") -> 0.76211361 | L54: =SUM($J$4:J54) -> -6073295.2
B55: 52 | C55: =EDATE(DATE(2024,1,1),51) -> 46844 | D55: =IF(52>Inputs!$C$74,"Expired",IF(Inputs!$C$68>0,IF(52<Inputs!$C$68,"Paying",IF(52<Inputs!$C$68+Inputs!$C$85,"Default","Re-Lease")),"Paying")) -> Paying | E55: =IF(D55="Expired",0,IF(D55="Default",0,IF(D55="Re-Lease",Inputs!$C$71*Inputs!$C$86,Inputs!$C$73))) -> 561600 | F55: =(Inputs!$C$82*(1+Inputs!$C$83)^4)/12+IF(52=Inputs!$C$68,Inputs!$C$69/12,0) -> 94743.94 | G55: =IF(D55="Expired",0,(IF(Inputs!$C$5=1,(Inputs!C38+Inputs!C39)/12,(Inputs!F38+Inputs!F39)/12)*(1+Inputs!$C$83)^4)) -> 57950.177 | H55: =E55-F55-G55 -> 408905.88 | I55: ='Debt Schedule'!I64 -> 536541.9 | J55: =H55-I55 -> -127636.02 | K55: =IFERROR(H55/I55,"-") -> 0.76211361 | L55: =SUM($J$4:J55) -> -6200931.3
B56: 53 | C56: =EDATE(DATE(2024,1,1),52) -> 46874 | D56: =IF(53>Inputs!$C$74,"Expired",IF(Inputs!$C$68>0,IF(53<Inputs!$C$68,"Paying",IF(53<Inputs!$C$68+Inputs!$C$85,"Default","Re-Lease")),"Paying")) -> Paying | E56: =IF(D56="Expired",0,IF(D56="Default",0,IF(D56="Re-Lease",Inputs!$C$71*Inputs!$C$86,Inputs!$C$73))) -> 561600 | F56: =(Inputs!$C$82*(1+Inputs!$C$83)^4)/12+IF(53=Inputs!$C$68,Inputs!$C$69/12,0) -> 94743.94 | G56: =IF(D56="Expired",0,(IF(Inputs!$C$5=1,(Inputs!C38+Inputs!C39)/12,(Inputs!F38+Inputs!F39)/12)*(1+Inputs!$C$83)^4)) -> 57950.177 | H56: =E56-F56-G56 -> 408905.88 | I56: ='Debt Schedule'!I65 -> 536541.9 | J56: =H56-I56 -> -127636.02 | K56: =IFERROR(H56/I56,"-") -> 0.76211361 | L56: =SUM($J$4:J56) -> -6328567.3
B57: 54 | C57: =EDATE(DATE(2024,1,1),53) -> 46905 | D57: =IF(54>Inputs!$C$74,"Expired",IF(Inputs!$C$68>0,IF(54<Inputs!$C$68,"Paying",IF(54<Inputs!$C$68+Inputs!$C$85,"Default","Re-Lease")),"Paying")) -> Paying | E57: =IF(D57="Expired",0,IF(D57="Default",0,IF(D57="Re-Lease",Inputs!$C$71*Inputs!$C$86,Inputs!$C$73))) -> 561600 | F57: =(Inputs!$C$82*(1+Inputs!$C$83)^4)/12+IF(54=Inputs!$C$68,Inputs!$C$69/12,0) -> 94743.94 | G57: =IF(D57="Expired",0,(IF(Inputs!$C$5=1,(Inputs!C38+Inputs!C39)/12,(Inputs!F38+Inputs!F39)/12)*(1+Inputs!$C$83)^4)) -> 57950.177 | H57: =E57-F57-G57 -> 408905.88 | I57: ='Debt Schedule'!I66 -> 536541.9 | J57: =H57-I57 -> -127636.02 | K57: =IFERROR(H57/I57,"-") -> 0.76211361 | L57: =SUM($J$4:J57) -> -6456203.3
B58: 55 | C58: =EDATE(DATE(2024,1,1),54) -> 46935 | D58: =IF(55>Inputs!$C$74,"Expired",IF(Inputs!$C$68>0,IF(55<Inputs!$C$68,"Paying",IF(55<Inputs!$C$68+Inputs!$C$85,"Default","Re-Lease")),"Paying")) -> Paying | E58: =IF(D58="Expired",0,IF(D58="Default",0,IF(D58="Re-Lease",Inputs!$C$71*Inputs!$C$86,Inputs!$C$73))) -> 561600 | F58: =(Inputs!$C$82*(1+Inputs!$C$83)^4)/12+IF(55=Inputs!$C$68,Inputs!$C$69/12,0) -> 94743.94 | G58: =IF(D58="Expired",0,(IF(Inputs!$C$5=1,(Inputs!C38+Inputs!C39)/12,(Inputs!F38+Inputs!F39)/12)*(1+Inputs!$C$83)^4)) -> 57950.177 | H58: =E58-F58-G58 -> 408905.88 | I58: ='Debt Schedule'!I67 -> 536541.9 | J58: =H58-I58 -> -127636.02 | K58: =IFERROR(H58/I58,"-") -> 0.76211361 | L58: =SUM($J$4:J58) -> -6583839.3
B59: 56 | C59: =EDATE(DATE(2024,1,1),55) -> 46966 | D59: =IF(56>Inputs!$C$74,"Expired",IF(Inputs!$C$68>0,IF(56<Inputs!$C$68,"Paying",IF(56<Inputs!$C$68+Inputs!$C$85,"Default","Re-Lease")),"Paying")) -> Paying | E59: =IF(D59="Expired",0,IF(D59="Default",0,IF(D59="Re-Lease",Inputs!$C$71*Inputs!$C$86,Inputs!$C$73))) -> 561600 | F59: =(Inputs!$C$82*(1+Inputs!$C$83)^4)/12+IF(56=Inputs!$C$68,Inputs!$C$69/12,0) -> 94743.94 | G59: =IF(D59="Expired",0,(IF(Inputs!$C$5=1,(Inputs!C38+Inputs!C39)/12,(Inputs!F38+Inputs!F39)/12)*(1+Inputs!$C$83)^4)) -> 57950.177 | H59: =E59-F59-G59 -> 408905.88 | I59: ='Debt Schedule'!I68 -> 536541.9 | J59: =H59-I59 -> -127636.02 | K59: =IFERROR(H59/I59,"-") -> 0.76211361 | L59: =SUM($J$4:J59) -> -6711475.3
B60: 57 | C60: =EDATE(DATE(2024,1,1),56) -> 46997 | D60: =IF(57>Inputs!$C$74,"Expired",IF(Inputs!$C$68>0,IF(57<Inputs!$C$68,"Paying",IF(57<Inputs!$C$68+Inputs!$C$85,"Default","Re-Lease")),"Paying")) -> Paying | E60: =IF(D60="Expired",0,IF(D60="Default",0,IF(D60="Re-Lease",Inputs!$C$71*Inputs!$C$86,Inputs!$C$73))) -> 561600 | F60: =(Inputs!$C$82*(1+Inputs!$C$83)^4)/12+IF(57=Inputs!$C$68,Inputs!$C$69/12,0) -> 94743.94 | G60: =IF(D60="Expired",0,(IF(Inputs!$C$5=1,(Inputs!C38+Inputs!C39)/12,(Inputs!F38+Inputs!F39)/12)*(1+Inputs!$C$83)^4)) -> 57950.177 | H60: =E60-F60-G60 -> 408905.88 | I60: ='Debt Schedule'!I69 -> 536541.9 | J60: =H60-I60 -> -127636.02 | K60: =IFERROR(H60/I60,"-") -> 0.76211361 | L60: =SUM($J$4:J60) -> -6839111.3
B61: 58 | C61: =EDATE(DATE(2024,1,1),57) -> 47027 | D61: =IF(58>Inputs!$C$74,"Expired",IF(Inputs!$C$68>0,IF(58<Inputs!$C$68,"Paying",IF(58<Inputs!$C$68+Inputs!$C$85,"Default","Re-Lease")),"Paying")) -> Paying | E61: =IF(D61="Expired",0,IF(D61="Default",0,IF(D61="Re-Lease",Inputs!$C$71*Inputs!$C$86,Inputs!$C$73))) -> 561600 | F61: =(Inputs!$C$82*(1+Inputs!$C$83)^4)/12+IF(58=Inputs!$C$68,Inputs!$C$69/12,0) -> 94743.94 | G61: =IF(D61="Expired",0,(IF(Inputs!$C$5=1,(Inputs!C38+Inputs!C39)/12,(Inputs!F38+Inputs!F39)/12)*(1+Inputs!$C$83)^4)) -> 57950.177 | H61: =E61-F61-G61 -> 408905.88 | I61: ='Debt Schedule'!I70 -> 536541.9 | J61: =H61-I61 -> -127636.02 | K61: =IFERROR(H61/I61,"-") -> 0.76211361 | L61: =SUM($J$4:J61) -> -6966747.4
B62: 59 | C62: =EDATE(DATE(2024,1,1),58) -> 47058 | D62: =IF(59>Inputs!$C$74,"Expired",IF(Inputs!$C$68>0,IF(59<Inputs!$C$68,"Paying",IF(59<Inputs!$C$68+Inputs!$C$85,"Default","Re-Lease")),"Paying")) -> Paying | E62: =IF(D62="Expired",0,IF(D62="Default",0,IF(D62="Re-Lease",Inputs!$C$71*Inputs!$C$86,Inputs!$C$73))) -> 561600 | F62: =(Inputs!$C$82*(1+Inputs!$C$83)^4)/12+IF(59=Inputs!$C$68,Inputs!$C$69/12,0) -> 94743.94 | G62: =IF(D62="Expired",0,(IF(Inputs!$C$5=1,(Inputs!C38+Inputs!C39)/12,(Inputs!F38+Inputs!F39)/12)*(1+Inputs!$C$83)^4)) -> 57950.177 | H62: =E62-F62-G62 -> 408905.88 | I62: ='Debt Schedule'!I71 -> 536541.9 | J62: =H62-I62 -> -127636.02 | K62: =IFERROR(H62/I62,"-") -> 0.76211361 | L62: =SUM($J$4:J62) -> -7094383.4
B63: 60 | C63: =EDATE(DATE(2024,1,1),59) -> 47088 | D63: =IF(60>Inputs!$C$74,"Expired",IF(Inputs!$C$68>0,IF(60<Inputs!$C$68,"Paying",IF(60<Inputs!$C$68+Inputs!$C$85,"Default","Re-Lease")),"Paying")) -> Paying | E63: =IF(D63="Expired",0,IF(D63="Default",0,IF(D63="Re-Lease",Inputs!$C$71*Inputs!$C$86,Inputs!$C$73))) -> 561600 | F63: =(Inputs!$C$82*(1+Inputs!$C$83)^4)/12+IF(60=Inputs!$C$68,Inputs!$C$69/12,0) -> 94743.94 | G63: =IF(D63="Expired",0,(IF(Inputs!$C$5=1,(Inputs!C38+Inputs!C39)/12,(Inputs!F38+Inputs!F39)/12)*(1+Inputs!$C$83)^4)) -> 57950.177 | H63: =E63-F63-G63 -> 408905.88 | I63: ='Debt Schedule'!I72 -> 536541.9 | J63: =H63-I63 -> -127636.02 | K63: =IFERROR(H63/I63,"-") -> 0.76211361 | L63: =SUM($J$4:J63) -> -7222019.4
B64: 61 | C64: =EDATE(DATE(2024,1,1),60) -> 47119 | D64: =IF(61>Inputs!$C$74,"Expired",IF(Inputs!$C$68>0,IF(61<Inputs!$C$68,"Paying",IF(61<Inputs!$C$68+Inputs!$C$85,"Default","Re-Lease")),"Paying")) -> Paying | E64: =IF(D64="Expired",0,IF(D64="Default",0,IF(D64="Re-Lease",Inputs!$C$71*Inputs!$C$86,Inputs!$C$73))) -> 561600 | F64: =(Inputs!$C$82*(1+Inputs!$C$83)^5)/12+IF(61=Inputs!$C$68,Inputs!$C$69/12,0) -> 97112.538 | G64: =IF(D64="Expired",0,(IF(Inputs!$C$5=1,(Inputs!C38+Inputs!C39)/12,(Inputs!F38+Inputs!F39)/12)*(1+Inputs!$C$83)^5)) -> 59398.931 | H64: =E64-F64-G64 -> 405088.53 | I64: ='Debt Schedule'!I73 -> 536541.9 | J64: =H64-I64 -> -131453.37 | K64: =IFERROR(H64/I64,"-") -> 0.75499887 | L64: =SUM($J$4:J64) -> -7353472.8
B65: 62 | C65: =EDATE(DATE(2024,1,1),61) -> 47150 | D65: =IF(62>Inputs!$C$74,"Expired",IF(Inputs!$C$68>0,IF(62<Inputs!$C$68,"Paying",IF(62<Inputs!$C$68+Inputs!$C$85,"Default","Re-Lease")),"Paying")) -> Paying | E65: =IF(D65="Expired",0,IF(D65="Default",0,IF(D65="Re-Lease",Inputs!$C$71*Inputs!$C$86,Inputs!$C$73))) -> 561600 | F65: =(Inputs!$C$82*(1+Inputs!$C$83)^5)/12+IF(62=Inputs!$C$68,Inputs!$C$69/12,0) -> 97112.538 | G65: =IF(D65="Expired",0,(IF(Inputs!$C$5=1,(Inputs!C38+Inputs!C39)/12,(Inputs!F38+Inputs!F39)/12)*(1+Inputs!$C$83)^5)) -> 59398.931 | H65: =E65-F65-G65 -> 405088.53 | I65: ='Debt Schedule'!I74 -> 536541.9 | J65: =H65-I65 -> -131453.37 | K65: =IFERROR(H65/I65,"-") -> 0.75499887 | L65: =SUM($J$4:J65) -> -7484926.1
B66: 63 | C66: =EDATE(DATE(2024,1,1),62) -> 47178 | D66: =IF(63>Inputs!$C$74,"Expired",IF(Inputs!$C$68>0,IF(63<Inputs!$C$68,"Paying",IF(63<Inputs!$C$68+Inputs!$C$85,"Default","Re-Lease")),"Paying")) -> Paying | E66: =IF(D66="Expired",0,IF(D66="Default",0,IF(D66="Re-Lease",Inputs!$C$71*Inputs!$C$86,Inputs!$C$73))) -> 561600 | F66: =(Inputs!$C$82*(1+Inputs!$C$83)^5)/12+IF(63=Inputs!$C$68,Inputs!$C$69/12,0) -> 97112.538 | G66: =IF(D66="Expired",0,(IF(Inputs!$C$5=1,(Inputs!C38+Inputs!C39)/12,(Inputs!F38+Inputs!F39)/12)*(1+Inputs!$C$83)^5)) -> 59398.931 | H66: =E66-F66-G66 -> 405088.53 | I66: ='Debt Schedule'!I75 -> 536541.9 | J66: =H66-I66 -> -131453.37 | K66: =IFERROR(H66/I66,"-") -> 0.75499887 | L66: =SUM($J$4:J66) -> -7616379.5
B67: 64 | C67: =EDATE(DATE(2024,1,1),63) -> 47209 | D67: =IF(64>Inputs!$C$74,"Expired",IF(Inputs!$C$68>0,IF(64<Inputs!$C$68,"Paying",IF(64<Inputs!$C$68+Inputs!$C$85,"Default","Re-Lease")),"Paying")) -> Paying | E67: =IF(D67="Expired",0,IF(D67="Default",0,IF(D67="Re-Lease",Inputs!$C$71*Inputs!$C$86,Inputs!$C$73))) -> 561600 | F67: =(Inputs!$C$82*(1+Inputs!$C$83)^5)/12+IF(64=Inputs!$C$68,Inputs!$C$69/12,0) -> 97112.538 | G67: =IF(D67="Expired",0,(IF(Inputs!$C$5=1,(Inputs!C38+Inputs!C39)/12,(Inputs!F38+Inputs!F39)/12)*(1+Inputs!$C$83)^5)) -> 59398.931 | H67: =E67-F67-G67 -> 405088.53 | I67: ='Debt Schedule'!I76 -> 536541.9 | J67: =H67-I67 -> -131453.37 | K67: =IFERROR(H67/I67,"-") -> 0.75499887 | L67: =SUM($J$4:J67) -> -7747832.9
B68: 65 | C68: =EDATE(DATE(2024,1,1),64) -> 47239 | D68: =IF(65>Inputs!$C$74,"Expired",IF(Inputs!$C$68>0,IF(65<Inputs!$C$68,"Paying",IF(65<Inputs!$C$68+Inputs!$C$85,"Default","Re-Lease")),"Paying")) -> Paying | E68: =IF(D68="Expired",0,IF(D68="Default",0,IF(D68="Re-Lease",Inputs!$C$71*Inputs!$C$86,Inputs!$C$73))) -> 561600 | F68: =(Inputs!$C$82*(1+Inputs!$C$83)^5)/12+IF(65=Inputs!$C$68,Inputs!$C$69/12,0) -> 97112.538 | G68: =IF(D68="Expired",0,(IF(Inputs!$C$5=1,(Inputs!C38+Inputs!C39)/12,(Inputs!F38+Inputs!F39)/12)*(1+Inputs!$C$83)^5)) -> 59398.931 | H68: =E68-F68-G68 -> 405088.53 | I68: ='Debt Schedule'!I77 -> 536541.9 | J68: =H68-I68 -> -131453.37 | K68: =IFERROR(H68/I68,"-") -> 0.75499887 | L68: =SUM($J$4:J68) -> -7879286.2
B69: 66 | C69: =EDATE(DATE(2024,1,1),65) -> 47270 | D69: =IF(66>Inputs!$C$74,"Expired",IF(Inputs!$C$68>0,IF(66<Inputs!$C$68,"Paying",IF(66<Inputs!$C$68+Inputs!$C$85,"Default","Re-Lease")),"Paying")) -> Paying | E69: =IF(D69="Expired",0,IF(D69="Default",0,IF(D69="Re-Lease",Inputs!$C$71*Inputs!$C$86,Inputs!$C$73))) -> 561600 | F69: =(Inputs!$C$82*(1+Inputs!$C$83)^5)/12+IF(66=Inputs!$C$68,Inputs!$C$69/12,0) -> 97112.538 | G69: =IF(D69="Expired",0,(IF(Inputs!$C$5=1,(Inputs!C38+Inputs!C39)/12,(Inputs!F38+Inputs!F39)/12)*(1+Inputs!$C$83)^5)) -> 59398.931 | H69: =E69-F69-G69 -> 405088.53 | I69: ='Debt Schedule'!I78 -> 536541.9 | J69: =H69-I69 -> -131453.37 | K69: =IFERROR(H69/I69,"-") -> 0.75499887 | L69: =SUM($J$4:J69) -> -8010739.6
B70: 67 | C70: =EDATE(DATE(2024,1,1),66) -> 47300 | D70: =IF(67>Inputs!$C$74,"Expired",IF(Inputs!$C$68>0,IF(67<Inputs!$C$68,"Paying",IF(67<Inputs!$C$68+Inputs!$C$85,"Default","Re-Lease")),"Paying")) -> Paying | E70: =IF(D70="Expired",0,IF(D70="Default",0,IF(D70="Re-Lease",Inputs!$C$71*Inputs!$C$86,Inputs!$C$73))) -> 561600 | F70: =(Inputs!$C$82*(1+Inputs!$C$83)^5)/12+IF(67=Inputs!$C$68,Inputs!$C$69/12,0) -> 97112.538 | G70: =IF(D70="Expired",0,(IF(Inputs!$C$5=1,(Inputs!C38+Inputs!C39)/12,(Inputs!F38+Inputs!F39)/12)*(1+Inputs!$C$83)^5)) -> 59398.931 | H70: =E70-F70-G70 -> 405088.53 | I70: ='Debt Schedule'!I79 -> 536541.9 | J70: =H70-I70 -> -131453.37 | K70: =IFERROR(H70/I70,"-") -> 0.75499887 | L70: =SUM($J$4:J70) -> -8142193
B71: 68 | C71: =EDATE(DATE(2024,1,1),67) -> 47331 | D71: =IF(68>Inputs!$C$74,"Expired",IF(Inputs!$C$68>0,IF(68<Inputs!$C$68,"Paying",IF(68<Inputs!$C$68+Inputs!$C$85,"Default","Re-Lease")),"Paying")) -> Paying | E71: =IF(D71="Expired",0,IF(D71="Default",0,IF(D71="Re-Lease",Inputs!$C$71*Inputs!$C$86,Inputs!$C$73))) -> 561600 | F71: =(Inputs!$C$82*(1+Inputs!$C$83)^5)/12+IF(68=Inputs!$C$68,Inputs!$C$69/12,0) -> 97112.538 | G71: =IF(D71="Expired",0,(IF(Inputs!$C$5=1,(Inputs!C38+Inputs!C39)/12,(Inputs!F38+Inputs!F39)/12)*(1+Inputs!$C$83)^5)) -> 59398.931 | H71: =E71-F71-G71 -> 405088.53 | I71: ='Debt Schedule'!I80 -> 536541.9 | J71: =H71-I71 -> -131453.37 | K71: =IFERROR(H71/I71,"-") -> 0.75499887 | L71: =SUM($J$4:J71) -> -8273646.4
B72: 69 | C72: =EDATE(DATE(2024,1,1),68) -> 47362 | D72: =IF(69>Inputs!$C$74,"Expired",IF(Inputs!$C$68>0,IF(69<Inputs!$C$68,"Paying",IF(69<Inputs!$C$68+Inputs!$C$85,"Default","Re-Lease")),"Paying")) -> Paying | E72: =IF(D72="Expired",0,IF(D72="Default",0,IF(D72="Re-Lease",Inputs!$C$71*Inputs!$C$86,Inputs!$C$73))) -> 561600 | F72: =(Inputs!$C$82*(1+Inputs!$C$83)^5)/12+IF(69=Inputs!$C$68,Inputs!$C$69/12,0) -> 97112.538 | G72: =IF(D72="Expired",0,(IF(Inputs!$C$5=1,(Inputs!C38+Inputs!C39)/12,(Inputs!F38+Inputs!F39)/12)*(1+Inputs!$C$83)^5)) -> 59398.931 | H72: =E72-F72-G72 -> 405088.53 | I72: ='Debt Schedule'!I81 -> 536541.9 | J72: =H72-I72 -> -131453.37 | K72: =IFERROR(H72/I72,"-") -> 0.75499887 | L72: =SUM($J$4:J72) -> -8405099.7
B73: 70 | C73: =EDATE(DATE(2024,1,1),69) -> 47392 | D73: =IF(70>Inputs!$C$74,"Expired",IF(Inputs!$C$68>0,IF(70<Inputs!$C$68,"Paying",IF(70<Inputs!$C$68+Inputs!$C$85,"Default","Re-Lease")),"Paying")) -> Paying | E73: =IF(D73="Expired",0,IF(D73="Default",0,IF(D73="Re-Lease",Inputs!$C$71*Inputs!$C$86,Inputs!$C$73))) -> 561600 | F73: =(Inputs!$C$82*(1+Inputs!$C$83)^5)/12+IF(70=Inputs!$C$68,Inputs!$C$69/12,0) -> 97112.538 | G73: =IF(D73="Expired",0,(IF(Inputs!$C$5=1,(Inputs!C38+Inputs!C39)/12,(Inputs!F38+Inputs!F39)/12)*(1+Inputs!$C$83)^5)) -> 59398.931 | H73: =E73-F73-G73 -> 405088.53 | I73: ='Debt Schedule'!I82 -> 536541.9 | J73: =H73-I73 -> -131453.37 | K73: =IFERROR(H73/I73,"-") -> 0.75499887 | L73: =SUM($J$4:J73) -> -8536553.1
B74: 71 | C74: =EDATE(DATE(2024,1,1),70) -> 47423 | D74: =IF(71>Inputs!$C$74,"Expired",IF(Inputs!$C$68>0,IF(71<Inputs!$C$68,"Paying",IF(71<Inputs!$C$68+Inputs!$C$85,"Default","Re-Lease")),"Paying")) -> Paying | E74: =IF(D74="Expired",0,IF(D74="Default",0,IF(D74="Re-Lease",Inputs!$C$71*Inputs!$C$86,Inputs!$C$73))) -> 561600 | F74: =(Inputs!$C$82*(1+Inputs!$C$83)^5)/12+IF(71=Inputs!$C$68,Inputs!$C$69/12,0) -> 97112.538 | G74: =IF(D74="Expired",0,(IF(Inputs!$C$5=1,(Inputs!C38+Inputs!C39)/12,(Inputs!F38+Inputs!F39)/12)*(1+Inputs!$C$83)^5)) -> 59398.931 | H74: =E74-F74-G74 -> 405088.53 | I74: ='Debt Schedule'!I83 -> 536541.9 | J74: =H74-I74 -> -131453.37 | K74: =IFERROR(H74/I74,"-") -> 0.75499887 | L74: =SUM($J$4:J74) -> -8668006.5
B75: 72 | C75: =EDATE(DATE(2024,1,1),71) -> 47453 | D75: =IF(72>Inputs!$C$74,"Expired",IF(Inputs!$C$68>0,IF(72<Inputs!$C$68,"Paying",IF(72<Inputs!$C$68+Inputs!$C$85,"Default","Re-Lease")),"Paying")) -> Paying | E75: =IF(D75="Expired",0,IF(D75="Default",0,IF(D75="Re-Lease",Inputs!$C$71*Inputs!$C$86,Inputs!$C$73))) -> 561600 | F75: =(Inputs!$C$82*(1+Inputs!$C$83)^5)/12+IF(72=Inputs!$C$68,Inputs!$C$69/12,0) -> 97112.538 | G75: =IF(D75="Expired",0,(IF(Inputs!$C$5=1,(Inputs!C38+Inputs!C39)/12,(Inputs!F38+Inputs!F39)/12)*(1+Inputs!$C$83)^5)) -> 59398.931 | H75: =E75-F75-G75 -> 405088.53 | I75: ='Debt Schedule'!I84 -> 536541.9 | J75: =H75-I75 -> -131453.37 | K75: =IFERROR(H75/I75,"-") -> 0.75499887 | L75: =SUM($J$4:J75) -> -8799459.8
B76: 73 | C76: =EDATE(DATE(2024,1,1),72) -> 47484 | D76: =IF(73>Inputs!$C$74,"Expired",IF(Inputs!$C$68>0,IF(73<Inputs!$C$68,"Paying",IF(73<Inputs!$C$68+Inputs!$C$85,"Default","Re-Lease")),"Paying")) -> Paying | E76: =IF(D76="Expired",0,IF(D76="Default",0,IF(D76="Re-Lease",Inputs!$C$71*Inputs!$C$86,Inputs!$C$73))) -> 561600 | F76: =(Inputs!$C$82*(1+Inputs!$C$83)^6)/12+IF(73=Inputs!$C$68,Inputs!$C$69/12,0) -> 99540.352 | G76: =IF(D76="Expired",0,(IF(Inputs!$C$5=1,(Inputs!C38+Inputs!C39)/12,(Inputs!F38+Inputs!F39)/12)*(1+Inputs!$C$83)^6)) -> 60883.904 | H76: =E76-F76-G76 -> 401175.74 | I76: ='Debt Schedule'!I85 -> 536541.9 | J76: =H76-I76 -> -135366.16 | K76: =IFERROR(H76/I76,"-") -> 0.74770627 | L76: =SUM($J$4:J76) -> -8934826
B77: 74 | C77: =EDATE(DATE(2024,1,1),73) -> 47515 | D77: =IF(74>Inputs!$C$74,"Expired",IF(Inputs!$C$68>0,IF(74<Inputs!$C$68,"Paying",IF(74<Inputs!$C$68+Inputs!$C$85,"Default","Re-Lease")),"Paying")) -> Paying | E77: =IF(D77="Expired",0,IF(D77="Default",0,IF(D77="Re-Lease",Inputs!$C$71*Inputs!$C$86,Inputs!$C$73))) -> 561600 | F77: =(Inputs!$C$82*(1+Inputs!$C$83)^6)/12+IF(74=Inputs!$C$68,Inputs!$C$69/12,0) -> 99540.352 | G77: =IF(D77="Expired",0,(IF(Inputs!$C$5=1,(Inputs!C38+Inputs!C39)/12,(Inputs!F38+Inputs!F39)/12)*(1+Inputs!$C$83)^6)) -> 60883.904 | H77: =E77-F77-G77 -> 401175.74 | I77: ='Debt Schedule'!I86 -> 536541.9 | J77: =H77-I77 -> -135366.16 | K77: =IFERROR(H77/I77,"-") -> 0.74770627 | L77: =SUM($J$4:J77) -> -9070192.2
B78: 75 | C78: =EDATE(DATE(2024,1,1),74) -> 47543 | D78: =IF(75>Inputs!$C$74,"Expired",IF(Inputs!$C$68>0,IF(75<Inputs!$C$68,"Paying",IF(75<Inputs!$C$68+Inputs!$C$85,"Default","Re-Lease")),"Paying")) -> Paying | E78: =IF(D78="Expired",0,IF(D78="Default",0,IF(D78="Re-Lease",Inputs!$C$71*Inputs!$C$86,Inputs!$C$73))) -> 561600 | F78: =(Inputs!$C$82*(1+Inputs!$C$83)^6)/12+IF(75=Inputs!$C$68,Inputs!$C$69/12,0) -> 99540.352 | G78: =IF(D78="Expired",0,(IF(Inputs!$C$5=1,(Inputs!C38+Inputs!C39)/12,(Inputs!F38+Inputs!F39)/12)*(1+Inputs!$C$83)^6)) -> 60883.904 | H78: =E78-F78-G78 -> 401175.74 | I78: ='Debt Schedule'!I87 -> 536541.9 | J78: =H78-I78 -> -135366.16 | K78: =IFERROR(H78/I78,"-") -> 0.74770627 | L78: =SUM($J$4:J78) -> -9205558.3
B79: 76 | C79: =EDATE(DATE(2024,1,1),75) -> 47574 | D79: =IF(76>Inputs!$C$74,"Expired",IF(Inputs!$C$68>0,IF(76<Inputs!$C$68,"Paying",IF(76<Inputs!$C$68+Inputs!$C$85,"Default","Re-Lease")),"Paying")) -> Paying | E79: =IF(D79="Expired",0,IF(D79="Default",0,IF(D79="Re-Lease",Inputs!$C$71*Inputs!$C$86,Inputs!$C$73))) -> 561600 | F79: =(Inputs!$C$82*(1+Inputs!$C$83)^6)/12+IF(76=Inputs!$C$68,Inputs!$C$69/12,0) -> 99540.352 | G79: =IF(D79="Expired",0,(IF(Inputs!$C$5=1,(Inputs!C38+Inputs!C39)/12,(Inputs!F38+Inputs!F39)/12)*(1+Inputs!$C$83)^6)) -> 60883.904 | H79: =E79-F79-G79 -> 401175.74 | I79: ='Debt Schedule'!I88 -> 536541.9 | J79: =H79-I79 -> -135366.16 | K79: =IFERROR(H79/I79,"-") -> 0.74770627 | L79: =SUM($J$4:J79) -> -9340924.5
B80: 77 | C80: =EDATE(DATE(2024,1,1),76) -> 47604 | D80: =IF(77>Inputs!$C$74,"Expired",IF(Inputs!$C$68>0,IF(77<Inputs!$C$68,"Paying",IF(77<Inputs!$C$68+Inputs!$C$85,"Default","Re-Lease")),"Paying")) -> Paying | E80: =IF(D80="Expired",0,IF(D80="Default",0,IF(D80="Re-Lease",Inputs!$C$71*Inputs!$C$86,Inputs!$C$73))) -> 561600 | F80: =(Inputs!$C$82*(1+Inputs!$C$83)^6)/12+IF(77=Inputs!$C$68,Inputs!$C$69/12,0) -> 99540.352 | G80: =IF(D80="Expired",0,(IF(Inputs!$C$5=1,(Inputs!C38+Inputs!C39)/12,(Inputs!F38+Inputs!F39)/12)*(1+Inputs!$C$83)^6)) -> 60883.904 | H80: =E80-F80-G80 -> 401175.74 | I80: ='Debt Schedule'!I89 -> 536541.9 | J80: =H80-I80 -> -135366.16 | K80: =IFERROR(H80/I80,"-") -> 0.74770627 | L80: =SUM($J$4:J80) -> -9476290.6
B81: 78 | C81: =EDATE(DATE(2024,1,1),77) -> 47635 | D81: =IF(78>Inputs!$C$74,"Expired",IF(Inputs!$C$68>0,IF(78<Inputs!$C$68,"Paying",IF(78<Inputs!$C$68+Inputs!$C$85,"Default","Re-Lease")),"Paying")) -> Paying | E81: =IF(D81="Expired",0,IF(D81="Default",0,IF(D81="Re-Lease",Inputs!$C$71*Inputs!$C$86,Inputs!$C$73))) -> 561600 | F81: =(Inputs!$C$82*(1+Inputs!$C$83)^6)/12+IF(78=Inputs!$C$68,Inputs!$C$69/12,0) -> 99540.352 | G81: =IF(D81="Expired",0,(IF(Inputs!$C$5=1,(Inputs!C38+Inputs!C39)/12,(Inputs!F38+Inputs!F39)/12)*(1+Inputs!$C$83)^6)) -> 60883.904 | H81: =E81-F81-G81 -> 401175.74 | I81: ='Debt Schedule'!I90 -> 536541.9 | J81: =H81-I81 -> -135366.16 | K81: =IFERROR(H81/I81,"-") -> 0.74770627 | L81: =SUM($J$4:J81) -> -9611656.8
B82: 79 | C82: =EDATE(DATE(2024,1,1),78) -> 47665 | D82: =IF(79>Inputs!$C$74,"Expired",IF(Inputs!$C$68>0,IF(79<Inputs!$C$68,"Paying",IF(79<Inputs!$C$68+Inputs!$C$85,"Default","Re-Lease")),"Paying")) -> Paying | E82: =IF(D82="Expired",0,IF(D82="Default",0,IF(D82="Re-Lease",Inputs!$C$71*Inputs!$C$86,Inputs!$C$73))) -> 561600 | F82: =(Inputs!$C$82*(1+Inputs!$C$83)^6)/12+IF(79=Inputs!$C$68,Inputs!$C$69/12,0) -> 99540.352 | G82: =IF(D82="Expired",0,(IF(Inputs!$C$5=1,(Inputs!C38+Inputs!C39)/12,(Inputs!F38+Inputs!F39)/12)*(1+Inputs!$C$83)^6)) -> 60883.904 | H82: =E82-F82-G82 -> 401175.74 | I82: ='Debt Schedule'!I91 -> 536541.9 | J82: =H82-I82 -> -135366.16 | K82: =IFERROR(H82/I82,"-") -> 0.74770627 | L82: =SUM($J$4:J82) -> -9747022.9
B83: 80 | C83: =EDATE(DATE(2024,1,1),79) -> 47696 | D83: =IF(80>Inputs!$C$74,"Expired",IF(Inputs!$C$68>0,IF(80<Inputs!$C$68,"Paying",IF(80<Inputs!$C$68+Inputs!$C$85,"Default","Re-Lease")),"Paying")) -> Paying | E83: =IF(D83="Expired",0,IF(D83="Default",0,IF(D83="Re-Lease",Inputs!$C$71*Inputs!$C$86,Inputs!$C$73))) -> 561600 | F83: =(Inputs!$C$82*(1+Inputs!$C$83)^6)/12+IF(80=Inputs!$C$68,Inputs!$C$69/12,0) -> 99540.352 | G83: =IF(D83="Expired",0,(IF(Inputs!$C$5=1,(Inputs!C38+Inputs!C39)/12,(Inputs!F38+Inputs!F39)/12)*(1+Inputs!$C$83)^6)) -> 60883.904 | H83: =E83-F83-G83 -> 401175.74 | I83: ='Debt Schedule'!I92 -> 536541.9 | J83: =H83-I83 -> -135366.16 | K83: =IFERROR(H83/I83,"-") -> 0.74770627 | L83: =SUM($J$4:J83) -> -9882389.1
B84: 81 | C84: =EDATE(DATE(2024,1,1),80) -> 47727 | D84: =IF(81>Inputs!$C$74,"Expired",IF(Inputs!$C$68>0,IF(81<Inputs!$C$68,"Paying",IF(81<Inputs!$C$68+Inputs!$C$85,"Default","Re-Lease")),"Paying")) -> Paying | E84: =IF(D84="Expired",0,IF(D84="Default",0,IF(D84="Re-Lease",Inputs!$C$71*Inputs!$C$86,Inputs!$C$73))) -> 561600 | F84: =(Inputs!$C$82*(1+Inputs!$C$83)^6)/12+IF(81=Inputs!$C$68,Inputs!$C$69/12,0) -> 99540.352 | G84: =IF(D84="Expired",0,(IF(Inputs!$C$5=1,(Inputs!C38+Inputs!C39)/12,(Inputs!F38+Inputs!F39)/12)*(1+Inputs!$C$83)^6)) -> 60883.904 | H84: =E84-F84-G84 -> 401175.74 | I84: ='Debt Schedule'!I93 -> 536541.9 | J84: =H84-I84 -> -135366.16 | K84: =IFERROR(H84/I84,"-") -> 0.74770627 | L84: =SUM($J$4:J84) -> -10017755
B85: 82 | C85: =EDATE(DATE(2024,1,1),81) -> 47757 | D85: =IF(82>Inputs!$C$74,"Expired",IF(Inputs!$C$68>0,IF(82<Inputs!$C$68,"Paying",IF(82<Inputs!$C$68+Inputs!$C$85,"Default","Re-Lease")),"Paying")) -> Paying | E85: =IF(D85="Expired",0,IF(D85="Default",0,IF(D85="Re-Lease",Inputs!$C$71*Inputs!$C$86,Inputs!$C$73))) -> 561600 | F85: =(Inputs!$C$82*(1+Inputs!$C$83)^6)/12+IF(82=Inputs!$C$68,Inputs!$C$69/12,0) -> 99540.352 | G85: =IF(D85="Expired",0,(IF(Inputs!$C$5=1,(Inputs!C38+Inputs!C39)/12,(Inputs!F38+Inputs!F39)/12)*(1+Inputs!$C$83)^6)) -> 60883.904 | H85: =E85-F85-G85 -> 401175.74 | I85: ='Debt Schedule'!I94 -> 536541.9 | J85: =H85-I85 -> -135366.16 | K85: =IFERROR(H85/I85,"-") -> 0.74770627 | L85: =SUM($J$4:J85) -> -10153121
B86: 83 | C86: =EDATE(DATE(2024,1,1),82) -> 47788 | D86: =IF(83>Inputs!$C$74,"Expired",IF(Inputs!$C$68>0,IF(83<Inputs!$C$68,"Paying",IF(83<Inputs!$C$68+Inputs!$C$85,"Default","Re-Lease")),"Paying")) -> Paying | E86: =IF(D86="Expired",0,IF(D86="Default",0,IF(D86="Re-Lease",Inputs!$C$71*Inputs!$C$86,Inputs!$C$73))) -> 561600 | F86: =(Inputs!$C$82*(1+Inputs!$C$83)^6)/12+IF(83=Inputs!$C$68,Inputs!$C$69/12,0) -> 99540.352 | G86: =IF(D86="Expired",0,(IF(Inputs!$C$5=1,(Inputs!C38+Inputs!C39)/12,(Inputs!F38+Inputs!F39)/12)*(1+Inputs!$C$83)^6)) -> 60883.904 | H86: =E86-F86-G86 -> 401175.74 | I86: ='Debt Schedule'!I95 -> 536541.9 | J86: =H86-I86 -> -135366.16 | K86: =IFERROR(H86/I86,"-") -> 0.74770627 | L86: =SUM($J$4:J86) -> -10288488
B87: 84 | C87: =EDATE(DATE(2024,1,1),83) -> 47818 | D87: =IF(84>Inputs!$C$74,"Expired",IF(Inputs!$C$68>0,IF(84<Inputs!$C$68,"Paying",IF(84<Inputs!$C$68+Inputs!$C$85,"Default","Re-Lease")),"Paying")) -> Paying | E87: =IF(D87="Expired",0,IF(D87="Default",0,IF(D87="Re-Lease",Inputs!$C$71*Inputs!$C$86,Inputs!$C$73))) -> 561600 | F87: =(Inputs!$C$82*(1+Inputs!$C$83)^6)/12+IF(84=Inputs!$C$68,Inputs!$C$69/12,0) -> 99540.352 | G87: =IF(D87="Expired",0,(IF(Inputs!$C$5=1,(Inputs!C38+Inputs!C39)/12,(Inputs!F38+Inputs!F39)/12)*(1+Inputs!$C$83)^6)) -> 60883.904 | H87: =E87-F87-G87 -> 401175.74 | I87: ='Debt Schedule'!I96 -> 536541.9 | J87: =H87-I87 -> -135366.16 | K87: =IFERROR(H87/I87,"-") -> 0.74770627 | L87: =SUM($J$4:J87) -> -10423854
B88: 85 | C88: =EDATE(DATE(2024,1,1),84) -> 47849 | D88: =IF(85>Inputs!$C$74,"Expired",IF(Inputs!$C$68>0,IF(85<Inputs!$C$68,"Paying",IF(85<Inputs!$C$68+Inputs!$C$85,"Default","Re-Lease")),"Paying")) -> Paying | E88: =IF(D88="Expired",0,IF(D88="Default",0,IF(D88="Re-Lease",Inputs!$C$71*Inputs!$C$86,Inputs!$C$73))) -> 561600 | F88: =(Inputs!$C$82*(1+Inputs!$C$83)^7)/12+IF(85=Inputs!$C$68,Inputs!$C$69/12,0) -> 102028.86 | G88: =IF(D88="Expired",0,(IF(Inputs!$C$5=1,(Inputs!C38+Inputs!C39)/12,(Inputs!F38+Inputs!F39)/12)*(1+Inputs!$C$83)^7)) -> 62406.002 | H88: =E88-F88-G88 -> 397165.14 | I88: ='Debt Schedule'!I97 -> 536541.9 | J88: =H88-I88 -> -139376.76 | K88: =IFERROR(H88/I88,"-") -> 0.74023135 | L88: =SUM($J$4:J88) -> -10563230
B89: 86 | C89: =EDATE(DATE(2024,1,1),85) -> 47880 | D89: =IF(86>Inputs!$C$74,"Expired",IF(Inputs!$C$68>0,IF(86<Inputs!$C$68,"Paying",IF(86<Inputs!$C$68+Inputs!$C$85,"Default","Re-Lease")),"Paying")) -> Paying | E89: =IF(D89="Expired",0,IF(D89="Default",0,IF(D89="Re-Lease",Inputs!$C$71*Inputs!$C$86,Inputs!$C$73))) -> 561600 | F89: =(Inputs!$C$82*(1+Inputs!$C$83)^7)/12+IF(86=Inputs!$C$68,Inputs!$C$69/12,0) -> 102028.86 | G89: =IF(D89="Expired",0,(IF(Inputs!$C$5=1,(Inputs!C38+Inputs!C39)/12,(Inputs!F38+Inputs!F39)/12)*(1+Inputs!$C$83)^7)) -> 62406.002 | H89: =E89-F89-G89 -> 397165.14 | I89: ='Debt Schedule'!I98 -> 536541.9 | J89: =H89-I89 -> -139376.76 | K89: =IFERROR(H89/I89,"-") -> 0.74023135 | L89: =SUM($J$4:J89) -> -10702607
B90: 87 | C90: =EDATE(DATE(2024,1,1),86) -> 47908 | D90: =IF(87>Inputs!$C$74,"Expired",IF(Inputs!$C$68>0,IF(87<Inputs!$C$68,"Paying",IF(87<Inputs!$C$68+Inputs!$C$85,"Default","Re-Lease")),"Paying")) -> Paying | E90: =IF(D90="Expired",0,IF(D90="Default",0,IF(D90="Re-Lease",Inputs!$C$71*Inputs!$C$86,Inputs!$C$73))) -> 561600 | F90: =(Inputs!$C$82*(1+Inputs!$C$83)^7)/12+IF(87=Inputs!$C$68,Inputs!$C$69/12,0) -> 102028.86 | G90: =IF(D90="Expired",0,(IF(Inputs!$C$5=1,(Inputs!C38+Inputs!C39)/12,(Inputs!F38+Inputs!F39)/12)*(1+Inputs!$C$83)^7)) -> 62406.002 | H90: =E90-F90-G90 -> 397165.14 | I90: ='Debt Schedule'!I99 -> 536541.9 | J90: =H90-I90 -> -139376.76 | K90: =IFERROR(H90/I90,"-") -> 0.74023135 | L90: =SUM($J$4:J90) -> -10841984
B91: 88 | C91: =EDATE(DATE(2024,1,1),87) -> 47939 | D91: =IF(88>Inputs!$C$74,"Expired",IF(Inputs!$C$68>0,IF(88<Inputs!$C$68,"Paying",IF(88<Inputs!$C$68+Inputs!$C$85,"Default","Re-Lease")),"Paying")) -> Paying | E91: =IF(D91="Expired",0,IF(D91="Default",0,IF(D91="Re-Lease",Inputs!$C$71*Inputs!$C$86,Inputs!$C$73))) -> 561600 | F91: =(Inputs!$C$82*(1+Inputs!$C$83)^7)/12+IF(88=Inputs!$C$68,Inputs!$C$69/12,0) -> 102028.86 | G91: =IF(D91="Expired",0,(IF(Inputs!$C$5=1,(Inputs!C38+Inputs!C39)/12,(Inputs!F38+Inputs!F39)/12)*(1+Inputs!$C$83)^7)) -> 62406.002 | H91: =E91-F91-G91 -> 397165.14 | I91: ='Debt Schedule'!I100 -> 536541.9 | J91: =H91-I91 -> -139376.76 | K91: =IFERROR(H91/I91,"-") -> 0.74023135 | L91: =SUM($J$4:J91) -> -10981361
B92: 89 | C92: =EDATE(DATE(2024,1,1),88) -> 47969 | D92: =IF(89>Inputs!$C$74,"Expired",IF(Inputs!$C$68>0,IF(89<Inputs!$C$68,"Paying",IF(89<Inputs!$C$68+Inputs!$C$85,"Default","Re-Lease")),"Paying")) -> Paying | E92: =IF(D92="Expired",0,IF(D92="Default",0,IF(D92="Re-Lease",Inputs!$C$71*Inputs!$C$86,Inputs!$C$73))) -> 561600 | F92: =(Inputs!$C$82*(1+Inputs!$C$83)^7)/12+IF(89=Inputs!$C$68,Inputs!$C$69/12,0) -> 102028.86 | G92: =IF(D92="Expired",0,(IF(Inputs!$C$5=1,(Inputs!C38+Inputs!C39)/12,(Inputs!F38+Inputs!F39)/12)*(1+Inputs!$C$83)^7)) -> 62406.002 | H92: =E92-F92-G92 -> 397165.14 | I92: ='Debt Schedule'!I101 -> 536541.9 | J92: =H92-I92 -> -139376.76 | K92: =IFERROR(H92/I92,"-") -> 0.74023135 | L92: =SUM($J$4:J92) -> -11120738
B93: 90 | C93: =EDATE(DATE(2024,1,1),89) -> 48000 | D93: =IF(90>Inputs!$C$74,"Expired",IF(Inputs!$C$68>0,IF(90<Inputs!$C$68,"Paying",IF(90<Inputs!$C$68+Inputs!$C$85,"Default","Re-Lease")),"Paying")) -> Paying | E93: =IF(D93="Expired",0,IF(D93="Default",0,IF(D93="Re-Lease",Inputs!$C$71*Inputs!$C$86,Inputs!$C$73))) -> 561600 | F93: =(Inputs!$C$82*(1+Inputs!$C$83)^7)/12+IF(90=Inputs!$C$68,Inputs!$C$69/12,0) -> 102028.86 | G93: =IF(D93="Expired",0,(IF(Inputs!$C$5=1,(Inputs!C38+Inputs!C39)/12,(Inputs!F38+Inputs!F39)/12)*(1+Inputs!$C$83)^7)) -> 62406.002 | H93: =E93-F93-G93 -> 397165.14 | I93: ='Debt Schedule'!I102 -> 536541.9 | J93: =H93-I93 -> -139376.76 | K93: =IFERROR(H93/I93,"-") -> 0.74023135 | L93: =SUM($J$4:J93) -> -11260114
B94: 91 | C94: =EDATE(DATE(2024,1,1),90) -> 48030 | D94: =IF(91>Inputs!$C$74,"Expired",IF(Inputs!$C$68>0,IF(91<Inputs!$C$68,"Paying",IF(91<Inputs!$C$68+Inputs!$C$85,"Default","Re-Lease")),"Paying")) -> Paying | E94: =IF(D94="Expired",0,IF(D94="Default",0,IF(D94="Re-Lease",Inputs!$C$71*Inputs!$C$86,Inputs!$C$73))) -> 561600 | F94: =(Inputs!$C$82*(1+Inputs!$C$83)^7)/12+IF(91=Inputs!$C$68,Inputs!$C$69/12,0) -> 102028.86 | G94: =IF(D94="Expired",0,(IF(Inputs!$C$5=1,(Inputs!C38+Inputs!C39)/12,(Inputs!F38+Inputs!F39)/12)*(1+Inputs!$C$83)^7)) -> 62406.002 | H94: =E94-F94-G94 -> 397165.14 | I94: ='Debt Schedule'!I103 -> 536541.9 | J94: =H94-I94 -> -139376.76 | K94: =IFERROR(H94/I94,"-") -> 0.74023135 | L94: =SUM($J$4:J94) -> -11399491
B95: 92 | C95: =EDATE(DATE(2024,1,1),91) -> 48061 | D95: =IF(92>Inputs!$C$74,"Expired",IF(Inputs!$C$68>0,IF(92<Inputs!$C$68,"Paying",IF(92<Inputs!$C$68+Inputs!$C$85,"Default","Re-Lease")),"Paying")) -> Paying | E95: =IF(D95="Expired",0,IF(D95="Default",0,IF(D95="Re-Lease",Inputs!$C$71*Inputs!$C$86,Inputs!$C$73))) -> 561600 | F95: =(Inputs!$C$82*(1+Inputs!$C$83)^7)/12+IF(92=Inputs!$C$68,Inputs!$C$69/12,0) -> 102028.86 | G95: =IF(D95="Expired",0,(IF(Inputs!$C$5=1,(Inputs!C38+Inputs!C39)/12,(Inputs!F38+Inputs!F39)/12)*(1+Inputs!$C$83)^7)) -> 62406.002 | H95: =E95-F95-G95 -> 397165.14 | I95: ='Debt Schedule'!I104 -> 536541.9 | J95: =H95-I95 -> -139376.76 | K95: =IFERROR(H95/I95,"-") -> 0.74023135 | L95: =SUM($J$4:J95) -> -11538868
B96: 93 | C96: =EDATE(DATE(2024,1,1),92) -> 48092 | D96: =IF(93>Inputs!$C$74,"Expired",IF(Inputs!$C$68>0,IF(93<Inputs!$C$68,"Paying",IF(93<Inputs!$C$68+Inputs!$C$85,"Default","Re-Lease")),"Paying")) -> Paying | E96: =IF(D96="Expired",0,IF(D96="Default",0,IF(D96="Re-Lease",Inputs!$C$71*Inputs!$C$86,Inputs!$C$73))) -> 561600 | F96: =(Inputs!$C$82*(1+Inputs!$C$83)^7)/12+IF(93=Inputs!$C$68,Inputs!$C$69/12,0) -> 102028.86 | G96: =IF(D96="Expired",0,(IF(Inputs!$C$5=1,(Inputs!C38+Inputs!C39)/12,(Inputs!F38+Inputs!F39)/12)*(1+Inputs!$C$83)^7)) -> 62406.002 | H96: =E96-F96-G96 -> 397165.14 | I96: ='Debt Schedule'!I105 -> 536541.9 | J96: =H96-I96 -> -139376.76 | K96: =IFERROR(H96/I96,"-") -> 0.74023135 | L96: =SUM($J$4:J96) -> -11678245
B97: 94 | C97: =EDATE(DATE(2024,1,1),93) -> 48122 | D97: =IF(94>Inputs!$C$74,"Expired",IF(Inputs!$C$68>0,IF(94<Inputs!$C$68,"Paying",IF(94<Inputs!$C$68+Inputs!$C$85,"Default","Re-Lease")),"Paying")) -> Paying | E97: =IF(D97="Expired",0,IF(D97="Default",0,IF(D97="Re-Lease",Inputs!$C$71*Inputs!$C$86,Inputs!$C$73))) -> 561600 | F97: =(Inputs!$C$82*(1+Inputs!$C$83)^7)/12+IF(94=Inputs!$C$68,Inputs!$C$69/12,0) -> 102028.86 | G97: =IF(D97="Expired",0,(IF(Inputs!$C$5=1,(Inputs!C38+Inputs!C39)/12,(Inputs!F38+Inputs!F39)/12)*(1+Inputs!$C$83)^7)) -> 62406.002 | H97: =E97-F97-G97 -> 397165.14 | I97: ='Debt Schedule'!I106 -> 536541.9 | J97: =H97-I97 -> -139376.76 | K97: =IFERROR(H97/I97,"-") -> 0.74023135 | L97: =SUM($J$4:J97) -> -11817621
B98: 95 | C98: =EDATE(DATE(2024,1,1),94) -> 48153 | D98: =IF(95>Inputs!$C$74,"Expired",IF(Inputs!$C$68>0,IF(95<Inputs!$C$68,"Paying",IF(95<Inputs!$C$68+Inputs!$C$85,"Default","Re-Lease")),"Paying")) -> Paying | E98: =IF(D98="Expired",0,IF(D98="Default",0,IF(D98="Re-Lease",Inputs!$C$71*Inputs!$C$86,Inputs!$C$73))) -> 561600 | F98: =(Inputs!$C$82*(1+Inputs!$C$83)^7)/12+IF(95=Inputs!$C$68,Inputs!$C$69/12,0) -> 102028.86 | G98: =IF(D98="Expired",0,(IF(Inputs!$C$5=1,(Inputs!C38+Inputs!C39)/12,(Inputs!F38+Inputs!F39)/12)*(1+Inputs!$C$83)^7)) -> 62406.002 | H98: =E98-F98-G98 -> 397165.14 | I98: ='Debt Schedule'!I107 -> 536541.9 | J98: =H98-I98 -> -139376.76 | K98: =IFERROR(H98/I98,"-") -> 0.74023135 | L98: =SUM($J$4:J98) -> -11956998
B99: 96 | C99: =EDATE(DATE(2024,1,1),95) -> 48183 | D99: =IF(96>Inputs!$C$74,"Expired",IF(Inputs!$C$68>0,IF(96<Inputs!$C$68,"Paying",IF(96<Inputs!$C$68+Inputs!$C$85,"Default","Re-Lease")),"Paying")) -> Paying | E99: =IF(D99="Expired",0,IF(D99="Default",0,IF(D99="Re-Lease",Inputs!$C$71*Inputs!$C$86,Inputs!$C$73))) -> 561600 | F99: =(Inputs!$C$82*(1+Inputs!$C$83)^7)/12+IF(96=Inputs!$C$68,Inputs!$C$69/12,0) -> 102028.86 | G99: =IF(D99="Expired",0,(IF(Inputs!$C$5=1,(Inputs!C38+Inputs!C39)/12,(Inputs!F38+Inputs!F39)/12)*(1+Inputs!$C$83)^7)) -> 62406.002 | H99: =E99-F99-G99 -> 397165.14 | I99: ='Debt Schedule'!I108 -> 536541.9 | J99: =H99-I99 -> -139376.76 | K99: =IFERROR(H99/I99,"-") -> 0.74023135 | L99: =SUM($J$4:J99) -> -12096375
B100: 97 | C100: =EDATE(DATE(2024,1,1),96) -> 48214 | D100: =IF(97>Inputs!$C$74,"Expired",IF(Inputs!$C$68>0,IF(97<Inputs!$C$68,"Paying",IF(97<Inputs!$C$68+Inputs!$C$85,"Default","Re-Lease")),"Paying")) -> Paying | E100: =IF(D100="Expired",0,IF(D100="Default",0,IF(D100="Re-Lease",Inputs!$C$71*Inputs!$C$86,Inputs!$C$73))) -> 561600 | F100: =(Inputs!$C$82*(1+Inputs!$C$83)^8)/12+IF(97=Inputs!$C$68,Inputs!$C$69/12,0) -> 104579.58 | G100: =IF(D100="Expired",0,(IF(Inputs!$C$5=1,(Inputs!C38+Inputs!C39)/12,(Inputs!F38+Inputs!F39)/12)*(1+Inputs!$C$83)^8)) -> 63966.152 | H100: =E100-F100-G100 -> 393054.27 | I100: ='Debt Schedule'!I109 -> 536541.9 | J100: =H100-I100 -> -143487.64 | K100: =IFERROR(H100/I100,"-") -> 0.73256956 | L100: =SUM($J$4:J100) -> -12239863
B101: 98 | C101: =EDATE(DATE(2024,1,1),97) -> 48245 | D101: =IF(98>Inputs!$C$74,"Expired",IF(Inputs!$C$68>0,IF(98<Inputs!$C$68,"Paying",IF(98<Inputs!$C$68+Inputs!$C$85,"Default","Re-Lease")),"Paying")) -> Paying | E101: =IF(D101="Expired",0,IF(D101="Default",0,IF(D101="Re-Lease",Inputs!$C$71*Inputs!$C$86,Inputs!$C$73))) -> 561600 | F101: =(Inputs!$C$82*(1+Inputs!$C$83)^8)/12+IF(98=Inputs!$C$68,Inputs!$C$69/12,0) -> 104579.58 | G101: =IF(D101="Expired",0,(IF(Inputs!$C$5=1,(Inputs!C38+Inputs!C39)/12,(Inputs!F38+Inputs!F39)/12)*(1+Inputs!$C$83)^8)) -> 63966.152 | H101: =E101-F101-G101 -> 393054.27 | I101: ='Debt Schedule'!I110 -> 536541.9 | J101: =H101-I101 -> -143487.64 | K101: =IFERROR(H101/I101,"-") -> 0.73256956 | L101: =SUM($J$4:J101) -> -12383350
...

Sheet Cash Flows
A1: AVIATION LEASE CASH FLOW MODEL | Equity Cash Flows & Returns
B3: INITIAL INVESTMENT (Month 0)
B4: Aircraft Purchase Price | C4: =-Inputs!C71 -> -72000000
B5: Equity Contribution (Purchase Price - Loan) | C5: =-(Inputs!C71-Inputs!C76) -> -18000000
B6: Loan Proceeds | C6: =Inputs!C76 -> 54000000
B7: Origination Fee Paid | C7: =-'Debt Schedule'!C9 -> -540000
B8: NET INITIAL EQUITY OUTFLOW | C8: =C5+C7 -> -18540000
B11: OPERATING PERIOD (Lease Term)
B12: Total Lease Revenue Collected | C12: =SUM(Calculations!E4:E148) -> 134784000
B13: Total Operating Expenses | C13: =-SUM(Calculations!F4:F148) -> -28418839
B14: Total Maintenance Reserves | C14: =-SUM(Calculations!G4:G148) -> -14116261
B15: NET OPERATING INCOME (Total) | C15: =SUM(Calculations!H4:H148) -> 92248900
B16: Total Debt Service Paid | C16: =-SUM(Calculations!I4:I148) -> -1.5037006e+08
B17: CASH FLOW AFTER DEBT SERVICE (CFADS) | C17: =SUM(Calculations!J4:J148) -> -58121156
B20: EXIT / RESIDUAL VALUE
B21: Aircraft Book Value at Exit | C21: =Inputs!C71*(1-Inputs!C80)^(Inputs!C74/12) -> 50420324
B22: RV Haircut (Scenario) | C22: =-C21*Inputs!C81 -> -2521016.2
B23: Net Residual Value Received | C23: =C21+C22 -> 47899308
B24: Remaining Loan Balance at Exit | C24: =IFERROR('Debt Schedule'!I156,0) -> 0
B25: NET EXIT EQUITY PROCEEDS | C25: =C23-C24 -> 47899308
B28: RETURNS SUMMARY
B29: Total Equity Invested | C29: =ABS(C8) -> 18540000
B30: Total Equity Returned (CFADS + Exit) | C30: =C17+C25 -> -10221849
B31: MOIC (Multiple of Invested Capital) | C31: =IFERROR(C30/C29,0) -> -0.55134028
B33: IRR CALCULATION
B34: Monthly IRR (XIRR placeholder) | C34: =IFERROR(IRR(irr_cfs,0.005)*12,"N/A") -> N/A
B35: Annualized Equity IRR | C35: =IFERROR((C30/C29)^(12/Inputs!C74)-1,"N/A") -> N/A
B36: Average Annual DSCR | C36: =IFERROR(AVERAGEIF(Calculations!I4:I148,">"&0,Calculations!H4:H148)/AVERAGEIF(Calculations!I4:I148,">"&0,Calculations!I4:I148),"N/A") -> 0.63123496
B37: Min. Monthly DSCR | C37: =IFERROR(_xludf.minifs(Calculations!K4:K148,Calculations!K4:K148,">"&0),"N/A") -> N/A
B38: DSCR Covenant (Min.) | C38: =Inputs!C84 -> 1.25
B39: Covenant Breach? | C39: =IF(ISNUMBER(C37),IF(C37<C38,"YES - BREACH","No"),"Check") -> Check

Sheet Dashboard
A1: ✈ AVIATION LEASE CASH FLOW MODEL | Executive Dashboard
A2: =IFERROR("Deal: "&IF(Inputs!C5=1,"Boeing 737-800 (MSN-28024)","Airbus A320neo (MSN-10458)")&" | Scenario: "&IF(Inputs!C6=1,"Base",IF(Inputs!C6=2,"Upside","Downside"))&" | As of: "&TEXT(TODAY(),"DD-MMM-YYYY"),"") -> Deal: Boeing 737-800 (MSN-28024) | Scenario: Base | As of: 15-Jun-2026
B4: Equity IRR | C4: MOIC | D4: Avg DSCR | E4: Min DSCR | F4: Total CFADS | G4: RV (Net) | H4: Loan Amount | I4: Covenant
B5: =TEXT('Cash Flows'!C35,"0.0%") -> N/A | C5: =TEXT('Cash Flows'!C31,"0.0x") -> -0.6x | D5: =TEXT('Cash Flows'!C36,"0.00x") -> 0.63x | E5: =TEXT('Cash Flows'!C37,"0.00x") -> N/A | F5: =TEXT('Cash Flows'!C17,"$#,##0") -> -$5,81,21,156 | G5: =TEXT('Cash Flows'!C23,"$#,##0") -> $4,78,99,308 | H5: =TEXT(Inputs!C76,"$#,##0") -> $5,40,00,000 | I5: =IF('Cash Flows'!C39="YES - BREACH","BREACH","OK") -> OK
B8: ▶ Change scenario: Inputs!C6 (1=Base, 2=Upside, 3=Downside) | Change deal: Inputs!C5 (1=737-800, 2=A320neo)
B42: IRR SENSITIVITY: Rate vs. Exit Haircut
B43: Rate \ Haircut | C43: 0% | D43: 5% | E43: 10% | F43: 15% | G43: 20%
B44: 5.5% | C44: 0.1405 | D44: 0.1361 | E44: 0.1316 | F44: 0.1269 | G44: 0.122
B45: 6.0%
B46: 6.5% | C46: 0.1309 | D46: 0.1262 | E46: 0.1213 | F46: 0.1162 | G46: 0.1109 | H46: Cum. CFADS | J46: Component | K46: Amount ($)
B47: 7.0% | C47: 0.1259 | D47: 0.121 | E47: 0.1159 | F47: 0.1105 | G47: 0.1049 | H47: =IFERROR(SUM(Calculations!$L$4:L15),0) -> -8835468.3 | J47: Debt | K47: =Inputs!C76 -> 54000000
B48: 7.5% | C48: 0.1206 | D48: 0.1155 | E48: 0.1101 | F48: 0.1045 | G48: 0.0987 | H48: =IFERROR(SUM(Calculations!$L$4:L27),0) -> -34252320 | J48: Equity | K48: =Inputs!C71-Inputs!C76 -> 18000000
B49: 3 | C49: =IFERROR(1*SUM(Calculations!E28:E39),0) -> 6739200 | D49: =IFERROR(-1*SUM(Calculations!F28:F39),0) -> -1082143.8 | E49: =IFERROR(1*SUM(Calculations!H28:H39),0) -> 4995162.5 | F49: =IFERROR(-1*SUM(Calculations!I28:I39),0) -> -6438502.8 | G49: =IFERROR(1*SUM(Calculations!J28:J39),0) -> -1443340.3 | H49: =IFERROR(SUM(Calculations!$L$4:L39),0) -> -76755300
B50: 4 | C50: =IFERROR(1*SUM(Calculations!E40:E51),0) -> 6739200 | D50: =IFERROR(-1*SUM(Calculations!F40:F51),0) -> -1109197.3 | E50: =IFERROR(1*SUM(Calculations!H40:H51),0) -> 4951561.6 | F50: =IFERROR(-1*SUM(Calculations!I40:I51),0) -> -6438502.8 | G50: =IFERROR(1*SUM(Calculations!J40:J51),0) -> -1486941.2 | H50: =IFERROR(SUM(Calculations!$L$4:L51),0) -> -1.3686177e+08
B51: 5 | C51: =IFERROR(1*SUM(Calculations!E52:E63),0) -> 6739200 | D51: =IFERROR(-1*SUM(Calculations!F52:F63),0) -> -1136927.3 | E51: =IFERROR(1*SUM(Calculations!H52:H63),0) -> 4906870.6 | F51: =IFERROR(-1*SUM(Calculations!I52:I63),0) -> -6438502.8 | G51: =IFERROR(1*SUM(Calculations!J52:J63),0) -> -1531632.2 | H51: =IFERROR(SUM(Calculations!$L$4:L63),0) -> -2.1510202e+08
B52: 6 | C52: =IFERROR(1*SUM(Calculations!E64:E75),0) -> 6739200 | D52: =IFERROR(-1*SUM(Calculations!F64:F75),0) -> -1165350.5 | E52: =IFERROR(1*SUM(Calculations!H64:H75),0) -> 4861062.4 | F52: =IFERROR(-1*SUM(Calculations!I64:I75),0) -> -6438502.8 | G52: =IFERROR(1*SUM(Calculations!J64:J75),0) -> -1577440.4 | H52: =IFERROR(SUM(Calculations!$L$4:L75),0) -> -3.1201962e+08
B53: 7 | C53: =IFERROR(1*SUM(Calculations!E76:E87),0) -> 6739200 | D53: =IFERROR(-1*SUM(Calculations!F76:F87),0) -> -1194484.2 | E53: =IFERROR(1*SUM(Calculations!H76:H87),0) -> 4814108.9 | F53: =IFERROR(-1*SUM(Calculations!I76:I87),0) -> -6438502.8 | G53: =IFERROR(1*SUM(Calculations!J76:J87),0) -> -1624393.9 | H53: =IFERROR(SUM(Calculations!$L$4:L87),0) -> -4.281717e+08
B54: 8 | C54: =IFERROR(1*SUM(Calculations!E88:E99),0) -> 6739200 | D54: =IFERROR(-1*SUM(Calculations!F88:F99),0) -> -1224346.3 | E54: =IFERROR(1*SUM(Calculations!H88:H99),0) -> 4765981.6 | F54: =IFERROR(-1*SUM(Calculations!I88:I99),0) -> -6438502.8 | G54: =IFERROR(1*SUM(Calculations!J88:J99),0) -> -1672521.2 | H54: =IFERROR(SUM(Calculations!$L$4:L99),0) -> -5.6412933e+08
B55: 9 | C55: =IFERROR(1*SUM(Calculations!E100:E111),0) -> 6739200 | D55: =IFERROR(-1*SUM(Calculations!F100:F111),0) -> -1254955 | E55: =IFERROR(1*SUM(Calculations!H100:H111),0) -> 4716651.2 | F55: =IFERROR(-1*SUM(Calculations!I100:I111),0) -> -6438502.8 | G55: =IFERROR(1*SUM(Calculations!J100:J111),0) -> -1721851.6 | H55: =IFERROR(SUM(Calculations!$L$4:L111),0) -> -7.2047787e+08
B56: 10 | C56: =IFERROR(1*SUM(Calculations!E112:E123),0) -> 6739200 | D56: =IFERROR(-1*SUM(Calculations!F112:F123),0) -> -1286328.9 | E56: =IFERROR(1*SUM(Calculations!H112:H123),0) -> 4666087.5 | F56: =IFERROR(-1*SUM(Calculations!I112:I123),0) -> -17238503 | G56: =IFERROR(1*SUM(Calculations!J112:J123),0) -> -12572415 | H56: =IFERROR(SUM(Calculations!$L$4:L123),0) -> -9.0861728e+08
B57: 11 | C57: =IFERROR(1*SUM(Calculations!E124:E135),0) -> 0 | D57: =IFERROR(-1*SUM(Calculations!F124:F135),0) -> -1318487.1 | E57: =IFERROR(1*SUM(Calculations!H124:H135),0) -> -1318487.1 | F57: =IFERROR(-1*SUM(Calculations!I124:I135),0) -> 0 | G57: =IFERROR(1*SUM(Calculations!J124:J135),0) -> -1318487.1 | H57: =IFERROR(SUM(Calculations!$L$4:L135),0) -> -1.2338752e+09
B58: 12 | C58: =IFERROR(1*SUM(Calculations!E136:E147),0) -> 0 | D58: =IFERROR(-1*SUM(Calculations!F136:F147),0) -> -1351449.3 | E58: =IFERROR(1*SUM(Calculations!H136:H147),0) -> -1351449.3 | F58: =IFERROR(-1*SUM(Calculations!I136:I147),0) -> 0 | G58: =IFERROR(1*SUM(Calculations!J136:J147),0) -> -1351449.3 | H58: =IFERROR(SUM(Calculations!$L$4:L147),0) -> -1.5751691e+09

Sheet Python_Reference
A1: PYTHON EQUIVALENT MODEL LOGIC (Reference Only — Not a Working Script)
B2: import pandas as pd
B3: import numpy as np
B4: import numpy_financial as npf
B6: # ── INPUTS ──
B7: purchase_price = 72_000_000 # Boeing 737-800
B8: lrf = 0.0078 # Lease Rate Factor (monthly)
B9: lease_term = 120 # months
B10: ltv = 0.75
B11: loan = purchase_price * ltv
B12: annual_rate = 0.055
B13: monthly_rate = annual_rate / 12
B14: amort_months = 120
... B78: print(f'Min DSCR: {df_cf["dscr"].min():.2f}x')
